[
  {
    "studentRegister": 29,
    "studentAccepted": 0,
    "maxRegister": 60,
    "maxAcceptedStudent": 20,
    "timestamp": 1744857881
  },
  {
    "studentRegister": 41,
    "studentAccepted": 0,
    "maxRegister": 60,
    "maxAcceptedStudent": 20,
    "timestamp": 1744860367
  },
  {
    "studentRegister": 44,
    "studentAccepted": 0,
    "maxRegister": 60,
    "maxAcceptedStudent": 20,
    "timestamp": 1744861721
  },
  {
    "studentRegister": 44,
    "studentAccepted": 0,
    "maxRegister": 60,
    "maxAcceptedStudent": 20,
    "timestamp": 1744862241
  },
  {
    "studentRegister": 48,
    "studentAccepted": 0,
    "maxRegister": 60,
    "maxAcceptedStudent": 20,
    "timestamp": 1744863477
  },
  {
    "studentRegister": 53,
    "studentAccepted": 0,
    "maxRegister": 60,
    "maxAcceptedStudent": 20,
    "timestamp": 1744864751
  },
  {
    "studentRegister": 56,
    "studentAccepted": 0,
    "maxRegister": 60,
    "maxAcceptedStudent": 20,
    "timestamp": 1744865396
  },
  {
    "studentRegister": 56,
    "studentAccepted": 0,
    "maxRegister": 60,
    "maxAcceptedStudent": 20,
    "timestamp": 1744865809
  },
  {
    "studentRegister": 60,
    "studentAccepted": 0,
    "maxRegister": 60,
    "maxAcceptedStudent": 20,
    "timestamp": 1744866848
  },
  {
    "studentRegister": 60,
    "studentAccepted": 0,
    "maxRegister": 60,
    "maxAcceptedStudent": 20,
    "timestamp": 1744867978
  },
  {
    "studentRegister": 60,
    "studentAccepted": 0,
    "maxRegister": 60,
    "maxAcceptedStudent": 20,
    "timestamp": 1744868614
  },
  {
    "studentRegister": 60,
    "studentAccepted": 0,
    "maxRegister": 60,
    "maxAcceptedStudent": 20,
    "timestamp": 1744869014
  },
  {
    "studentRegister": 60,
    "studentAccepted": 0,
    "maxRegister": 60,
    "maxAcceptedStudent": 20,
    "timestamp": 1744869419
  },
  {
    "studentRegister": 60,
    "studentAccepted": 0,
    "maxRegister": 60,
    "maxAcceptedStudent": 20,
    "timestamp": 1744870823
  },
  {
    "studentRegister": 60,
    "studentAccepted": 0,
    "maxRegister": 60,
    "maxAcceptedStudent": 20,
    "timestamp": 1744872237
  },
  {
    "studentRegister": 60,
    "studentAccepted": 0,
    "maxRegister": 60,
    "maxAcceptedStudent": 20,
    "timestamp": 1744872820
  },
  {
    "studentRegister": 60,
    "studentAccepted": 0,
    "maxRegister": 60,
    "maxAcceptedStudent": 20,
    "timestamp": 1744873228
  },
  {
    "studentRegister": 60,
    "studentAccepted": 0,
    "maxRegister": 60,
    "maxAcceptedStudent": 20,
    "timestamp": 1744874552
  },
  {
    "studentRegister": 60,
    "studentAccepted": 0,
    "maxRegister": 60,
    "maxAcceptedStudent": 20,
    "timestamp": 1744875316
  },
  {
    "studentRegister": 60,
    "studentAccepted": 0,
    "maxRegister": 60,
    "maxAcceptedStudent": 20,
    "timestamp": 1744875848
  },
  {
    "studentRegister": 60,
    "studentAccepted": 0,
    "maxRegister": 60,
    "maxAcceptedStudent": 20,
    "timestamp": 1744876248
  },
  {
    "studentRegister": 60,
    "studentAccepted": 0,
    "maxRegister": 60,
    "maxAcceptedStudent": 20,
    "timestamp": 1744876639
  },
  {
    "studentRegister": 60,
    "studentAccepted": 0,
    "maxRegister": 60,
    "maxAcceptedStudent": 20,
    "timestamp": 1744878033
  },
  {
    "studentRegister": 60,
    "studentAccepted": 0,
    "maxRegister": 60,
    "maxAcceptedStudent": 20,
    "timestamp": 1744879300
  },
  {
    "studentRegister": 60,
    "studentAccepted": 0,
    "maxRegister": 60,
    "maxAcceptedStudent": 20,
    "timestamp": 1744880009
  },
  {
    "studentRegister": 60,
    "studentAccepted": 0,
    "maxRegister": 60,
    "maxAcceptedStudent": 20,
    "timestamp": 1744880404
  },
  {
    "studentRegister": 60,
    "studentAccepted": 0,
    "maxRegister": 60,
    "maxAcceptedStudent": 20,
    "timestamp": 1744881811
  },
  {
    "studentRegister": 60,
    "studentAccepted": 0,
    "maxRegister": 60,
    "maxAcceptedStudent": 20,
    "timestamp": 1744883112
  },
  {
    "studentRegister": 60,
    "studentAccepted": 0,
    "maxRegister": 60,
    "maxAcceptedStudent": 20,
    "timestamp": 1744883517
  },
  {
    "studentRegister": 60,
    "studentAccepted": 0,
    "maxRegister": 60,
    "maxAcceptedStudent": 20,
    "timestamp": 1744883923
  },
  {
    "studentRegister": 60,
    "studentAccepted": 0,
    "maxRegister": 60,
    "maxAcceptedStudent": 20,
    "timestamp": 1744885158
  },
  {
    "studentRegister": 60,
    "studentAccepted": 0,
    "maxRegister": 60,
    "maxAcceptedStudent": 20,
    "timestamp": 1744886411
  },
  {
    "studentRegister": 60,
    "studentAccepted": 0,
    "maxRegister": 60,
    "maxAcceptedStudent": 20,
    "timestamp": 1744886949
  },
  {
    "studentRegister": 60,
    "studentAccepted": 0,
    "maxRegister": 60,
    "maxAcceptedStudent": 20,
    "timestamp": 1744887350
  },
  {
    "studentRegister": 60,
    "studentAccepted": 0,
    "maxRegister": 60,
    "maxAcceptedStudent": 20,
    "timestamp": 1744888201
  },
  {
    "studentRegister": 60,
    "studentAccepted": 0,
    "maxRegister": 60,
    "maxAcceptedStudent": 20,
    "timestamp": 1744889062
  },
  {
    "studentRegister": 60,
    "studentAccepted": 0,
    "maxRegister": 60,
    "maxAcceptedStudent": 20,
    "timestamp": 1744889506
  },
  {
    "studentRegister": 60,
    "studentAccepted": 0,
    "maxRegister": 60,
    "maxAcceptedStudent": 20,
    "timestamp": 1744890056
  },
  {
    "studentRegister": 60,
    "studentAccepted": 0,
    "maxRegister": 60,
    "maxAcceptedStudent": 20,
    "timestamp": 1744890451
  },
  {
    "studentRegister": 60,
    "studentAccepted": 0,
    "maxRegister": 60,
    "maxAcceptedStudent": 20,
    "timestamp": 1744890859
  },
  {
    "studentRegister": 60,
    "studentAccepted": 0,
    "maxRegister": 60,
    "maxAcceptedStudent": 20,
    "timestamp": 1744892121
  },
  {
    "studentRegister": 60,
    "studentAccepted": 0,
    "maxRegister": 60,
    "maxAcceptedStudent": 20,
    "timestamp": 1744894579
  },
  {
    "studentRegister": 60,
    "studentAccepted": 0,
    "maxRegister": 60,
    "maxAcceptedStudent": 20,
    "timestamp": 1744896186
  },
  {
    "studentRegister": 60,
    "studentAccepted": 0,
    "maxRegister": 60,
    "maxAcceptedStudent": 20,
    "timestamp": 1744897266
  },
  {
    "studentRegister": 60,
    "studentAccepted": 0,
    "maxRegister": 60,
    "maxAcceptedStudent": 20,
    "timestamp": 1744897732
  },
  {
    "studentRegister": 60,
    "studentAccepted": 0,
    "maxRegister": 60,
    "maxAcceptedStudent": 20,
    "timestamp": 1744898133
  },
  {
    "studentRegister": 60,
    "studentAccepted": 0,
    "maxRegister": 60,
    "maxAcceptedStudent": 20,
    "timestamp": 1744899084
  },
  {
    "studentRegister": 60,
    "studentAccepted": 0,
    "maxRegister": 60,
    "maxAcceptedStudent": 20,
    "timestamp": 1744900327
  },
  {
    "studentRegister": 60,
    "studentAccepted": 0,
    "maxRegister": 60,
    "maxAcceptedStudent": 20,
    "timestamp": 1744901069
  },
  {
    "studentRegister": 60,
    "studentAccepted": 0,
    "maxRegister": 60,
    "maxAcceptedStudent": 20,
    "timestamp": 1744901486
  },
  {
    "studentRegister": 60,
    "studentAccepted": 0,
    "maxRegister": 60,
    "maxAcceptedStudent": 20,
    "timestamp": 1744901901
  },
  {
    "studentRegister": 60,
    "studentAccepted": 0,
    "maxRegister": 60,
    "maxAcceptedStudent": 20,
    "timestamp": 1744903070
  },
  {
    "studentRegister": 60,
    "studentAccepted": 0,
    "maxRegister": 60,
    "maxAcceptedStudent": 20,
    "timestamp": 1744904013
  },
  {
    "studentRegister": 60,
    "studentAccepted": 0,
    "maxRegister": 60,
    "maxAcceptedStudent": 20,
    "timestamp": 1744904641
  },
  {
    "studentRegister": 60,
    "studentAccepted": 0,
    "maxRegister": 60,
    "maxAcceptedStudent": 20,
    "timestamp": 1744905050
  },
  {
    "studentRegister": 60,
    "studentAccepted": 0,
    "maxRegister": 60,
    "maxAcceptedStudent": 20,
    "timestamp": 1744905465
  },
  {
    "studentRegister": 60,
    "studentAccepted": 0,
    "maxRegister": 60,
    "maxAcceptedStudent": 20,
    "timestamp": 1744906904
  },
  {
    "studentRegister": 60,
    "studentAccepted": 0,
    "maxRegister": 60,
    "maxAcceptedStudent": 20,
    "timestamp": 1744908197
  },
  {
    "studentRegister": 60,
    "studentAccepted": 0,
    "maxRegister": 60,
    "maxAcceptedStudent": 20,
    "timestamp": 1744908881
  },
  {
    "studentRegister": 60,
    "studentAccepted": 0,
    "maxRegister": 60,
    "maxAcceptedStudent": 20,
    "timestamp": 1744909694
  },
  {
    "studentRegister": 60,
    "studentAccepted": 0,
    "maxRegister": 60,
    "maxAcceptedStudent": 20,
    "timestamp": 1744910928
  },
  {
    "studentRegister": 60,
    "studentAccepted": 0,
    "maxRegister": 60,
    "maxAcceptedStudent": 20,
    "timestamp": 1744911593
  },
  {
    "studentRegister": 60,
    "studentAccepted": 0,
    "maxRegister": 60,
    "maxAcceptedStudent": 20,
    "timestamp": 1744911998
  },
  {
    "studentRegister": 60,
    "studentAccepted": 0,
    "maxRegister": 60,
    "maxAcceptedStudent": 20,
    "timestamp": 1744912393
  },
  {
    "studentRegister": 60,
    "studentAccepted": 0,
    "maxRegister": 60,
    "maxAcceptedStudent": 20,
    "timestamp": 1744912798
  },
  {
    "studentRegister": 60,
    "studentAccepted": 0,
    "maxRegister": 60,
    "maxAcceptedStudent": 20,
    "timestamp": 1744914513
  },
  {
    "studentRegister": 60,
    "studentAccepted": 0,
    "maxRegister": 60,
    "maxAcceptedStudent": 20,
    "timestamp": 1744915605
  },
  {
    "studentRegister": 60,
    "studentAccepted": 0,
    "maxRegister": 60,
    "maxAcceptedStudent": 20,
    "timestamp": 1744916060
  },
  {
    "studentRegister": 60,
    "studentAccepted": 0,
    "maxRegister": 60,
    "maxAcceptedStudent": 20,
    "timestamp": 1744916828
  },
  {
    "studentRegister": 60,
    "studentAccepted": 0,
    "maxRegister": 60,
    "maxAcceptedStudent": 20,
    "timestamp": 1744917707
  },
  {
    "studentRegister": 60,
    "studentAccepted": 0,
    "maxRegister": 60,
    "maxAcceptedStudent": 20,
    "timestamp": 1744918118
  },
  {
    "studentRegister": 60,
    "studentAccepted": 0,
    "maxRegister": 60,
    "maxAcceptedStudent": 20,
    "timestamp": 1744918637
  },
  {
    "studentRegister": 60,
    "studentAccepted": 0,
    "maxRegister": 60,
    "maxAcceptedStudent": 20,
    "timestamp": 1744919039
  },
  {
    "studentRegister": 60,
    "studentAccepted": 0,
    "maxRegister": 60,
    "maxAcceptedStudent": 20,
    "timestamp": 1744919429
  },
  {
    "studentRegister": 60,
    "studentAccepted": 0,
    "maxRegister": 60,
    "maxAcceptedStudent": 20,
    "timestamp": 1744919838
  },
  {
    "studentRegister": 60,
    "studentAccepted": 0,
    "maxRegister": 60,
    "maxAcceptedStudent": 20,
    "timestamp": 1744920974
  },
  {
    "studentRegister": 60,
    "studentAccepted": 0,
    "maxRegister": 60,
    "maxAcceptedStudent": 20,
    "timestamp": 1744921946
  },
  {
    "studentRegister": 60,
    "studentAccepted": 0,
    "maxRegister": 60,
    "maxAcceptedStudent": 20,
    "timestamp": 1744922589
  },
  {
    "studentRegister": 60,
    "studentAccepted": 0,
    "maxRegister": 60,
    "maxAcceptedStudent": 20,
    "timestamp": 1744922998
  },
  {
    "studentRegister": 60,
    "studentAccepted": 0,
    "maxRegister": 60,
    "maxAcceptedStudent": 20,
    "timestamp": 1744923396
  },
  {
    "studentRegister": 60,
    "studentAccepted": 0,
    "maxRegister": 60,
    "maxAcceptedStudent": 20,
    "timestamp": 1744924355
  },
  {
    "studentRegister": 60,
    "studentAccepted": 0,
    "maxRegister": 60,
    "maxAcceptedStudent": 20,
    "timestamp": 1744925229
  },
  {
    "studentRegister": 60,
    "studentAccepted": 0,
    "maxRegister": 60,
    "maxAcceptedStudent": 20,
    "timestamp": 1744925802
  },
  {
    "studentRegister": 60,
    "studentAccepted": 0,
    "maxRegister": 60,
    "maxAcceptedStudent": 20,
    "timestamp": 1744926191
  },
  {
    "studentRegister": 60,
    "studentAccepted": 0,
    "maxRegister": 60,
    "maxAcceptedStudent": 20,
    "timestamp": 1744926599
  },
  {
    "studentRegister": 60,
    "studentAccepted": 0,
    "maxRegister": 60,
    "maxAcceptedStudent": 20,
    "timestamp": 1744927004
  },
  {
    "studentRegister": 60,
    "studentAccepted": 0,
    "maxRegister": 60,
    "maxAcceptedStudent": 20,
    "timestamp": 1744927971
  },
  {
    "studentRegister": 60,
    "studentAccepted": 0,
    "maxRegister": 60,
    "maxAcceptedStudent": 20,
    "timestamp": 1744929095
  },
  {
    "studentRegister": 60,
    "studentAccepted": 0,
    "maxRegister": 60,
    "maxAcceptedStudent": 20,
    "timestamp": 1744929765
  },
  {
    "studentRegister": 60,
    "studentAccepted": 0,
    "maxRegister": 60,
    "maxAcceptedStudent": 20,
    "timestamp": 1744930157
  },
  {
    "studentRegister": 60,
    "studentAccepted": 0,
    "maxRegister": 60,
    "maxAcceptedStudent": 20,
    "timestamp": 1744930567
  },
  {
    "studentRegister": 60,
    "studentAccepted": 0,
    "maxRegister": 60,
    "maxAcceptedStudent": 20,
    "timestamp": 1744931513
  },
  {
    "studentRegister": 60,
    "studentAccepted": 0,
    "maxRegister": 60,
    "maxAcceptedStudent": 20,
    "timestamp": 1744932472
  },
  {
    "studentRegister": 60,
    "studentAccepted": 0,
    "maxRegister": 60,
    "maxAcceptedStudent": 20,
    "timestamp": 1744933055
  },
  {
    "studentRegister": 60,
    "studentAccepted": 0,
    "maxRegister": 60,
    "maxAcceptedStudent": 20,
    "timestamp": 1744933460
  },
  {
    "studentRegister": 60,
    "studentAccepted": 0,
    "maxRegister": 60,
    "maxAcceptedStudent": 20,
    "timestamp": 1744933870
  },
  {
    "studentRegister": 60,
    "studentAccepted": 0,
    "maxRegister": 60,
    "maxAcceptedStudent": 20,
    "timestamp": 1744934279
  },
  {
    "studentRegister": 60,
    "studentAccepted": 0,
    "maxRegister": 60,
    "maxAcceptedStudent": 20,
    "timestamp": 1744938964
  },
  {
    "studentRegister": 60,
    "studentAccepted": 0,
    "maxRegister": 60,
    "maxAcceptedStudent": 20,
    "timestamp": 1744943997
  },
  {
    "studentRegister": 60,
    "studentAccepted": 0,
    "maxRegister": 60,
    "maxAcceptedStudent": 20,
    "timestamp": 1744946538
  },
  {
    "studentRegister": 60,
    "studentAccepted": 0,
    "maxRegister": 60,
    "maxAcceptedStudent": 20,
    "timestamp": 1744947943
  },
  {
    "studentRegister": 60,
    "studentAccepted": 0,
    "maxRegister": 60,
    "maxAcceptedStudent": 20,
    "timestamp": 1744948514
  },
  {
    "studentRegister": 60,
    "studentAccepted": 0,
    "maxRegister": 60,
    "maxAcceptedStudent": 20,
    "timestamp": 1744949570
  },
  {
    "studentRegister": 60,
    "studentAccepted": 0,
    "maxRegister": 60,
    "maxAcceptedStudent": 20,
    "timestamp": 1744950913
  },
  {
    "studentRegister": 60,
    "studentAccepted": 0,
    "maxRegister": 60,
    "maxAcceptedStudent": 20,
    "timestamp": 1744951705
  },
  {
    "studentRegister": 60,
    "studentAccepted": 0,
    "maxRegister": 60,
    "maxAcceptedStudent": 20,
    "timestamp": 1744952129
  },
  {
    "studentRegister": 60,
    "studentAccepted": 0,
    "maxRegister": 60,
    "maxAcceptedStudent": 20,
    "timestamp": 1744953098
  },
  {
    "studentRegister": 60,
    "studentAccepted": 0,
    "maxRegister": 60,
    "maxAcceptedStudent": 20,
    "timestamp": 1744954308
  },
  {
    "studentRegister": 60,
    "studentAccepted": 0,
    "maxRegister": 60,
    "maxAcceptedStudent": 20,
    "timestamp": 1744954974
  },
  {
    "studentRegister": 60,
    "studentAccepted": 0,
    "maxRegister": 60,
    "maxAcceptedStudent": 20,
    "timestamp": 1744955381
  },
  {
    "studentRegister": 60,
    "studentAccepted": 0,
    "maxRegister": 60,
    "maxAcceptedStudent": 20,
    "timestamp": 1744955785
  },
  {
    "studentRegister": 60,
    "studentAccepted": 0,
    "maxRegister": 60,
    "maxAcceptedStudent": 20,
    "timestamp": 1744957121
  },
  {
    "studentRegister": 60,
    "studentAccepted": 0,
    "maxRegister": 60,
    "maxAcceptedStudent": 20,
    "timestamp": 1744958585
  },
  {
    "studentRegister": 60,
    "studentAccepted": 0,
    "maxRegister": 60,
    "maxAcceptedStudent": 20,
    "timestamp": 1744959197
  },
  {
    "studentRegister": 60,
    "studentAccepted": 0,
    "maxRegister": 60,
    "maxAcceptedStudent": 20,
    "timestamp": 1744959588
  },
  {
    "studentRegister": 60,
    "studentAccepted": 0,
    "maxRegister": 60,
    "maxAcceptedStudent": 20,
    "timestamp": 1744960811
  },
  {
    "studentRegister": 60,
    "studentAccepted": 0,
    "maxRegister": 60,
    "maxAcceptedStudent": 20,
    "timestamp": 1744961556
  },
  {
    "studentRegister": 60,
    "studentAccepted": 0,
    "maxRegister": 60,
    "maxAcceptedStudent": 20,
    "timestamp": 1744962083
  },
  {
    "studentRegister": 60,
    "studentAccepted": 0,
    "maxRegister": 60,
    "maxAcceptedStudent": 20,
    "timestamp": 1744962490
  },
  {
    "studentRegister": 60,
    "studentAccepted": 0,
    "maxRegister": 60,
    "maxAcceptedStudent": 20,
    "timestamp": 1744962899
  },
  {
    "studentRegister": 60,
    "studentAccepted": 0,
    "maxRegister": 60,
    "maxAcceptedStudent": 20,
    "timestamp": 1744963993
  },
  {
    "studentRegister": 60,
    "studentAccepted": 0,
    "maxRegister": 60,
    "maxAcceptedStudent": 20,
    "timestamp": 1744965306
  },
  {
    "studentRegister": 60,
    "studentAccepted": 0,
    "maxRegister": 60,
    "maxAcceptedStudent": 20,
    "timestamp": 1744966107
  },
  {
    "studentRegister": 60,
    "studentAccepted": 0,
    "maxRegister": 60,
    "maxAcceptedStudent": 20,
    "timestamp": 1744966524
  },
  {
    "studentRegister": 60,
    "studentAccepted": 0,
    "maxRegister": 60,
    "maxAcceptedStudent": 20,
    "timestamp": 1744967495
  },
  {
    "studentRegister": 60,
    "studentAccepted": 0,
    "maxRegister": 60,
    "maxAcceptedStudent": 20,
    "timestamp": 1744968648
  },
  {
    "studentRegister": 59,
    "studentAccepted": 0,
    "maxRegister": 60,
    "maxAcceptedStudent": 20,
    "timestamp": 1744969308
  },
  {
    "studentRegister": 60,
    "studentAccepted": 0,
    "maxRegister": 60,
    "maxAcceptedStudent": 20,
    "timestamp": 1744969712
  },
  {
    "studentRegister": 60,
    "studentAccepted": 0,
    "maxRegister": 60,
    "maxAcceptedStudent": 20,
    "timestamp": 1744970123
  },
  {
    "studentRegister": 60,
    "studentAccepted": 0,
    "maxRegister": 60,
    "maxAcceptedStudent": 20,
    "timestamp": 1744971087
  },
  {
    "studentRegister": 60,
    "studentAccepted": 0,
    "maxRegister": 60,
    "maxAcceptedStudent": 20,
    "timestamp": 1744972528
  },
  {
    "studentRegister": 60,
    "studentAccepted": 0,
    "maxRegister": 60,
    "maxAcceptedStudent": 20,
    "timestamp": 1744973279
  },
  {
    "studentRegister": 60,
    "studentAccepted": 0,
    "maxRegister": 60,
    "maxAcceptedStudent": 20,
    "timestamp": 1744973696
  },
  {
    "studentRegister": 60,
    "studentAccepted": 0,
    "maxRegister": 60,
    "maxAcceptedStudent": 20,
    "timestamp": 1744974485
  },
  {
    "studentRegister": 60,
    "studentAccepted": 0,
    "maxRegister": 60,
    "maxAcceptedStudent": 20,
    "timestamp": 1744975373
  },
  {
    "studentRegister": 60,
    "studentAccepted": 0,
    "maxRegister": 60,
    "maxAcceptedStudent": 20,
    "timestamp": 1744975771
  },
  {
    "studentRegister": 60,
    "studentAccepted": 0,
    "maxRegister": 60,
    "maxAcceptedStudent": 20,
    "timestamp": 1744976284
  },
  {
    "studentRegister": 60,
    "studentAccepted": 0,
    "maxRegister": 60,
    "maxAcceptedStudent": 20,
    "timestamp": 1744976685
  },
  {
    "studentRegister": 60,
    "studentAccepted": 0,
    "maxRegister": 60,
    "maxAcceptedStudent": 20,
    "timestamp": 1744977096
  },
  {
    "studentRegister": 60,
    "studentAccepted": 0,
    "maxRegister": 60,
    "maxAcceptedStudent": 20,
    "timestamp": 1744977483
  },
  {
    "studentRegister": 60,
    "studentAccepted": 0,
    "maxRegister": 60,
    "maxAcceptedStudent": 20,
    "timestamp": 1744979505
  },
  {
    "studentRegister": 60,
    "studentAccepted": 0,
    "maxRegister": 60,
    "maxAcceptedStudent": 20,
    "timestamp": 1744981349
  },
  {
    "studentRegister": 60,
    "studentAccepted": 0,
    "maxRegister": 60,
    "maxAcceptedStudent": 20,
    "timestamp": 1744983057
  },
  {
    "studentRegister": 60,
    "studentAccepted": 0,
    "maxRegister": 60,
    "maxAcceptedStudent": 20,
    "timestamp": 1744983753
  },
  {
    "studentRegister": 60,
    "studentAccepted": 0,
    "maxRegister": 60,
    "maxAcceptedStudent": 20,
    "timestamp": 1744984165
  },
  {
    "studentRegister": 60,
    "studentAccepted": 0,
    "maxRegister": 60,
    "maxAcceptedStudent": 20,
    "timestamp": 1744984562
  },
  {
    "studentRegister": 60,
    "studentAccepted": 0,
    "maxRegister": 60,
    "maxAcceptedStudent": 20,
    "timestamp": 1744985477
  },
  {
    "studentRegister": 60,
    "studentAccepted": 0,
    "maxRegister": 60,
    "maxAcceptedStudent": 20,
    "timestamp": 1744986643
  },
  {
    "studentRegister": 60,
    "studentAccepted": 0,
    "maxRegister": 60,
    "maxAcceptedStudent": 20,
    "timestamp": 1744987307
  },
  {
    "studentRegister": 60,
    "studentAccepted": 0,
    "maxRegister": 60,
    "maxAcceptedStudent": 20,
    "timestamp": 1744987721
  },
  {
    "studentRegister": 60,
    "studentAccepted": 0,
    "maxRegister": 60,
    "maxAcceptedStudent": 20,
    "timestamp": 1744988135
  },
  {
    "studentRegister": 60,
    "studentAccepted": 0,
    "maxRegister": 60,
    "maxAcceptedStudent": 20,
    "timestamp": 1744989084
  },
  {
    "studentRegister": 60,
    "studentAccepted": 0,
    "maxRegister": 60,
    "maxAcceptedStudent": 20,
    "timestamp": 1744990183
  },
  {
    "studentRegister": 60,
    "studentAccepted": 0,
    "maxRegister": 60,
    "maxAcceptedStudent": 20,
    "timestamp": 1744990832
  },
  {
    "studentRegister": 60,
    "studentAccepted": 0,
    "maxRegister": 60,
    "maxAcceptedStudent": 20,
    "timestamp": 1744991231
  },
  {
    "studentRegister": 60,
    "studentAccepted": 0,
    "maxRegister": 60,
    "maxAcceptedStudent": 20,
    "timestamp": 1744991650
  },
  {
    "studentRegister": 60,
    "studentAccepted": 0,
    "maxRegister": 60,
    "maxAcceptedStudent": 20,
    "timestamp": 1744992591
  },
  {
    "studentRegister": 60,
    "studentAccepted": 0,
    "maxRegister": 60,
    "maxAcceptedStudent": 20,
    "timestamp": 1744994052
  },
  {
    "studentRegister": 60,
    "studentAccepted": 0,
    "maxRegister": 60,
    "maxAcceptedStudent": 20,
    "timestamp": 1744994774
  },
  {
    "studentRegister": 60,
    "studentAccepted": 0,
    "maxRegister": 60,
    "maxAcceptedStudent": 20,
    "timestamp": 1744995249
  },
  {
    "studentRegister": 60,
    "studentAccepted": 0,
    "maxRegister": 60,
    "maxAcceptedStudent": 20,
    "timestamp": 1744996045
  },
  {
    "studentRegister": 60,
    "studentAccepted": 0,
    "maxRegister": 60,
    "maxAcceptedStudent": 20,
    "timestamp": 1744997203
  },
  {
    "studentRegister": 60,
    "studentAccepted": 0,
    "maxRegister": 60,
    "maxAcceptedStudent": 20,
    "timestamp": 1744997863
  },
  {
    "studentRegister": 60,
    "studentAccepted": 0,
    "maxRegister": 60,
    "maxAcceptedStudent": 20,
    "timestamp": 1744998266
  },
  {
    "studentRegister": 60,
    "studentAccepted": 0,
    "maxRegister": 60,
    "maxAcceptedStudent": 20,
    "timestamp": 1744998686
  },
  {
    "studentRegister": 60,
    "studentAccepted": 0,
    "maxRegister": 60,
    "maxAcceptedStudent": 20,
    "timestamp": 1744999075
  },
  {
    "studentRegister": 60,
    "studentAccepted": 0,
    "maxRegister": 60,
    "maxAcceptedStudent": 20,
    "timestamp": 1745000481
  },
  {
    "studentRegister": 60,
    "studentAccepted": 0,
    "maxRegister": 60,
    "maxAcceptedStudent": 20,
    "timestamp": 1745001702
  },
  {
    "studentRegister": 60,
    "studentAccepted": 0,
    "maxRegister": 60,
    "maxAcceptedStudent": 20,
    "timestamp": 1745002318
  },
  {
    "studentRegister": 60,
    "studentAccepted": 0,
    "maxRegister": 60,
    "maxAcceptedStudent": 20,
    "timestamp": 1745002731
  },
  {
    "studentRegister": 60,
    "studentAccepted": 0,
    "maxRegister": 60,
    "maxAcceptedStudent": 20,
    "timestamp": 1745003674
  },
  {
    "studentRegister": 60,
    "studentAccepted": 0,
    "maxRegister": 60,
    "maxAcceptedStudent": 20,
    "timestamp": 1745004280
  },
  {
    "studentRegister": 60,
    "studentAccepted": 0,
    "maxRegister": 60,
    "maxAcceptedStudent": 20,
    "timestamp": 1745004710
  },
  {
    "studentRegister": 60,
    "studentAccepted": 0,
    "maxRegister": 60,
    "maxAcceptedStudent": 20,
    "timestamp": 1745005199
  },
  {
    "studentRegister": 60,
    "studentAccepted": 0,
    "maxRegister": 60,
    "maxAcceptedStudent": 20,
    "timestamp": 1745005594
  },
  {
    "studentRegister": 60,
    "studentAccepted": 0,
    "maxRegister": 60,
    "maxAcceptedStudent": 20,
    "timestamp": 1745005975
  },
  {
    "studentRegister": 60,
    "studentAccepted": 0,
    "maxRegister": 60,
    "maxAcceptedStudent": 20,
    "timestamp": 1745006375
  },
  {
    "studentRegister": 60,
    "studentAccepted": 0,
    "maxRegister": 60,
    "maxAcceptedStudent": 20,
    "timestamp": 1745007647
  },
  {
    "studentRegister": 60,
    "studentAccepted": 0,
    "maxRegister": 60,
    "maxAcceptedStudent": 20,
    "timestamp": 1745008435
  },
  {
    "studentRegister": 60,
    "studentAccepted": 0,
    "maxRegister": 60,
    "maxAcceptedStudent": 20,
    "timestamp": 1745008979
  },
  {
    "studentRegister": 60,
    "studentAccepted": 0,
    "maxRegister": 60,
    "maxAcceptedStudent": 20,
    "timestamp": 1745009386
  },
  {
    "studentRegister": 60,
    "studentAccepted": 0,
    "maxRegister": 60,
    "maxAcceptedStudent": 20,
    "timestamp": 1745009796
  },
  {
    "studentRegister": 60,
    "studentAccepted": 0,
    "maxRegister": 60,
    "maxAcceptedStudent": 20,
    "timestamp": 1745010719
  },
  {
    "studentRegister": 60,
    "studentAccepted": 0,
    "maxRegister": 60,
    "maxAcceptedStudent": 20,
    "timestamp": 1745011671
  },
  {
    "studentRegister": 60,
    "studentAccepted": 0,
    "maxRegister": 60,
    "maxAcceptedStudent": 20,
    "timestamp": 1745012185
  },
  {
    "studentRegister": 60,
    "studentAccepted": 0,
    "maxRegister": 60,
    "maxAcceptedStudent": 20,
    "timestamp": 1745012593
  },
  {
    "studentRegister": 60,
    "studentAccepted": 0,
    "maxRegister": 60,
    "maxAcceptedStudent": 20,
    "timestamp": 1745013012
  },
  {
    "studentRegister": 60,
    "studentAccepted": 0,
    "maxRegister": 60,
    "maxAcceptedStudent": 20,
    "timestamp": 1745013404
  },
  {
    "studentRegister": 60,
    "studentAccepted": 0,
    "maxRegister": 60,
    "maxAcceptedStudent": 20,
    "timestamp": 1745014376
  },
  {
    "studentRegister": 60,
    "studentAccepted": 0,
    "maxRegister": 60,
    "maxAcceptedStudent": 20,
    "timestamp": 1745015533
  },
  {
    "studentRegister": 60,
    "studentAccepted": 0,
    "maxRegister": 60,
    "maxAcceptedStudent": 20,
    "timestamp": 1745016236
  },
  {
    "studentRegister": 60,
    "studentAccepted": 0,
    "maxRegister": 60,
    "maxAcceptedStudent": 20,
    "timestamp": 1745016634
  },
  {
    "studentRegister": 60,
    "studentAccepted": 0,
    "maxRegister": 60,
    "maxAcceptedStudent": 20,
    "timestamp": 1745017041
  },
  {
    "studentRegister": 60,
    "studentAccepted": 0,
    "maxRegister": 60,
    "maxAcceptedStudent": 20,
    "timestamp": 1745018050
  },
  {
    "studentRegister": 60,
    "studentAccepted": 0,
    "maxRegister": 60,
    "maxAcceptedStudent": 20,
    "timestamp": 1745018928
  },
  {
    "studentRegister": 60,
    "studentAccepted": 0,
    "maxRegister": 60,
    "maxAcceptedStudent": 20,
    "timestamp": 1745019441
  },
  {
    "studentRegister": 60,
    "studentAccepted": 0,
    "maxRegister": 60,
    "maxAcceptedStudent": 20,
    "timestamp": 1745019846
  },
  {
    "studentRegister": 60,
    "studentAccepted": 0,
    "maxRegister": 60,
    "maxAcceptedStudent": 20,
    "timestamp": 1745020244
  },
  {
    "studentRegister": 60,
    "studentAccepted": 0,
    "maxRegister": 60,
    "maxAcceptedStudent": 20,
    "timestamp": 1745020632
  },
  {
    "studentRegister": 60,
    "studentAccepted": 0,
    "maxRegister": 60,
    "maxAcceptedStudent": 20,
    "timestamp": 1745024815
  },
  {
    "studentRegister": 60,
    "studentAccepted": 0,
    "maxRegister": 60,
    "maxAcceptedStudent": 20,
    "timestamp": 1745030049
  },
  {
    "studentRegister": 60,
    "studentAccepted": 0,
    "maxRegister": 60,
    "maxAcceptedStudent": 20,
    "timestamp": 1745032227
  },
  {
    "studentRegister": 60,
    "studentAccepted": 0,
    "maxRegister": 60,
    "maxAcceptedStudent": 20,
    "timestamp": 1745033957
  },
  {
    "studentRegister": 60,
    "studentAccepted": 0,
    "maxRegister": 60,
    "maxAcceptedStudent": 20,
    "timestamp": 1745034644
  },
  {
    "studentRegister": 60,
    "studentAccepted": 0,
    "maxRegister": 60,
    "maxAcceptedStudent": 20,
    "timestamp": 1745035041
  },
  {
    "studentRegister": 60,
    "studentAccepted": 0,
    "maxRegister": 60,
    "maxAcceptedStudent": 20,
    "timestamp": 1745036238
  },
  {
    "studentRegister": 60,
    "studentAccepted": 0,
    "maxRegister": 60,
    "maxAcceptedStudent": 20,
    "timestamp": 1745037367
  },
  {
    "studentRegister": 60,
    "studentAccepted": 0,
    "maxRegister": 60,
    "maxAcceptedStudent": 20,
    "timestamp": 1745037968
  },
  {
    "studentRegister": 60,
    "studentAccepted": 0,
    "maxRegister": 60,
    "maxAcceptedStudent": 20,
    "timestamp": 1745038362
  },
  {
    "studentRegister": 60,
    "studentAccepted": 0,
    "maxRegister": 60,
    "maxAcceptedStudent": 20,
    "timestamp": 1745038754
  },
  {
    "studentRegister": 60,
    "studentAccepted": 0,
    "maxRegister": 60,
    "maxAcceptedStudent": 20,
    "timestamp": 1745039920
  },
  {
    "studentRegister": 60,
    "studentAccepted": 0,
    "maxRegister": 60,
    "maxAcceptedStudent": 20,
    "timestamp": 1745040874
  },
  {
    "studentRegister": 60,
    "studentAccepted": 0,
    "maxRegister": 60,
    "maxAcceptedStudent": 20,
    "timestamp": 1745041415
  },
  {
    "studentRegister": 60,
    "studentAccepted": 0,
    "maxRegister": 60,
    "maxAcceptedStudent": 20,
    "timestamp": 1745041805
  },
  {
    "studentRegister": 60,
    "studentAccepted": 0,
    "maxRegister": 60,
    "maxAcceptedStudent": 20,
    "timestamp": 1745042211
  },
  {
    "studentRegister": 60,
    "studentAccepted": 0,
    "maxRegister": 60,
    "maxAcceptedStudent": 20,
    "timestamp": 1745043522
  },
  {
    "studentRegister": 60,
    "studentAccepted": 0,
    "maxRegister": 60,
    "maxAcceptedStudent": 20,
    "timestamp": 1745044888
  },
  {
    "studentRegister": 60,
    "studentAccepted": 0,
    "maxRegister": 60,
    "maxAcceptedStudent": 20,
    "timestamp": 1745045464
  },
  {
    "studentRegister": 60,
    "studentAccepted": 0,
    "maxRegister": 60,
    "maxAcceptedStudent": 20,
    "timestamp": 1745045851
  },
  {
    "studentRegister": 60,
    "studentAccepted": 0,
    "maxRegister": 60,
    "maxAcceptedStudent": 20,
    "timestamp": 1745046803
  },
  {
    "studentRegister": 60,
    "studentAccepted": 0,
    "maxRegister": 60,
    "maxAcceptedStudent": 20,
    "timestamp": 1745047556
  },
  {
    "studentRegister": 60,
    "studentAccepted": 0,
    "maxRegister": 60,
    "maxAcceptedStudent": 20,
    "timestamp": 1745048012
  },
  {
    "studentRegister": 60,
    "studentAccepted": 0,
    "maxRegister": 60,
    "maxAcceptedStudent": 20,
    "timestamp": 1745048414
  },
  {
    "studentRegister": 60,
    "studentAccepted": 0,
    "maxRegister": 60,
    "maxAcceptedStudent": 20,
    "timestamp": 1745048834
  },
  {
    "studentRegister": 60,
    "studentAccepted": 0,
    "maxRegister": 60,
    "maxAcceptedStudent": 20,
    "timestamp": 1745049250
  },
  {
    "studentRegister": 60,
    "studentAccepted": 0,
    "maxRegister": 60,
    "maxAcceptedStudent": 20,
    "timestamp": 1745050188
  },
  {
    "studentRegister": 60,
    "studentAccepted": 0,
    "maxRegister": 60,
    "maxAcceptedStudent": 20,
    "timestamp": 1745051488
  },
  {
    "studentRegister": 60,
    "studentAccepted": 0,
    "maxRegister": 60,
    "maxAcceptedStudent": 20,
    "timestamp": 1745052224
  },
  {
    "studentRegister": 60,
    "studentAccepted": 0,
    "maxRegister": 60,
    "maxAcceptedStudent": 20,
    "timestamp": 1745052638
  },
  {
    "studentRegister": 60,
    "studentAccepted": 0,
    "maxRegister": 60,
    "maxAcceptedStudent": 20,
    "timestamp": 1745053025
  },
  {
    "studentRegister": 60,
    "studentAccepted": 0,
    "maxRegister": 60,
    "maxAcceptedStudent": 20,
    "timestamp": 1745054019
  },
  {
    "studentRegister": 60,
    "studentAccepted": 0,
    "maxRegister": 60,
    "maxAcceptedStudent": 20,
    "timestamp": 1745054906
  },
  {
    "studentRegister": 60,
    "studentAccepted": 0,
    "maxRegister": 60,
    "maxAcceptedStudent": 20,
    "timestamp": 1745055417
  },
  {
    "studentRegister": 60,
    "studentAccepted": 0,
    "maxRegister": 60,
    "maxAcceptedStudent": 20,
    "timestamp": 1745055822
  },
  {
    "studentRegister": 60,
    "studentAccepted": 0,
    "maxRegister": 60,
    "maxAcceptedStudent": 20,
    "timestamp": 1745056226
  },
  {
    "studentRegister": 60,
    "studentAccepted": 0,
    "maxRegister": 60,
    "maxAcceptedStudent": 20,
    "timestamp": 1745056625
  },
  {
    "studentRegister": 60,
    "studentAccepted": 0,
    "maxRegister": 60,
    "maxAcceptedStudent": 20,
    "timestamp": 1745057616
  },
  {
    "studentRegister": 60,
    "studentAccepted": 0,
    "maxRegister": 60,
    "maxAcceptedStudent": 20,
    "timestamp": 1745058758
  },
  {
    "studentRegister": 60,
    "studentAccepted": 0,
    "maxRegister": 60,
    "maxAcceptedStudent": 20,
    "timestamp": 1745059359
  },
  {
    "studentRegister": 60,
    "studentAccepted": 0,
    "maxRegister": 60,
    "maxAcceptedStudent": 20,
    "timestamp": 1745059753
  },
  {
    "studentRegister": 60,
    "studentAccepted": 0,
    "maxRegister": 60,
    "maxAcceptedStudent": 20,
    "timestamp": 1745060146
  },
  {
    "studentRegister": 60,
    "studentAccepted": 0,
    "maxRegister": 60,
    "maxAcceptedStudent": 20,
    "timestamp": 1745060962
  },
  {
    "studentRegister": 60,
    "studentAccepted": 0,
    "maxRegister": 60,
    "maxAcceptedStudent": 20,
    "timestamp": 1745061774
  },
  {
    "studentRegister": 60,
    "studentAccepted": 0,
    "maxRegister": 60,
    "maxAcceptedStudent": 20,
    "timestamp": 1745062194
  },
  {
    "studentRegister": 60,
    "studentAccepted": 0,
    "maxRegister": 60,
    "maxAcceptedStudent": 20,
    "timestamp": 1745062652
  },
  {
    "studentRegister": 60,
    "studentAccepted": 0,
    "maxRegister": 60,
    "maxAcceptedStudent": 20,
    "timestamp": 1745063053
  },
  {
    "studentRegister": 60,
    "studentAccepted": 0,
    "maxRegister": 60,
    "maxAcceptedStudent": 20,
    "timestamp": 1745063464
  },
  {
    "studentRegister": 60,
    "studentAccepted": 0,
    "maxRegister": 60,
    "maxAcceptedStudent": 20,
    "timestamp": 1745063852
  },
  {
    "studentRegister": 60,
    "studentAccepted": 0,
    "maxRegister": 60,
    "maxAcceptedStudent": 20,
    "timestamp": 1745065646
  },
  {
    "studentRegister": 60,
    "studentAccepted": 0,
    "maxRegister": 60,
    "maxAcceptedStudent": 20,
    "timestamp": 1745067417
  },
  {
    "studentRegister": 60,
    "studentAccepted": 0,
    "maxRegister": 60,
    "maxAcceptedStudent": 20,
    "timestamp": 1745068733
  },
  {
    "studentRegister": 60,
    "studentAccepted": 0,
    "maxRegister": 60,
    "maxAcceptedStudent": 20,
    "timestamp": 1745069661
  },
  {
    "studentRegister": 60,
    "studentAccepted": 0,
    "maxRegister": 60,
    "maxAcceptedStudent": 20,
    "timestamp": 1745070133
  },
  {
    "studentRegister": 60,
    "studentAccepted": 0,
    "maxRegister": 60,
    "maxAcceptedStudent": 20,
    "timestamp": 1745070524
  },
  {
    "studentRegister": 60,
    "studentAccepted": 0,
    "maxRegister": 60,
    "maxAcceptedStudent": 20,
    "timestamp": 1745070930
  },
  {
    "studentRegister": 60,
    "studentAccepted": 0,
    "maxRegister": 60,
    "maxAcceptedStudent": 20,
    "timestamp": 1745071778
  },
  {
    "studentRegister": 60,
    "studentAccepted": 0,
    "maxRegister": 60,
    "maxAcceptedStudent": 20,
    "timestamp": 1745072884
  },
  {
    "studentRegister": 60,
    "studentAccepted": 0,
    "maxRegister": 60,
    "maxAcceptedStudent": 20,
    "timestamp": 1745073506
  },
  {
    "studentRegister": 60,
    "studentAccepted": 0,
    "maxRegister": 60,
    "maxAcceptedStudent": 20,
    "timestamp": 1745073910
  },
  {
    "studentRegister": 60,
    "studentAccepted": 0,
    "maxRegister": 60,
    "maxAcceptedStudent": 20,
    "timestamp": 1745074326
  },
  {
    "studentRegister": 60,
    "studentAccepted": 0,
    "maxRegister": 60,
    "maxAcceptedStudent": 20,
    "timestamp": 1745074733
  },
  {
    "studentRegister": 60,
    "studentAccepted": 0,
    "maxRegister": 60,
    "maxAcceptedStudent": 20,
    "timestamp": 1745075815
  },
  {
    "studentRegister": 60,
    "studentAccepted": 0,
    "maxRegister": 60,
    "maxAcceptedStudent": 20,
    "timestamp": 1745076610
  },
  {
    "studentRegister": 60,
    "studentAccepted": 0,
    "maxRegister": 60,
    "maxAcceptedStudent": 20,
    "timestamp": 1745077124
  },
  {
    "studentRegister": 60,
    "studentAccepted": 0,
    "maxRegister": 60,
    "maxAcceptedStudent": 20,
    "timestamp": 1745077527
  },
  {
    "studentRegister": 60,
    "studentAccepted": 0,
    "maxRegister": 60,
    "maxAcceptedStudent": 20,
    "timestamp": 1745077945
  },
  {
    "studentRegister": 60,
    "studentAccepted": 0,
    "maxRegister": 60,
    "maxAcceptedStudent": 20,
    "timestamp": 1745078355
  },
  {
    "studentRegister": 60,
    "studentAccepted": 0,
    "maxRegister": 60,
    "maxAcceptedStudent": 20,
    "timestamp": 1745079768
  },
  {
    "studentRegister": 60,
    "studentAccepted": 0,
    "maxRegister": 60,
    "maxAcceptedStudent": 20,
    "timestamp": 1745080816
  },
  {
    "studentRegister": 60,
    "studentAccepted": 0,
    "maxRegister": 60,
    "maxAcceptedStudent": 20,
    "timestamp": 1745081374
  },
  {
    "studentRegister": 60,
    "studentAccepted": 0,
    "maxRegister": 60,
    "maxAcceptedStudent": 20,
    "timestamp": 1745081785
  },
  {
    "studentRegister": 60,
    "studentAccepted": 0,
    "maxRegister": 60,
    "maxAcceptedStudent": 20,
    "timestamp": 1745082667
  },
  {
    "studentRegister": 60,
    "studentAccepted": 0,
    "maxRegister": 60,
    "maxAcceptedStudent": 20,
    "timestamp": 1745083668
  },
  {
    "studentRegister": 60,
    "studentAccepted": 0,
    "maxRegister": 60,
    "maxAcceptedStudent": 20,
    "timestamp": 1745084268
  },
  {
    "studentRegister": 60,
    "studentAccepted": 0,
    "maxRegister": 60,
    "maxAcceptedStudent": 20,
    "timestamp": 1745084674
  },
  {
    "studentRegister": 60,
    "studentAccepted": 0,
    "maxRegister": 60,
    "maxAcceptedStudent": 20,
    "timestamp": 1745085085
  },
  {
    "studentRegister": 60,
    "studentAccepted": 0,
    "maxRegister": 60,
    "maxAcceptedStudent": 20,
    "timestamp": 1745085490
  },
  {
    "studentRegister": 60,
    "studentAccepted": 0,
    "maxRegister": 60,
    "maxAcceptedStudent": 20,
    "timestamp": 1745086841
  },
  {
    "studentRegister": 60,
    "studentAccepted": 0,
    "maxRegister": 60,
    "maxAcceptedStudent": 20,
    "timestamp": 1745087956
  },
  {
    "studentRegister": 60,
    "studentAccepted": 0,
    "maxRegister": 60,
    "maxAcceptedStudent": 20,
    "timestamp": 1745088476
  },
  {
    "studentRegister": 60,
    "studentAccepted": 0,
    "maxRegister": 60,
    "maxAcceptedStudent": 20,
    "timestamp": 1745088866
  },
  {
    "studentRegister": 60,
    "studentAccepted": 0,
    "maxRegister": 60,
    "maxAcceptedStudent": 20,
    "timestamp": 1745089622
  },
  {
    "studentRegister": 60,
    "studentAccepted": 0,
    "maxRegister": 60,
    "maxAcceptedStudent": 20,
    "timestamp": 1745090479
  },
  {
    "studentRegister": 60,
    "studentAccepted": 0,
    "maxRegister": 60,
    "maxAcceptedStudent": 20,
    "timestamp": 1745090901
  },
  {
    "studentRegister": 60,
    "studentAccepted": 0,
    "maxRegister": 60,
    "maxAcceptedStudent": 20,
    "timestamp": 1745091369
  },
  {
    "studentRegister": 60,
    "studentAccepted": 0,
    "maxRegister": 60,
    "maxAcceptedStudent": 20,
    "timestamp": 1745091788
  },
  {
    "studentRegister": 60,
    "studentAccepted": 0,
    "maxRegister": 60,
    "maxAcceptedStudent": 20,
    "timestamp": 1745092191
  },
  {
    "studentRegister": 60,
    "studentAccepted": 0,
    "maxRegister": 60,
    "maxAcceptedStudent": 20,
    "timestamp": 1745092599
  },
  {
    "studentRegister": 60,
    "studentAccepted": 0,
    "maxRegister": 60,
    "maxAcceptedStudent": 20,
    "timestamp": 1745093600
  },
  {
    "studentRegister": 60,
    "studentAccepted": 0,
    "maxRegister": 60,
    "maxAcceptedStudent": 20,
    "timestamp": 1745094626
  },
  {
    "studentRegister": 60,
    "studentAccepted": 0,
    "maxRegister": 60,
    "maxAcceptedStudent": 20,
    "timestamp": 1745095233
  },
  {
    "studentRegister": 60,
    "studentAccepted": 0,
    "maxRegister": 60,
    "maxAcceptedStudent": 20,
    "timestamp": 1745095636
  },
  {
    "studentRegister": 60,
    "studentAccepted": 0,
    "maxRegister": 60,
    "maxAcceptedStudent": 20,
    "timestamp": 1745096035
  },
  {
    "studentRegister": 60,
    "studentAccepted": 0,
    "maxRegister": 60,
    "maxAcceptedStudent": 20,
    "timestamp": 1745096436
  },
  {
    "studentRegister": 60,
    "studentAccepted": 0,
    "maxRegister": 60,
    "maxAcceptedStudent": 20,
    "timestamp": 1745097559
  },
  {
    "studentRegister": 60,
    "studentAccepted": 0,
    "maxRegister": 60,
    "maxAcceptedStudent": 20,
    "timestamp": 1745098213
  },
  {
    "studentRegister": 60,
    "studentAccepted": 0,
    "maxRegister": 60,
    "maxAcceptedStudent": 20,
    "timestamp": 1745098679
  },
  {
    "studentRegister": 60,
    "studentAccepted": 0,
    "maxRegister": 60,
    "maxAcceptedStudent": 20,
    "timestamp": 1745099068
  },
  {
    "studentRegister": 60,
    "studentAccepted": 0,
    "maxRegister": 60,
    "maxAcceptedStudent": 20,
    "timestamp": 1745099468
  },
  {
    "studentRegister": 60,
    "studentAccepted": 0,
    "maxRegister": 60,
    "maxAcceptedStudent": 20,
    "timestamp": 1745099880
  },
  {
    "studentRegister": 60,
    "studentAccepted": 0,
    "maxRegister": 60,
    "maxAcceptedStudent": 20,
    "timestamp": 1745100882
  },
  {
    "studentRegister": 60,
    "studentAccepted": 0,
    "maxRegister": 60,
    "maxAcceptedStudent": 20,
    "timestamp": 1745101900
  },
  {
    "studentRegister": 60,
    "studentAccepted": 0,
    "maxRegister": 60,
    "maxAcceptedStudent": 20,
    "timestamp": 1745102512
  },
  {
    "studentRegister": 60,
    "studentAccepted": 0,
    "maxRegister": 60,
    "maxAcceptedStudent": 20,
    "timestamp": 1745102906
  },
  {
    "studentRegister": 60,
    "studentAccepted": 0,
    "maxRegister": 60,
    "maxAcceptedStudent": 20,
    "timestamp": 1745103310
  },
  {
    "studentRegister": 60,
    "studentAccepted": 0,
    "maxRegister": 60,
    "maxAcceptedStudent": 20,
    "timestamp": 1745104189
  },
  {
    "studentRegister": 60,
    "studentAccepted": 0,
    "maxRegister": 60,
    "maxAcceptedStudent": 20,
    "timestamp": 1745105258
  },
  {
    "studentRegister": 60,
    "studentAccepted": 0,
    "maxRegister": 60,
    "maxAcceptedStudent": 20,
    "timestamp": 1745105823
  },
  {
    "studentRegister": 60,
    "studentAccepted": 0,
    "maxRegister": 60,
    "maxAcceptedStudent": 20,
    "timestamp": 1745106224
  },
  {
    "studentRegister": 60,
    "studentAccepted": 0,
    "maxRegister": 60,
    "maxAcceptedStudent": 20,
    "timestamp": 1745106632
  },
  {
    "studentRegister": 60,
    "studentAccepted": 0,
    "maxRegister": 60,
    "maxAcceptedStudent": 20,
    "timestamp": 1745107030
  },
  {
    "studentRegister": 60,
    "studentAccepted": 0,
    "maxRegister": 60,
    "maxAcceptedStudent": 20,
    "timestamp": 1745111677
  },
  {
    "studentRegister": 60,
    "studentAccepted": 0,
    "maxRegister": 60,
    "maxAcceptedStudent": 20,
    "timestamp": 1745117253
  },
  {
    "studentRegister": 60,
    "studentAccepted": 0,
    "maxRegister": 60,
    "maxAcceptedStudent": 20,
    "timestamp": 1745119735
  },
  {
    "studentRegister": 60,
    "studentAccepted": 0,
    "maxRegister": 60,
    "maxAcceptedStudent": 20,
    "timestamp": 1745121065
  },
  {
    "studentRegister": 60,
    "studentAccepted": 0,
    "maxRegister": 60,
    "maxAcceptedStudent": 20,
    "timestamp": 1745121494
  },
  {
    "studentRegister": 60,
    "studentAccepted": 0,
    "maxRegister": 60,
    "maxAcceptedStudent": 20,
    "timestamp": 1745122735
  },
  {
    "studentRegister": 60,
    "studentAccepted": 0,
    "maxRegister": 60,
    "maxAcceptedStudent": 20,
    "timestamp": 1745123806
  },
  {
    "studentRegister": 60,
    "studentAccepted": 0,
    "maxRegister": 60,
    "maxAcceptedStudent": 20,
    "timestamp": 1745124407
  },
  {
    "studentRegister": 60,
    "studentAccepted": 0,
    "maxRegister": 60,
    "maxAcceptedStudent": 20,
    "timestamp": 1745124815
  },
  {
    "studentRegister": 60,
    "studentAccepted": 0,
    "maxRegister": 60,
    "maxAcceptedStudent": 20,
    "timestamp": 1745125204
  },
  {
    "studentRegister": 60,
    "studentAccepted": 0,
    "maxRegister": 60,
    "maxAcceptedStudent": 20,
    "timestamp": 1745126402
  },
  {
    "studentRegister": 60,
    "studentAccepted": 0,
    "maxRegister": 60,
    "maxAcceptedStudent": 20,
    "timestamp": 1745127320
  },
  {
    "studentRegister": 60,
    "studentAccepted": 0,
    "maxRegister": 60,
    "maxAcceptedStudent": 20,
    "timestamp": 1745127831
  },
  {
    "studentRegister": 60,
    "studentAccepted": 0,
    "maxRegister": 60,
    "maxAcceptedStudent": 20,
    "timestamp": 1745128237
  },
  {
    "studentRegister": 60,
    "studentAccepted": 0,
    "maxRegister": 60,
    "maxAcceptedStudent": 20,
    "timestamp": 1745128642
  },
  {
    "studentRegister": 60,
    "studentAccepted": 0,
    "maxRegister": 60,
    "maxAcceptedStudent": 20,
    "timestamp": 1745129994
  },
  {
    "studentRegister": 60,
    "studentAccepted": 0,
    "maxRegister": 60,
    "maxAcceptedStudent": 20,
    "timestamp": 1745131298
  },
  {
    "studentRegister": 60,
    "studentAccepted": 0,
    "maxRegister": 60,
    "maxAcceptedStudent": 20,
    "timestamp": 1745131869
  },
  {
    "studentRegister": 60,
    "studentAccepted": 0,
    "maxRegister": 60,
    "maxAcceptedStudent": 20,
    "timestamp": 1745132264
  },
  {
    "studentRegister": 60,
    "studentAccepted": 0,
    "maxRegister": 60,
    "maxAcceptedStudent": 20,
    "timestamp": 1745133306
  },
  {
    "studentRegister": 60,
    "studentAccepted": 0,
    "maxRegister": 60,
    "maxAcceptedStudent": 20,
    "timestamp": 1745134129
  },
  {
    "studentRegister": 60,
    "studentAccepted": 0,
    "maxRegister": 60,
    "maxAcceptedStudent": 20,
    "timestamp": 1745134601
  },
  {
    "studentRegister": 60,
    "studentAccepted": 0,
    "maxRegister": 60,
    "maxAcceptedStudent": 20,
    "timestamp": 1745135005
  },
  {
    "studentRegister": 60,
    "studentAccepted": 0,
    "maxRegister": 60,
    "maxAcceptedStudent": 20,
    "timestamp": 1745135411
  },
  {
    "studentRegister": 60,
    "studentAccepted": 0,
    "maxRegister": 60,
    "maxAcceptedStudent": 20,
    "timestamp": 1745135801
  },
  {
    "studentRegister": 60,
    "studentAccepted": 0,
    "maxRegister": 60,
    "maxAcceptedStudent": 20,
    "timestamp": 1745136960
  },
  {
    "studentRegister": 60,
    "studentAccepted": 0,
    "maxRegister": 60,
    "maxAcceptedStudent": 20,
    "timestamp": 1745138026
  },
  {
    "studentRegister": 60,
    "studentAccepted": 0,
    "maxRegister": 60,
    "maxAcceptedStudent": 20,
    "timestamp": 1745138670
  },
  {
    "studentRegister": 60,
    "studentAccepted": 0,
    "maxRegister": 60,
    "maxAcceptedStudent": 20,
    "timestamp": 1745139074
  },
  {
    "studentRegister": 60,
    "studentAccepted": 0,
    "maxRegister": 60,
    "maxAcceptedStudent": 20,
    "timestamp": 1745139481
  },
  {
    "studentRegister": 60,
    "studentAccepted": 0,
    "maxRegister": 60,
    "maxAcceptedStudent": 20,
    "timestamp": 1745140509
  },
  {
    "studentRegister": 60,
    "studentAccepted": 0,
    "maxRegister": 60,
    "maxAcceptedStudent": 20,
    "timestamp": 1745141336
  },
  {
    "studentRegister": 60,
    "studentAccepted": 0,
    "maxRegister": 60,
    "maxAcceptedStudent": 20,
    "timestamp": 1745141904
  },
  {
    "studentRegister": 60,
    "studentAccepted": 0,
    "maxRegister": 60,
    "maxAcceptedStudent": 20,
    "timestamp": 1745142287
  },
  {
    "studentRegister": 60,
    "studentAccepted": 0,
    "maxRegister": 60,
    "maxAcceptedStudent": 20,
    "timestamp": 1745142705
  },
  {
    "studentRegister": 60,
    "studentAccepted": 0,
    "maxRegister": 60,
    "maxAcceptedStudent": 20,
    "timestamp": 1745143100
  },
  {
    "studentRegister": 60,
    "studentAccepted": 0,
    "maxRegister": 60,
    "maxAcceptedStudent": 20,
    "timestamp": 1745144211
  },
  {
    "studentRegister": 60,
    "studentAccepted": 0,
    "maxRegister": 60,
    "maxAcceptedStudent": 20,
    "timestamp": 1745145397
  },
  {
    "studentRegister": 60,
    "studentAccepted": 0,
    "maxRegister": 60,
    "maxAcceptedStudent": 20,
    "timestamp": 1745145952
  },
  {
    "studentRegister": 60,
    "studentAccepted": 0,
    "maxRegister": 60,
    "maxAcceptedStudent": 20,
    "timestamp": 1745146348
  },
  {
    "studentRegister": 60,
    "studentAccepted": 0,
    "maxRegister": 60,
    "maxAcceptedStudent": 20,
    "timestamp": 1745146745
  },
  {
    "studentRegister": 60,
    "studentAccepted": 0,
    "maxRegister": 60,
    "maxAcceptedStudent": 20,
    "timestamp": 1745147680
  },
  {
    "studentRegister": 60,
    "studentAccepted": 0,
    "maxRegister": 60,
    "maxAcceptedStudent": 20,
    "timestamp": 1745148318
  },
  {
    "studentRegister": 60,
    "studentAccepted": 0,
    "maxRegister": 60,
    "maxAcceptedStudent": 20,
    "timestamp": 1745148777
  },
  {
    "studentRegister": 60,
    "studentAccepted": 0,
    "maxRegister": 60,
    "maxAcceptedStudent": 20,
    "timestamp": 1745149234
  },
  {
    "studentRegister": 60,
    "studentAccepted": 0,
    "maxRegister": 60,
    "maxAcceptedStudent": 20,
    "timestamp": 1745149645
  },
  {
    "studentRegister": 60,
    "studentAccepted": 0,
    "maxRegister": 60,
    "maxAcceptedStudent": 20,
    "timestamp": 1745150035
  },
  {
    "studentRegister": 60,
    "studentAccepted": 0,
    "maxRegister": 60,
    "maxAcceptedStudent": 20,
    "timestamp": 1745150447
  },
  {
    "studentRegister": 60,
    "studentAccepted": 0,
    "maxRegister": 60,
    "maxAcceptedStudent": 20,
    "timestamp": 1745152836
  },
  {
    "studentRegister": 60,
    "studentAccepted": 0,
    "maxRegister": 60,
    "maxAcceptedStudent": 20,
    "timestamp": 1745154280
  },
  {
    "studentRegister": 60,
    "studentAccepted": 0,
    "maxRegister": 60,
    "maxAcceptedStudent": 20,
    "timestamp": 1745155833
  },
  {
    "studentRegister": 60,
    "studentAccepted": 0,
    "maxRegister": 60,
    "maxAcceptedStudent": 20,
    "timestamp": 1745156535
  },
  {
    "studentRegister": 60,
    "studentAccepted": 0,
    "maxRegister": 60,
    "maxAcceptedStudent": 20,
    "timestamp": 1745156936
  },
  {
    "studentRegister": 60,
    "studentAccepted": 0,
    "maxRegister": 60,
    "maxAcceptedStudent": 20,
    "timestamp": 1745157341
  },
  {
    "studentRegister": 60,
    "studentAccepted": 0,
    "maxRegister": 60,
    "maxAcceptedStudent": 20,
    "timestamp": 1745158186
  },
  {
    "studentRegister": 60,
    "studentAccepted": 0,
    "maxRegister": 60,
    "maxAcceptedStudent": 20,
    "timestamp": 1745159348
  },
  {
    "studentRegister": 60,
    "studentAccepted": 0,
    "maxRegister": 60,
    "maxAcceptedStudent": 20,
    "timestamp": 1745160053
  },
  {
    "studentRegister": 60,
    "studentAccepted": 0,
    "maxRegister": 60,
    "maxAcceptedStudent": 20,
    "timestamp": 1745160450
  },
  {
    "studentRegister": 60,
    "studentAccepted": 0,
    "maxRegister": 60,
    "maxAcceptedStudent": 20,
    "timestamp": 1745160842
  },
  {
    "studentRegister": 60,
    "studentAccepted": 0,
    "maxRegister": 60,
    "maxAcceptedStudent": 20,
    "timestamp": 1745161477
  },
  {
    "studentRegister": 60,
    "studentAccepted": 0,
    "maxRegister": 60,
    "maxAcceptedStudent": 20,
    "timestamp": 1745162689
  },
  {
    "studentRegister": 60,
    "studentAccepted": 0,
    "maxRegister": 60,
    "maxAcceptedStudent": 20,
    "timestamp": 1745163232
  },
  {
    "studentRegister": 60,
    "studentAccepted": 0,
    "maxRegister": 60,
    "maxAcceptedStudent": 20,
    "timestamp": 1745163779
  },
  {
    "studentRegister": 60,
    "studentAccepted": 0,
    "maxRegister": 60,
    "maxAcceptedStudent": 20,
    "timestamp": 1745164167
  },
  {
    "studentRegister": 60,
    "studentAccepted": 0,
    "maxRegister": 60,
    "maxAcceptedStudent": 20,
    "timestamp": 1745164574
  },
  {
    "studentRegister": 60,
    "studentAccepted": 0,
    "maxRegister": 60,
    "maxAcceptedStudent": 20,
    "timestamp": 1745165636
  },
  {
    "studentRegister": 60,
    "studentAccepted": 0,
    "maxRegister": 60,
    "maxAcceptedStudent": 20,
    "timestamp": 1745166898
  },
  {
    "studentRegister": 60,
    "studentAccepted": 0,
    "maxRegister": 60,
    "maxAcceptedStudent": 20,
    "timestamp": 1745167604
  },
  {
    "studentRegister": 60,
    "studentAccepted": 0,
    "maxRegister": 60,
    "maxAcceptedStudent": 20,
    "timestamp": 1745168007
  },
  {
    "studentRegister": 60,
    "studentAccepted": 0,
    "maxRegister": 60,
    "maxAcceptedStudent": 20,
    "timestamp": 1745168411
  },
  {
    "studentRegister": 60,
    "studentAccepted": 0,
    "maxRegister": 60,
    "maxAcceptedStudent": 20,
    "timestamp": 1745169532
  },
  {
    "studentRegister": 60,
    "studentAccepted": 0,
    "maxRegister": 60,
    "maxAcceptedStudent": 20,
    "timestamp": 1745170357
  },
  {
    "studentRegister": 60,
    "studentAccepted": 0,
    "maxRegister": 60,
    "maxAcceptedStudent": 20,
    "timestamp": 1745170928
  },
  {
    "studentRegister": 60,
    "studentAccepted": 0,
    "maxRegister": 60,
    "maxAcceptedStudent": 20,
    "timestamp": 1745171329
  },
  {
    "studentRegister": 60,
    "studentAccepted": 0,
    "maxRegister": 60,
    "maxAcceptedStudent": 20,
    "timestamp": 1745171709
  },
  {
    "studentRegister": 60,
    "studentAccepted": 0,
    "maxRegister": 60,
    "maxAcceptedStudent": 20,
    "timestamp": 1745172763
  },
  {
    "studentRegister": 60,
    "studentAccepted": 0,
    "maxRegister": 60,
    "maxAcceptedStudent": 20,
    "timestamp": 1745174131
  },
  {
    "studentRegister": 60,
    "studentAccepted": 0,
    "maxRegister": 60,
    "maxAcceptedStudent": 20,
    "timestamp": 1745174900
  },
  {
    "studentRegister": 60,
    "studentAccepted": 0,
    "maxRegister": 60,
    "maxAcceptedStudent": 20,
    "timestamp": 1745175309
  },
  {
    "studentRegister": 60,
    "studentAccepted": 0,
    "maxRegister": 60,
    "maxAcceptedStudent": 20,
    "timestamp": 1745176146
  },
  {
    "studentRegister": 60,
    "studentAccepted": 0,
    "maxRegister": 60,
    "maxAcceptedStudent": 20,
    "timestamp": 1745176919
  },
  {
    "studentRegister": 60,
    "studentAccepted": 0,
    "maxRegister": 60,
    "maxAcceptedStudent": 20,
    "timestamp": 1745177309
  },
  {
    "studentRegister": 60,
    "studentAccepted": 0,
    "maxRegister": 60,
    "maxAcceptedStudent": 20,
    "timestamp": 1745177795
  },
  {
    "studentRegister": 60,
    "studentAccepted": 0,
    "maxRegister": 60,
    "maxAcceptedStudent": 20,
    "timestamp": 1745178205
  },
  {
    "studentRegister": 60,
    "studentAccepted": 0,
    "maxRegister": 60,
    "maxAcceptedStudent": 20,
    "timestamp": 1745178580
  },
  {
    "studentRegister": 60,
    "studentAccepted": 0,
    "maxRegister": 60,
    "maxAcceptedStudent": 20,
    "timestamp": 1745178993
  },
  {
    "studentRegister": 60,
    "studentAccepted": 0,
    "maxRegister": 60,
    "maxAcceptedStudent": 20,
    "timestamp": 1745180016
  },
  {
    "studentRegister": 60,
    "studentAccepted": 0,
    "maxRegister": 60,
    "maxAcceptedStudent": 20,
    "timestamp": 1745180998
  },
  {
    "studentRegister": 60,
    "studentAccepted": 0,
    "maxRegister": 60,
    "maxAcceptedStudent": 20,
    "timestamp": 1745181627
  },
  {
    "studentRegister": 60,
    "studentAccepted": 0,
    "maxRegister": 60,
    "maxAcceptedStudent": 20,
    "timestamp": 1745182039
  },
  {
    "studentRegister": 60,
    "studentAccepted": 0,
    "maxRegister": 60,
    "maxAcceptedStudent": 20,
    "timestamp": 1745182452
  },
  {
    "studentRegister": 60,
    "studentAccepted": 0,
    "maxRegister": 60,
    "maxAcceptedStudent": 20,
    "timestamp": 1745183224
  },
  {
    "studentRegister": 60,
    "studentAccepted": 0,
    "maxRegister": 60,
    "maxAcceptedStudent": 20,
    "timestamp": 1745184238
  },
  {
    "studentRegister": 60,
    "studentAccepted": 0,
    "maxRegister": 60,
    "maxAcceptedStudent": 20,
    "timestamp": 1745184659
  },
  {
    "studentRegister": 60,
    "studentAccepted": 0,
    "maxRegister": 60,
    "maxAcceptedStudent": 20,
    "timestamp": 1745185177
  },
  {
    "studentRegister": 60,
    "studentAccepted": 0,
    "maxRegister": 60,
    "maxAcceptedStudent": 20,
    "timestamp": 1745185580
  },
  {
    "studentRegister": 60,
    "studentAccepted": 0,
    "maxRegister": 60,
    "maxAcceptedStudent": 20,
    "timestamp": 1745186002
  },
  {
    "studentRegister": 60,
    "studentAccepted": 0,
    "maxRegister": 60,
    "maxAcceptedStudent": 20,
    "timestamp": 1745186408
  },
  {
    "studentRegister": 60,
    "studentAccepted": 0,
    "maxRegister": 60,
    "maxAcceptedStudent": 20,
    "timestamp": 1745187610
  },
  {
    "studentRegister": 60,
    "studentAccepted": 0,
    "maxRegister": 60,
    "maxAcceptedStudent": 20,
    "timestamp": 1745188555
  },
  {
    "studentRegister": 60,
    "studentAccepted": 0,
    "maxRegister": 60,
    "maxAcceptedStudent": 20,
    "timestamp": 1745189061
  },
  {
    "studentRegister": 60,
    "studentAccepted": 0,
    "maxRegister": 60,
    "maxAcceptedStudent": 20,
    "timestamp": 1745189483
  },
  {
    "studentRegister": 60,
    "studentAccepted": 0,
    "maxRegister": 60,
    "maxAcceptedStudent": 20,
    "timestamp": 1745189868
  },
  {
    "studentRegister": 60,
    "studentAccepted": 0,
    "maxRegister": 60,
    "maxAcceptedStudent": 20,
    "timestamp": 1745190870
  },
  {
    "studentRegister": 60,
    "studentAccepted": 0,
    "maxRegister": 60,
    "maxAcceptedStudent": 20,
    "timestamp": 1745191668
  },
  {
    "studentRegister": 60,
    "studentAccepted": 0,
    "maxRegister": 60,
    "maxAcceptedStudent": 20,
    "timestamp": 1745192169
  },
  {
    "studentRegister": 60,
    "studentAccepted": 0,
    "maxRegister": 60,
    "maxAcceptedStudent": 20,
    "timestamp": 1745192574
  },
  {
    "studentRegister": 60,
    "studentAccepted": 0,
    "maxRegister": 60,
    "maxAcceptedStudent": 20,
    "timestamp": 1745192993
  },
  {
    "studentRegister": 60,
    "studentAccepted": 0,
    "maxRegister": 60,
    "maxAcceptedStudent": 20,
    "timestamp": 1745193402
  },
  {
    "studentRegister": 60,
    "studentAccepted": 0,
    "maxRegister": 60,
    "maxAcceptedStudent": 20,
    "timestamp": 1745197690
  },
  {
    "studentRegister": 60,
    "studentAccepted": 0,
    "maxRegister": 60,
    "maxAcceptedStudent": 20,
    "timestamp": 1745203645
  },
  {
    "studentRegister": 60,
    "studentAccepted": 0,
    "maxRegister": 60,
    "maxAcceptedStudent": 20,
    "timestamp": 1745206310
  },
  {
    "studentRegister": 57,
    "studentAccepted": 0,
    "maxRegister": 60,
    "maxAcceptedStudent": 20,
    "timestamp": 1745207761
  },
  {
    "studentRegister": 58,
    "studentAccepted": 0,
    "maxRegister": 60,
    "maxAcceptedStudent": 20,
    "timestamp": 1745208967
  },
  {
    "studentRegister": 60,
    "studentAccepted": 0,
    "maxRegister": 60,
    "maxAcceptedStudent": 20,
    "timestamp": 1745210294
  },
  {
    "studentRegister": 60,
    "studentAccepted": 0,
    "maxRegister": 60,
    "maxAcceptedStudent": 20,
    "timestamp": 1745211049
  },
  {
    "studentRegister": 60,
    "studentAccepted": 0,
    "maxRegister": 60,
    "maxAcceptedStudent": 20,
    "timestamp": 1745211448
  },
  {
    "studentRegister": 60,
    "studentAccepted": 0,
    "maxRegister": 60,
    "maxAcceptedStudent": 20,
    "timestamp": 1745212573
  },
  {
    "studentRegister": 60,
    "studentAccepted": 0,
    "maxRegister": 60,
    "maxAcceptedStudent": 20,
    "timestamp": 1745213730
  },
  {
    "studentRegister": 60,
    "studentAccepted": 0,
    "maxRegister": 60,
    "maxAcceptedStudent": 20,
    "timestamp": 1745214447
  },
  {
    "studentRegister": 60,
    "studentAccepted": 0,
    "maxRegister": 60,
    "maxAcceptedStudent": 20,
    "timestamp": 1745214849
  },
  {
    "studentRegister": 60,
    "studentAccepted": 0,
    "maxRegister": 60,
    "maxAcceptedStudent": 20,
    "timestamp": 1745215967
  },
  {
    "studentRegister": 60,
    "studentAccepted": 0,
    "maxRegister": 60,
    "maxAcceptedStudent": 20,
    "timestamp": 1745217699
  },
  {
    "studentRegister": 60,
    "studentAccepted": 0,
    "maxRegister": 60,
    "maxAcceptedStudent": 20,
    "timestamp": 1745218455
  },
  {
    "studentRegister": 60,
    "studentAccepted": 0,
    "maxRegister": 60,
    "maxAcceptedStudent": 20,
    "timestamp": 1745219368
  },
  {
    "studentRegister": 60,
    "studentAccepted": 0,
    "maxRegister": 60,
    "maxAcceptedStudent": 20,
    "timestamp": 1745220435
  },
  {
    "studentRegister": 60,
    "studentAccepted": 0,
    "maxRegister": 60,
    "maxAcceptedStudent": 20,
    "timestamp": 1745221010
  },
  {
    "studentRegister": 60,
    "studentAccepted": 0,
    "maxRegister": 60,
    "maxAcceptedStudent": 20,
    "timestamp": 1745221412
  },
  {
    "studentRegister": 60,
    "studentAccepted": 0,
    "maxRegister": 60,
    "maxAcceptedStudent": 20,
    "timestamp": 1745221817
  },
  {
    "studentRegister": 60,
    "studentAccepted": 0,
    "maxRegister": 60,
    "maxAcceptedStudent": 20,
    "timestamp": 1745222220
  },
  {
    "studentRegister": 60,
    "studentAccepted": 0,
    "maxRegister": 60,
    "maxAcceptedStudent": 20,
    "timestamp": 1745223567
  },
  {
    "studentRegister": 60,
    "studentAccepted": 0,
    "maxRegister": 60,
    "maxAcceptedStudent": 20,
    "timestamp": 1745224908
  },
  {
    "studentRegister": 60,
    "studentAccepted": 0,
    "maxRegister": 60,
    "maxAcceptedStudent": 20,
    "timestamp": 1745225688
  },
  {
    "studentRegister": 60,
    "studentAccepted": 0,
    "maxRegister": 60,
    "maxAcceptedStudent": 20,
    "timestamp": 1745226657
  },
  {
    "studentRegister": 60,
    "studentAccepted": 0,
    "maxRegister": 60,
    "maxAcceptedStudent": 20,
    "timestamp": 1745227841
  },
  {
    "studentRegister": 60,
    "studentAccepted": 0,
    "maxRegister": 60,
    "maxAcceptedStudent": 20,
    "timestamp": 1745228494
  },
  {
    "studentRegister": 60,
    "studentAccepted": 0,
    "maxRegister": 60,
    "maxAcceptedStudent": 20,
    "timestamp": 1745228895
  },
  {
    "studentRegister": 60,
    "studentAccepted": 0,
    "maxRegister": 60,
    "maxAcceptedStudent": 20,
    "timestamp": 1745229298
  },
  {
    "studentRegister": 60,
    "studentAccepted": 0,
    "maxRegister": 60,
    "maxAcceptedStudent": 20,
    "timestamp": 1745230259
  },
  {
    "studentRegister": 60,
    "studentAccepted": 0,
    "maxRegister": 60,
    "maxAcceptedStudent": 20,
    "timestamp": 1745231741
  },
  {
    "studentRegister": 60,
    "studentAccepted": 0,
    "maxRegister": 60,
    "maxAcceptedStudent": 20,
    "timestamp": 1745232519
  },
  {
    "studentRegister": 60,
    "studentAccepted": 0,
    "maxRegister": 60,
    "maxAcceptedStudent": 20,
    "timestamp": 1745232915
  },
  {
    "studentRegister": 60,
    "studentAccepted": 0,
    "maxRegister": 60,
    "maxAcceptedStudent": 20,
    "timestamp": 1745233758
  },
  {
    "studentRegister": 60,
    "studentAccepted": 0,
    "maxRegister": 60,
    "maxAcceptedStudent": 20,
    "timestamp": 1745234629
  },
  {
    "studentRegister": 60,
    "studentAccepted": 0,
    "maxRegister": 60,
    "maxAcceptedStudent": 20,
    "timestamp": 1745235050
  },
  {
    "studentRegister": 60,
    "studentAccepted": 0,
    "maxRegister": 60,
    "maxAcceptedStudent": 20,
    "timestamp": 1745235567
  },
  {
    "studentRegister": 60,
    "studentAccepted": 0,
    "maxRegister": 60,
    "maxAcceptedStudent": 20,
    "timestamp": 1745235980
  },
  {
    "studentRegister": 60,
    "studentAccepted": 0,
    "maxRegister": 60,
    "maxAcceptedStudent": 20,
    "timestamp": 1745236393
  },
  {
    "studentRegister": 60,
    "studentAccepted": 0,
    "maxRegister": 60,
    "maxAcceptedStudent": 20,
    "timestamp": 1745236787
  },
  {
    "studentRegister": 60,
    "studentAccepted": 0,
    "maxRegister": 60,
    "maxAcceptedStudent": 20,
    "timestamp": 1745239185
  },
  {
    "studentRegister": 60,
    "studentAccepted": 0,
    "maxRegister": 60,
    "maxAcceptedStudent": 20,
    "timestamp": 1745240773
  },
  {
    "studentRegister": 60,
    "studentAccepted": 0,
    "maxRegister": 60,
    "maxAcceptedStudent": 20,
    "timestamp": 1745242448
  },
  {
    "studentRegister": 60,
    "studentAccepted": 0,
    "maxRegister": 60,
    "maxAcceptedStudent": 20,
    "timestamp": 1745243113
  },
  {
    "studentRegister": 60,
    "studentAccepted": 0,
    "maxRegister": 60,
    "maxAcceptedStudent": 20,
    "timestamp": 1745243508
  },
  {
    "studentRegister": 60,
    "studentAccepted": 0,
    "maxRegister": 60,
    "maxAcceptedStudent": 20,
    "timestamp": 1745243895
  },
  {
    "studentRegister": 60,
    "studentAccepted": 0,
    "maxRegister": 60,
    "maxAcceptedStudent": 20,
    "timestamp": 1745244977
  },
  {
    "studentRegister": 60,
    "studentAccepted": 0,
    "maxRegister": 60,
    "maxAcceptedStudent": 20,
    "timestamp": 1745246021
  },
  {
    "studentRegister": 60,
    "studentAccepted": 0,
    "maxRegister": 60,
    "maxAcceptedStudent": 20,
    "timestamp": 1745246657
  },
  {
    "studentRegister": 60,
    "studentAccepted": 0,
    "maxRegister": 60,
    "maxAcceptedStudent": 20,
    "timestamp": 1745247061
  },
  {
    "studentRegister": 60,
    "studentAccepted": 0,
    "maxRegister": 60,
    "maxAcceptedStudent": 20,
    "timestamp": 1745247467
  },
  {
    "studentRegister": 60,
    "studentAccepted": 0,
    "maxRegister": 60,
    "maxAcceptedStudent": 20,
    "timestamp": 1745248587
  },
  {
    "studentRegister": 60,
    "studentAccepted": 0,
    "maxRegister": 60,
    "maxAcceptedStudent": 20,
    "timestamp": 1745249593
  },
  {
    "studentRegister": 60,
    "studentAccepted": 0,
    "maxRegister": 60,
    "maxAcceptedStudent": 20,
    "timestamp": 1745250211
  },
  {
    "studentRegister": 60,
    "studentAccepted": 0,
    "maxRegister": 60,
    "maxAcceptedStudent": 20,
    "timestamp": 1745250595
  },
  {
    "studentRegister": 60,
    "studentAccepted": 0,
    "maxRegister": 60,
    "maxAcceptedStudent": 20,
    "timestamp": 1745251004
  },
  {
    "studentRegister": 60,
    "studentAccepted": 0,
    "maxRegister": 60,
    "maxAcceptedStudent": 20,
    "timestamp": 1745252196
  },
  {
    "studentRegister": 60,
    "studentAccepted": 0,
    "maxRegister": 60,
    "maxAcceptedStudent": 20,
    "timestamp": 1745253684
  },
  {
    "studentRegister": 60,
    "studentAccepted": 0,
    "maxRegister": 60,
    "maxAcceptedStudent": 20,
    "timestamp": 1745254399
  },
  {
    "studentRegister": 60,
    "studentAccepted": 0,
    "maxRegister": 60,
    "maxAcceptedStudent": 20,
    "timestamp": 1745254782
  },
  {
    "studentRegister": 60,
    "studentAccepted": 0,
    "maxRegister": 60,
    "maxAcceptedStudent": 20,
    "timestamp": 1745255929
  },
  {
    "studentRegister": 60,
    "studentAccepted": 0,
    "maxRegister": 60,
    "maxAcceptedStudent": 20,
    "timestamp": 1745256868
  },
  {
    "studentRegister": 60,
    "studentAccepted": 0,
    "maxRegister": 60,
    "maxAcceptedStudent": 20,
    "timestamp": 1745257402
  },
  {
    "studentRegister": 60,
    "studentAccepted": 0,
    "maxRegister": 60,
    "maxAcceptedStudent": 20,
    "timestamp": 1745257872
  },
  {
    "studentRegister": 60,
    "studentAccepted": 0,
    "maxRegister": 60,
    "maxAcceptedStudent": 20,
    "timestamp": 1745258194
  },
  {
    "studentRegister": 60,
    "studentAccepted": 0,
    "maxRegister": 60,
    "maxAcceptedStudent": 20,
    "timestamp": 1745259507
  },
  {
    "studentRegister": 60,
    "studentAccepted": 0,
    "maxRegister": 60,
    "maxAcceptedStudent": 20,
    "timestamp": 1745260962
  },
  {
    "studentRegister": 60,
    "studentAccepted": 0,
    "maxRegister": 60,
    "maxAcceptedStudent": 20,
    "timestamp": 1745261582
  },
  {
    "studentRegister": 60,
    "studentAccepted": 0,
    "maxRegister": 60,
    "maxAcceptedStudent": 20,
    "timestamp": 1745261988
  },
  {
    "studentRegister": 60,
    "studentAccepted": 0,
    "maxRegister": 60,
    "maxAcceptedStudent": 20,
    "timestamp": 1745263044
  },
  {
    "studentRegister": 60,
    "studentAccepted": 0,
    "maxRegister": 60,
    "maxAcceptedStudent": 20,
    "timestamp": 1745263673
  },
  {
    "studentRegister": 60,
    "studentAccepted": 0,
    "maxRegister": 60,
    "maxAcceptedStudent": 20,
    "timestamp": 1745264159
  },
  {
    "studentRegister": 60,
    "studentAccepted": 0,
    "maxRegister": 60,
    "maxAcceptedStudent": 20,
    "timestamp": 1745264564
  },
  {
    "studentRegister": 60,
    "studentAccepted": 0,
    "maxRegister": 60,
    "maxAcceptedStudent": 20,
    "timestamp": 1745264986
  },
  {
    "studentRegister": 60,
    "studentAccepted": 0,
    "maxRegister": 60,
    "maxAcceptedStudent": 20,
    "timestamp": 1745265372
  },
  {
    "studentRegister": 60,
    "studentAccepted": 0,
    "maxRegister": 60,
    "maxAcceptedStudent": 20,
    "timestamp": 1745266440
  },
  {
    "studentRegister": 60,
    "studentAccepted": 0,
    "maxRegister": 60,
    "maxAcceptedStudent": 20,
    "timestamp": 1745267487
  },
  {
    "studentRegister": 60,
    "studentAccepted": 0,
    "maxRegister": 60,
    "maxAcceptedStudent": 20,
    "timestamp": 1745268165
  },
  {
    "studentRegister": 60,
    "studentAccepted": 0,
    "maxRegister": 60,
    "maxAcceptedStudent": 20,
    "timestamp": 1745268562
  },
  {
    "studentRegister": 60,
    "studentAccepted": 0,
    "maxRegister": 60,
    "maxAcceptedStudent": 20,
    "timestamp": 1745268958
  },
  {
    "studentRegister": 60,
    "studentAccepted": 0,
    "maxRegister": 60,
    "maxAcceptedStudent": 20,
    "timestamp": 1745269908
  }
]