[
  {
    "studentRegister": 0,
    "studentAccepted": 0,
    "maxRegister": 6,
    "maxAcceptedStudent": 2,
    "timestamp": 1748485854
  },
  {
    "studentRegister": 0,
    "studentAccepted": 0,
    "maxRegister": 6,
    "maxAcceptedStudent": 2,
    "timestamp": 1748489670
  },
  {
    "studentRegister": 1,
    "studentAccepted": 0,
    "maxRegister": 6,
    "maxAcceptedStudent": 2,
    "timestamp": 1748491298
  },
  {
    "studentRegister": 1,
    "studentAccepted": 0,
    "maxRegister": 6,
    "maxAcceptedStudent": 2,
    "timestamp": 1748492821
  },
  {
    "studentRegister": 1,
    "studentAccepted": 0,
    "maxRegister": 6,
    "maxAcceptedStudent": 2,
    "timestamp": 1748494015
  },
  {
    "studentRegister": 1,
    "studentAccepted": 0,
    "maxRegister": 6,
    "maxAcceptedStudent": 2,
    "timestamp": 1748494662
  },
  {
    "studentRegister": 1,
    "studentAccepted": 0,
    "maxRegister": 6,
    "maxAcceptedStudent": 2,
    "timestamp": 1748495612
  },
  {
    "studentRegister": 1,
    "studentAccepted": 0,
    "maxRegister": 6,
    "maxAcceptedStudent": 2,
    "timestamp": 1748496979
  },
  {
    "studentRegister": 1,
    "studentAccepted": 0,
    "maxRegister": 6,
    "maxAcceptedStudent": 2,
    "timestamp": 1748497760
  },
  {
    "studentRegister": 1,
    "studentAccepted": 0,
    "maxRegister": 6,
    "maxAcceptedStudent": 2,
    "timestamp": 1748498158
  },
  {
    "studentRegister": 1,
    "studentAccepted": 0,
    "maxRegister": 6,
    "maxAcceptedStudent": 2,
    "timestamp": 1748498567
  },
  {
    "studentRegister": 1,
    "studentAccepted": 0,
    "maxRegister": 6,
    "maxAcceptedStudent": 2,
    "timestamp": 1748500447
  },
  {
    "studentRegister": 1,
    "studentAccepted": 0,
    "maxRegister": 6,
    "maxAcceptedStudent": 2,
    "timestamp": 1748501687
  },
  {
    "studentRegister": 2,
    "studentAccepted": 0,
    "maxRegister": 6,
    "maxAcceptedStudent": 2,
    "timestamp": 1748502138
  },
  {
    "studentRegister": 2,
    "studentAccepted": 0,
    "maxRegister": 6,
    "maxAcceptedStudent": 2,
    "timestamp": 1748503346
  },
  {
    "studentRegister": 2,
    "studentAccepted": 0,
    "maxRegister": 6,
    "maxAcceptedStudent": 2,
    "timestamp": 1748504136
  },
  {
    "studentRegister": 2,
    "studentAccepted": 0,
    "maxRegister": 6,
    "maxAcceptedStudent": 2,
    "timestamp": 1748504745
  },
  {
    "studentRegister": 2,
    "studentAccepted": 0,
    "maxRegister": 6,
    "maxAcceptedStudent": 2,
    "timestamp": 1748505151
  },
  {
    "studentRegister": 2,
    "studentAccepted": 0,
    "maxRegister": 6,
    "maxAcceptedStudent": 2,
    "timestamp": 1748505547
  },
  {
    "studentRegister": 2,
    "studentAccepted": 0,
    "maxRegister": 6,
    "maxAcceptedStudent": 2,
    "timestamp": 1748506837
  },
  {
    "studentRegister": 2,
    "studentAccepted": 0,
    "maxRegister": 6,
    "maxAcceptedStudent": 2,
    "timestamp": 1748508353
  },
  {
    "studentRegister": 2,
    "studentAccepted": 0,
    "maxRegister": 6,
    "maxAcceptedStudent": 2,
    "timestamp": 1748509104
  },
  {
    "studentRegister": 3,
    "studentAccepted": 0,
    "maxRegister": 6,
    "maxAcceptedStudent": 2,
    "timestamp": 1748510118
  },
  {
    "studentRegister": 3,
    "studentAccepted": 0,
    "maxRegister": 6,
    "maxAcceptedStudent": 2,
    "timestamp": 1748511340
  },
  {
    "studentRegister": 3,
    "studentAccepted": 0,
    "maxRegister": 6,
    "maxAcceptedStudent": 2,
    "timestamp": 1748512048
  },
  {
    "studentRegister": 3,
    "studentAccepted": 0,
    "maxRegister": 6,
    "maxAcceptedStudent": 2,
    "timestamp": 1748512455
  },
  {
    "studentRegister": 3,
    "studentAccepted": 0,
    "maxRegister": 6,
    "maxAcceptedStudent": 2,
    "timestamp": 1748512842
  },
  {
    "studentRegister": 3,
    "studentAccepted": 0,
    "maxRegister": 6,
    "maxAcceptedStudent": 2,
    "timestamp": 1748514063
  },
  {
    "studentRegister": 3,
    "studentAccepted": 0,
    "maxRegister": 6,
    "maxAcceptedStudent": 2,
    "timestamp": 1748515486
  },
  {
    "studentRegister": 3,
    "studentAccepted": 0,
    "maxRegister": 6,
    "maxAcceptedStudent": 2,
    "timestamp": 1748516129
  },
  {
    "studentRegister": 3,
    "studentAccepted": 0,
    "maxRegister": 6,
    "maxAcceptedStudent": 2,
    "timestamp": 1748516534
  },
  {
    "studentRegister": 3,
    "studentAccepted": 0,
    "maxRegister": 6,
    "maxAcceptedStudent": 2,
    "timestamp": 1748517583
  },
  {
    "studentRegister": 3,
    "studentAccepted": 0,
    "maxRegister": 6,
    "maxAcceptedStudent": 2,
    "timestamp": 1748518317
  },
  {
    "studentRegister": 3,
    "studentAccepted": 0,
    "maxRegister": 6,
    "maxAcceptedStudent": 2,
    "timestamp": 1748518868
  },
  {
    "studentRegister": 3,
    "studentAccepted": 0,
    "maxRegister": 6,
    "maxAcceptedStudent": 2,
    "timestamp": 1748519272
  },
  {
    "studentRegister": 3,
    "studentAccepted": 0,
    "maxRegister": 6,
    "maxAcceptedStudent": 2,
    "timestamp": 1748519683
  },
  {
    "studentRegister": 3,
    "studentAccepted": 0,
    "maxRegister": 6,
    "maxAcceptedStudent": 2,
    "timestamp": 1748520088
  },
  {
    "studentRegister": 3,
    "studentAccepted": 0,
    "maxRegister": 6,
    "maxAcceptedStudent": 2,
    "timestamp": 1748522329
  },
  {
    "studentRegister": 3,
    "studentAccepted": 0,
    "maxRegister": 6,
    "maxAcceptedStudent": 2,
    "timestamp": 1748524321
  },
  {
    "studentRegister": 4,
    "studentAccepted": 0,
    "maxRegister": 6,
    "maxAcceptedStudent": 2,
    "timestamp": 1748526077
  },
  {
    "studentRegister": 4,
    "studentAccepted": 0,
    "maxRegister": 6,
    "maxAcceptedStudent": 2,
    "timestamp": 1748526752
  },
  {
    "studentRegister": 4,
    "studentAccepted": 0,
    "maxRegister": 6,
    "maxAcceptedStudent": 2,
    "timestamp": 1748527159
  },
  {
    "studentRegister": 4,
    "studentAccepted": 0,
    "maxRegister": 6,
    "maxAcceptedStudent": 2,
    "timestamp": 1748528143
  },
  {
    "studentRegister": 4,
    "studentAccepted": 0,
    "maxRegister": 6,
    "maxAcceptedStudent": 2,
    "timestamp": 1748529428
  },
  {
    "studentRegister": 4,
    "studentAccepted": 0,
    "maxRegister": 6,
    "maxAcceptedStudent": 2,
    "timestamp": 1748530199
  },
  {
    "studentRegister": 4,
    "studentAccepted": 0,
    "maxRegister": 6,
    "maxAcceptedStudent": 2,
    "timestamp": 1748530614
  },
  {
    "studentRegister": 4,
    "studentAccepted": 0,
    "maxRegister": 6,
    "maxAcceptedStudent": 2,
    "timestamp": 1748531019
  },
  {
    "studentRegister": 4,
    "studentAccepted": 0,
    "maxRegister": 6,
    "maxAcceptedStudent": 2,
    "timestamp": 1748532434
  },
  {
    "studentRegister": 4,
    "studentAccepted": 0,
    "maxRegister": 6,
    "maxAcceptedStudent": 2,
    "timestamp": 1748533336
  },
  {
    "studentRegister": 4,
    "studentAccepted": 0,
    "maxRegister": 6,
    "maxAcceptedStudent": 2,
    "timestamp": 1748533870
  },
  {
    "studentRegister": 4,
    "studentAccepted": 0,
    "maxRegister": 6,
    "maxAcceptedStudent": 2,
    "timestamp": 1748534294
  },
  {
    "studentRegister": 4,
    "studentAccepted": 0,
    "maxRegister": 6,
    "maxAcceptedStudent": 2,
    "timestamp": 1748535331
  },
  {
    "studentRegister": 4,
    "studentAccepted": 0,
    "maxRegister": 6,
    "maxAcceptedStudent": 2,
    "timestamp": 1748537012
  },
  {
    "studentRegister": 4,
    "studentAccepted": 0,
    "maxRegister": 6,
    "maxAcceptedStudent": 2,
    "timestamp": 1748537901
  },
  {
    "studentRegister": 4,
    "studentAccepted": 0,
    "maxRegister": 6,
    "maxAcceptedStudent": 2,
    "timestamp": 1748538748
  },
  {
    "studentRegister": 4,
    "studentAccepted": 0,
    "maxRegister": 6,
    "maxAcceptedStudent": 2,
    "timestamp": 1748540610
  },
  {
    "studentRegister": 4,
    "studentAccepted": 0,
    "maxRegister": 6,
    "maxAcceptedStudent": 2,
    "timestamp": 1748541145
  },
  {
    "studentRegister": 4,
    "studentAccepted": 0,
    "maxRegister": 6,
    "maxAcceptedStudent": 2,
    "timestamp": 1748541539
  },
  {
    "studentRegister": 4,
    "studentAccepted": 0,
    "maxRegister": 6,
    "maxAcceptedStudent": 2,
    "timestamp": 1748542779
  },
  {
    "studentRegister": 4,
    "studentAccepted": 0,
    "maxRegister": 6,
    "maxAcceptedStudent": 2,
    "timestamp": 1748544435
  },
  {
    "studentRegister": 4,
    "studentAccepted": 0,
    "maxRegister": 6,
    "maxAcceptedStudent": 2,
    "timestamp": 1748545105
  },
  {
    "studentRegister": 4,
    "studentAccepted": 0,
    "maxRegister": 6,
    "maxAcceptedStudent": 2,
    "timestamp": 1748545915
  },
  {
    "studentRegister": 4,
    "studentAccepted": 0,
    "maxRegister": 6,
    "maxAcceptedStudent": 2,
    "timestamp": 1748546689
  },
  {
    "studentRegister": 4,
    "studentAccepted": 0,
    "maxRegister": 6,
    "maxAcceptedStudent": 2,
    "timestamp": 1748547172
  },
  {
    "studentRegister": 4,
    "studentAccepted": 0,
    "maxRegister": 6,
    "maxAcceptedStudent": 2,
    "timestamp": 1748547691
  },
  {
    "studentRegister": 4,
    "studentAccepted": 0,
    "maxRegister": 6,
    "maxAcceptedStudent": 2,
    "timestamp": 1748548090
  },
  {
    "studentRegister": 4,
    "studentAccepted": 0,
    "maxRegister": 6,
    "maxAcceptedStudent": 2,
    "timestamp": 1748548496
  },
  {
    "studentRegister": 4,
    "studentAccepted": 0,
    "maxRegister": 6,
    "maxAcceptedStudent": 2,
    "timestamp": 1748548897
  },
  {
    "studentRegister": 4,
    "studentAccepted": 0,
    "maxRegister": 6,
    "maxAcceptedStudent": 2,
    "timestamp": 1748550221
  },
  {
    "studentRegister": 4,
    "studentAccepted": 0,
    "maxRegister": 6,
    "maxAcceptedStudent": 2,
    "timestamp": 1748551244
  },
  {
    "studentRegister": 4,
    "studentAccepted": 0,
    "maxRegister": 6,
    "maxAcceptedStudent": 2,
    "timestamp": 1748551843
  },
  {
    "studentRegister": 4,
    "studentAccepted": 0,
    "maxRegister": 6,
    "maxAcceptedStudent": 2,
    "timestamp": 1748552257
  },
  {
    "studentRegister": 4,
    "studentAccepted": 0,
    "maxRegister": 6,
    "maxAcceptedStudent": 2,
    "timestamp": 1748553100
  },
  {
    "studentRegister": 4,
    "studentAccepted": 0,
    "maxRegister": 6,
    "maxAcceptedStudent": 2,
    "timestamp": 1748554237
  },
  {
    "studentRegister": 4,
    "studentAccepted": 0,
    "maxRegister": 6,
    "maxAcceptedStudent": 2,
    "timestamp": 1748554819
  },
  {
    "studentRegister": 4,
    "studentAccepted": 0,
    "maxRegister": 6,
    "maxAcceptedStudent": 2,
    "timestamp": 1748555328
  },
  {
    "studentRegister": 4,
    "studentAccepted": 0,
    "maxRegister": 6,
    "maxAcceptedStudent": 2,
    "timestamp": 1748555736
  },
  {
    "studentRegister": 4,
    "studentAccepted": 0,
    "maxRegister": 6,
    "maxAcceptedStudent": 2,
    "timestamp": 1748556130
  },
  {
    "studentRegister": 4,
    "studentAccepted": 0,
    "maxRegister": 6,
    "maxAcceptedStudent": 2,
    "timestamp": 1748557297
  },
  {
    "studentRegister": 4,
    "studentAccepted": 0,
    "maxRegister": 6,
    "maxAcceptedStudent": 2,
    "timestamp": 1748558439
  },
  {
    "studentRegister": 4,
    "studentAccepted": 0,
    "maxRegister": 6,
    "maxAcceptedStudent": 2,
    "timestamp": 1748559045
  },
  {
    "studentRegister": 4,
    "studentAccepted": 0,
    "maxRegister": 6,
    "maxAcceptedStudent": 2,
    "timestamp": 1748559434
  },
  {
    "studentRegister": 4,
    "studentAccepted": 0,
    "maxRegister": 6,
    "maxAcceptedStudent": 2,
    "timestamp": 1748559979
  },
  {
    "studentRegister": 4,
    "studentAccepted": 0,
    "maxRegister": 6,
    "maxAcceptedStudent": 2,
    "timestamp": 1748561284
  },
  {
    "studentRegister": 4,
    "studentAccepted": 0,
    "maxRegister": 6,
    "maxAcceptedStudent": 2,
    "timestamp": 1748561907
  },
  {
    "studentRegister": 4,
    "studentAccepted": 0,
    "maxRegister": 6,
    "maxAcceptedStudent": 2,
    "timestamp": 1748562477
  },
  {
    "studentRegister": 4,
    "studentAccepted": 0,
    "maxRegister": 6,
    "maxAcceptedStudent": 2,
    "timestamp": 1748562862
  },
  {
    "studentRegister": 4,
    "studentAccepted": 0,
    "maxRegister": 6,
    "maxAcceptedStudent": 2,
    "timestamp": 1748563271
  },
  {
    "studentRegister": 4,
    "studentAccepted": 0,
    "maxRegister": 6,
    "maxAcceptedStudent": 2,
    "timestamp": 1748568101
  },
  {
    "studentRegister": 4,
    "studentAccepted": 0,
    "maxRegister": 6,
    "maxAcceptedStudent": 2,
    "timestamp": 1748573658
  },
  {
    "studentRegister": 4,
    "studentAccepted": 0,
    "maxRegister": 6,
    "maxAcceptedStudent": 2,
    "timestamp": 1748576291
  },
  {
    "studentRegister": 4,
    "studentAccepted": 0,
    "maxRegister": 6,
    "maxAcceptedStudent": 2,
    "timestamp": 1748577661
  },
  {
    "studentRegister": 5,
    "studentAccepted": 0,
    "maxRegister": 6,
    "maxAcceptedStudent": 2,
    "timestamp": 1748579042
  },
  {
    "studentRegister": 5,
    "studentAccepted": 0,
    "maxRegister": 6,
    "maxAcceptedStudent": 2,
    "timestamp": 1748580334
  },
  {
    "studentRegister": 5,
    "studentAccepted": 0,
    "maxRegister": 6,
    "maxAcceptedStudent": 2,
    "timestamp": 1748580990
  },
  {
    "studentRegister": 5,
    "studentAccepted": 0,
    "maxRegister": 6,
    "maxAcceptedStudent": 2,
    "timestamp": 1748581390
  },
  {
    "studentRegister": 5,
    "studentAccepted": 0,
    "maxRegister": 6,
    "maxAcceptedStudent": 2,
    "timestamp": 1748582636
  },
  {
    "studentRegister": 5,
    "studentAccepted": 0,
    "maxRegister": 6,
    "maxAcceptedStudent": 2,
    "timestamp": 1748583706
  },
  {
    "studentRegister": 5,
    "studentAccepted": 0,
    "maxRegister": 6,
    "maxAcceptedStudent": 2,
    "timestamp": 1748584294
  },
  {
    "studentRegister": 5,
    "studentAccepted": 0,
    "maxRegister": 6,
    "maxAcceptedStudent": 2,
    "timestamp": 1748584698
  },
  {
    "studentRegister": 5,
    "studentAccepted": 0,
    "maxRegister": 6,
    "maxAcceptedStudent": 2,
    "timestamp": 1748585901
  },
  {
    "studentRegister": 4,
    "studentAccepted": 0,
    "maxRegister": 6,
    "maxAcceptedStudent": 2,
    "timestamp": 1748587634
  },
  {
    "studentRegister": 4,
    "studentAccepted": 0,
    "maxRegister": 6,
    "maxAcceptedStudent": 2,
    "timestamp": 1748588382
  },
  {
    "studentRegister": 4,
    "studentAccepted": 0,
    "maxRegister": 6,
    "maxAcceptedStudent": 2,
    "timestamp": 1748589392
  },
  {
    "studentRegister": 4,
    "studentAccepted": 0,
    "maxRegister": 6,
    "maxAcceptedStudent": 2,
    "timestamp": 1748590342
  },
  {
    "studentRegister": 4,
    "studentAccepted": 0,
    "maxRegister": 6,
    "maxAcceptedStudent": 2,
    "timestamp": 1748590926
  },
  {
    "studentRegister": 4,
    "studentAccepted": 0,
    "maxRegister": 6,
    "maxAcceptedStudent": 2,
    "timestamp": 1748591329
  },
  {
    "studentRegister": 5,
    "studentAccepted": 0,
    "maxRegister": 6,
    "maxAcceptedStudent": 2,
    "timestamp": 1748591729
  },
  {
    "studentRegister": 5,
    "studentAccepted": 0,
    "maxRegister": 6,
    "maxAcceptedStudent": 2,
    "timestamp": 1748592132
  },
  {
    "studentRegister": 5,
    "studentAccepted": 0,
    "maxRegister": 6,
    "maxAcceptedStudent": 2,
    "timestamp": 1748593745
  },
  {
    "studentRegister": 5,
    "studentAccepted": 0,
    "maxRegister": 6,
    "maxAcceptedStudent": 2,
    "timestamp": 1748594873
  },
  {
    "studentRegister": 5,
    "studentAccepted": 0,
    "maxRegister": 6,
    "maxAcceptedStudent": 2,
    "timestamp": 1748595534
  },
  {
    "studentRegister": 5,
    "studentAccepted": 0,
    "maxRegister": 6,
    "maxAcceptedStudent": 2,
    "timestamp": 1748596547
  },
  {
    "studentRegister": 5,
    "studentAccepted": 0,
    "maxRegister": 6,
    "maxAcceptedStudent": 2,
    "timestamp": 1748597697
  },
  {
    "studentRegister": 5,
    "studentAccepted": 0,
    "maxRegister": 6,
    "maxAcceptedStudent": 2,
    "timestamp": 1748598394
  },
  {
    "studentRegister": 5,
    "studentAccepted": 0,
    "maxRegister": 6,
    "maxAcceptedStudent": 2,
    "timestamp": 1748598813
  },
  {
    "studentRegister": 5,
    "studentAccepted": 0,
    "maxRegister": 6,
    "maxAcceptedStudent": 2,
    "timestamp": 1748599219
  },
  {
    "studentRegister": 5,
    "studentAccepted": 0,
    "maxRegister": 6,
    "maxAcceptedStudent": 2,
    "timestamp": 1748600344
  },
  {
    "studentRegister": 5,
    "studentAccepted": 0,
    "maxRegister": 6,
    "maxAcceptedStudent": 2,
    "timestamp": 1748601685
  },
  {
    "studentRegister": 4,
    "studentAccepted": 1,
    "maxRegister": 6,
    "maxAcceptedStudent": 2,
    "timestamp": 1748602320
  },
  {
    "studentRegister": 4,
    "studentAccepted": 1,
    "maxRegister": 6,
    "maxAcceptedStudent": 2,
    "timestamp": 1748602712
  },
  {
    "studentRegister": 0,
    "studentAccepted": 1,
    "maxRegister": 6,
    "maxAcceptedStudent": 2,
    "timestamp": 1748603558
  },
  {
    "studentRegister": 0,
    "studentAccepted": 1,
    "maxRegister": 6,
    "maxAcceptedStudent": 2,
    "timestamp": 1748604465
  },
  {
    "studentRegister": 0,
    "studentAccepted": 1,
    "maxRegister": 6,
    "maxAcceptedStudent": 2,
    "timestamp": 1748604977
  },
  {
    "studentRegister": 0,
    "studentAccepted": 1,
    "maxRegister": 6,
    "maxAcceptedStudent": 2,
    "timestamp": 1748605467
  },
  {
    "studentRegister": 0,
    "studentAccepted": 1,
    "maxRegister": 6,
    "maxAcceptedStudent": 2,
    "timestamp": 1748605870
  },
  {
    "studentRegister": 0,
    "studentAccepted": 1,
    "maxRegister": 6,
    "maxAcceptedStudent": 2,
    "timestamp": 1748606279
  },
  {
    "studentRegister": 0,
    "studentAccepted": 1,
    "maxRegister": 6,
    "maxAcceptedStudent": 2,
    "timestamp": 1748607679
  },
  {
    "studentRegister": 0,
    "studentAccepted": 1,
    "maxRegister": 6,
    "maxAcceptedStudent": 2,
    "timestamp": 1748610234
  },
  {
    "studentRegister": 0,
    "studentAccepted": 1,
    "maxRegister": 6,
    "maxAcceptedStudent": 2,
    "timestamp": 1748612170
  },
  {
    "studentRegister": 0,
    "studentAccepted": 1,
    "maxRegister": 6,
    "maxAcceptedStudent": 2,
    "timestamp": 1748613046
  },
  {
    "studentRegister": 0,
    "studentAccepted": 1,
    "maxRegister": 6,
    "maxAcceptedStudent": 2,
    "timestamp": 1748613453
  },
  {
    "studentRegister": 0,
    "studentAccepted": 1,
    "maxRegister": 6,
    "maxAcceptedStudent": 2,
    "timestamp": 1748614369
  },
  {
    "studentRegister": 0,
    "studentAccepted": 1,
    "maxRegister": 6,
    "maxAcceptedStudent": 2,
    "timestamp": 1748615758
  },
  {
    "studentRegister": 0,
    "studentAccepted": 1,
    "maxRegister": 6,
    "maxAcceptedStudent": 2,
    "timestamp": 1748616574
  },
  {
    "studentRegister": 0,
    "studentAccepted": 1,
    "maxRegister": 6,
    "maxAcceptedStudent": 2,
    "timestamp": 1748616978
  },
  {
    "studentRegister": 0,
    "studentAccepted": 1,
    "maxRegister": 6,
    "maxAcceptedStudent": 2,
    "timestamp": 1748617371
  },
  {
    "studentRegister": 0,
    "studentAccepted": 1,
    "maxRegister": 6,
    "maxAcceptedStudent": 2,
    "timestamp": 1748618719
  },
  {
    "studentRegister": 0,
    "studentAccepted": 1,
    "maxRegister": 6,
    "maxAcceptedStudent": 2,
    "timestamp": 1748619648
  },
  {
    "studentRegister": 0,
    "studentAccepted": 1,
    "maxRegister": 6,
    "maxAcceptedStudent": 2,
    "timestamp": 1748620193
  },
  {
    "studentRegister": 0,
    "studentAccepted": 1,
    "maxRegister": 6,
    "maxAcceptedStudent": 2,
    "timestamp": 1748620598
  },
  {
    "studentRegister": 0,
    "studentAccepted": 1,
    "maxRegister": 6,
    "maxAcceptedStudent": 2,
    "timestamp": 1748620998
  },
  {
    "studentRegister": 0,
    "studentAccepted": 1,
    "maxRegister": 6,
    "maxAcceptedStudent": 2,
    "timestamp": 1748622693
  },
  {
    "studentRegister": 0,
    "studentAccepted": 1,
    "maxRegister": 6,
    "maxAcceptedStudent": 2,
    "timestamp": 1748623811
  },
  {
    "studentRegister": 0,
    "studentAccepted": 1,
    "maxRegister": 6,
    "maxAcceptedStudent": 2,
    "timestamp": 1748624388
  },
  {
    "studentRegister": 0,
    "studentAccepted": 1,
    "maxRegister": 6,
    "maxAcceptedStudent": 2,
    "timestamp": 1748625307
  },
  {
    "studentRegister": 0,
    "studentAccepted": 1,
    "maxRegister": 6,
    "maxAcceptedStudent": 2,
    "timestamp": 1748626422
  },
  {
    "studentRegister": 0,
    "studentAccepted": 1,
    "maxRegister": 6,
    "maxAcceptedStudent": 2,
    "timestamp": 1748627134
  },
  {
    "studentRegister": 0,
    "studentAccepted": 1,
    "maxRegister": 6,
    "maxAcceptedStudent": 2,
    "timestamp": 1748627543
  },
  {
    "studentRegister": 0,
    "studentAccepted": 1,
    "maxRegister": 6,
    "maxAcceptedStudent": 2,
    "timestamp": 1748627933
  },
  {
    "studentRegister": 0,
    "studentAccepted": 1,
    "maxRegister": 6,
    "maxAcceptedStudent": 2,
    "timestamp": 1748629168
  },
  {
    "studentRegister": 0,
    "studentAccepted": 1,
    "maxRegister": 6,
    "maxAcceptedStudent": 2,
    "timestamp": 1748630800
  },
  {
    "studentRegister": 0,
    "studentAccepted": 1,
    "maxRegister": 6,
    "maxAcceptedStudent": 2,
    "timestamp": 1748631450
  },
  {
    "studentRegister": 0,
    "studentAccepted": 1,
    "maxRegister": 6,
    "maxAcceptedStudent": 2,
    "timestamp": 1748632234
  },
  {
    "studentRegister": 0,
    "studentAccepted": 1,
    "maxRegister": 6,
    "maxAcceptedStudent": 2,
    "timestamp": 1748633144
  },
  {
    "studentRegister": 0,
    "studentAccepted": 1,
    "maxRegister": 6,
    "maxAcceptedStudent": 2,
    "timestamp": 1748633537
  },
  {
    "studentRegister": 0,
    "studentAccepted": 1,
    "maxRegister": 6,
    "maxAcceptedStudent": 2,
    "timestamp": 1748634037
  },
  {
    "studentRegister": 0,
    "studentAccepted": 1,
    "maxRegister": 6,
    "maxAcceptedStudent": 2,
    "timestamp": 1748634444
  },
  {
    "studentRegister": 0,
    "studentAccepted": 1,
    "maxRegister": 6,
    "maxAcceptedStudent": 2,
    "timestamp": 1748634863
  },
  {
    "studentRegister": 0,
    "studentAccepted": 1,
    "maxRegister": 6,
    "maxAcceptedStudent": 2,
    "timestamp": 1748635257
  },
  {
    "studentRegister": 0,
    "studentAccepted": 1,
    "maxRegister": 6,
    "maxAcceptedStudent": 2,
    "timestamp": 1748636474
  },
  {
    "studentRegister": 0,
    "studentAccepted": 1,
    "maxRegister": 6,
    "maxAcceptedStudent": 2,
    "timestamp": 1748637478
  },
  {
    "studentRegister": 0,
    "studentAccepted": 1,
    "maxRegister": 6,
    "maxAcceptedStudent": 2,
    "timestamp": 1748638173
  },
  {
    "studentRegister": 0,
    "studentAccepted": 1,
    "maxRegister": 6,
    "maxAcceptedStudent": 2,
    "timestamp": 1748638613
  },
  {
    "studentRegister": 0,
    "studentAccepted": 1,
    "maxRegister": 6,
    "maxAcceptedStudent": 2,
    "timestamp": 1748639012
  },
  {
    "studentRegister": 0,
    "studentAccepted": 1,
    "maxRegister": 6,
    "maxAcceptedStudent": 2,
    "timestamp": 1748640183
  },
  {
    "studentRegister": 0,
    "studentAccepted": 1,
    "maxRegister": 6,
    "maxAcceptedStudent": 2,
    "timestamp": 1748640871
  },
  {
    "studentRegister": 0,
    "studentAccepted": 1,
    "maxRegister": 6,
    "maxAcceptedStudent": 2,
    "timestamp": 1748641436
  },
  {
    "studentRegister": 0,
    "studentAccepted": 1,
    "maxRegister": 6,
    "maxAcceptedStudent": 2,
    "timestamp": 1748641836
  },
  {
    "studentRegister": 0,
    "studentAccepted": 1,
    "maxRegister": 6,
    "maxAcceptedStudent": 2,
    "timestamp": 1748642252
  },
  {
    "studentRegister": 0,
    "studentAccepted": 1,
    "maxRegister": 6,
    "maxAcceptedStudent": 2,
    "timestamp": 1748643095
  },
  {
    "studentRegister": 0,
    "studentAccepted": 1,
    "maxRegister": 6,
    "maxAcceptedStudent": 2,
    "timestamp": 1748644452
  },
  {
    "studentRegister": 0,
    "studentAccepted": 1,
    "maxRegister": 6,
    "maxAcceptedStudent": 2,
    "timestamp": 1748645201
  },
  {
    "studentRegister": 0,
    "studentAccepted": 1,
    "maxRegister": 6,
    "maxAcceptedStudent": 2,
    "timestamp": 1748645619
  },
  {
    "studentRegister": 0,
    "studentAccepted": 1,
    "maxRegister": 6,
    "maxAcceptedStudent": 2,
    "timestamp": 1748646010
  },
  {
    "studentRegister": 0,
    "studentAccepted": 1,
    "maxRegister": 6,
    "maxAcceptedStudent": 2,
    "timestamp": 1748647009
  },
  {
    "studentRegister": 0,
    "studentAccepted": 1,
    "maxRegister": 6,
    "maxAcceptedStudent": 2,
    "timestamp": 1748647960
  },
  {
    "studentRegister": 0,
    "studentAccepted": 1,
    "maxRegister": 6,
    "maxAcceptedStudent": 2,
    "timestamp": 1748648571
  },
  {
    "studentRegister": 0,
    "studentAccepted": 1,
    "maxRegister": 6,
    "maxAcceptedStudent": 2,
    "timestamp": 1748648968
  },
  {
    "studentRegister": 0,
    "studentAccepted": 1,
    "maxRegister": 6,
    "maxAcceptedStudent": 2,
    "timestamp": 1748649387
  },
  {
    "studentRegister": 0,
    "studentAccepted": 1,
    "maxRegister": 6,
    "maxAcceptedStudent": 2,
    "timestamp": 1748649781
  },
  {
    "studentRegister": 0,
    "studentAccepted": 1,
    "maxRegister": 6,
    "maxAcceptedStudent": 2,
    "timestamp": 1748656041
  },
  {
    "studentRegister": 0,
    "studentAccepted": 1,
    "maxRegister": 6,
    "maxAcceptedStudent": 2,
    "timestamp": 1748660757
  },
  {
    "studentRegister": 0,
    "studentAccepted": 1,
    "maxRegister": 6,
    "maxAcceptedStudent": 2,
    "timestamp": 1748663240
  },
  {
    "studentRegister": 0,
    "studentAccepted": 1,
    "maxRegister": 6,
    "maxAcceptedStudent": 2,
    "timestamp": 1748664189
  },
  {
    "studentRegister": 0,
    "studentAccepted": 1,
    "maxRegister": 6,
    "maxAcceptedStudent": 2,
    "timestamp": 1748665742
  },
  {
    "studentRegister": 0,
    "studentAccepted": 1,
    "maxRegister": 6,
    "maxAcceptedStudent": 2,
    "timestamp": 1748666796
  },
  {
    "studentRegister": 0,
    "studentAccepted": 1,
    "maxRegister": 6,
    "maxAcceptedStudent": 2,
    "timestamp": 1748667463
  },
  {
    "studentRegister": 0,
    "studentAccepted": 1,
    "maxRegister": 6,
    "maxAcceptedStudent": 2,
    "timestamp": 1748668321
  },
  {
    "studentRegister": 0,
    "studentAccepted": 1,
    "maxRegister": 6,
    "maxAcceptedStudent": 2,
    "timestamp": 1748669601
  },
  {
    "studentRegister": 0,
    "studentAccepted": 1,
    "maxRegister": 6,
    "maxAcceptedStudent": 2,
    "timestamp": 1748670296
  },
  {
    "studentRegister": 0,
    "studentAccepted": 1,
    "maxRegister": 6,
    "maxAcceptedStudent": 2,
    "timestamp": 1748670696
  },
  {
    "studentRegister": 0,
    "studentAccepted": 1,
    "maxRegister": 6,
    "maxAcceptedStudent": 2,
    "timestamp": 1748671100
  },
  {
    "studentRegister": 0,
    "studentAccepted": 1,
    "maxRegister": 6,
    "maxAcceptedStudent": 2,
    "timestamp": 1748672225
  },
  {
    "studentRegister": 0,
    "studentAccepted": 1,
    "maxRegister": 6,
    "maxAcceptedStudent": 2,
    "timestamp": 1748673787
  },
  {
    "studentRegister": 0,
    "studentAccepted": 1,
    "maxRegister": 6,
    "maxAcceptedStudent": 2,
    "timestamp": 1748674474
  },
  {
    "studentRegister": 0,
    "studentAccepted": 1,
    "maxRegister": 6,
    "maxAcceptedStudent": 2,
    "timestamp": 1748674886
  },
  {
    "studentRegister": 0,
    "studentAccepted": 1,
    "maxRegister": 6,
    "maxAcceptedStudent": 2,
    "timestamp": 1748675943
  },
  {
    "studentRegister": 0,
    "studentAccepted": 1,
    "maxRegister": 6,
    "maxAcceptedStudent": 2,
    "timestamp": 1748676709
  },
  {
    "studentRegister": 0,
    "studentAccepted": 1,
    "maxRegister": 6,
    "maxAcceptedStudent": 2,
    "timestamp": 1748677237
  },
  {
    "studentRegister": 0,
    "studentAccepted": 1,
    "maxRegister": 6,
    "maxAcceptedStudent": 2,
    "timestamp": 1748677630
  },
  {
    "studentRegister": 0,
    "studentAccepted": 1,
    "maxRegister": 6,
    "maxAcceptedStudent": 2,
    "timestamp": 1748678019
  },
  {
    "studentRegister": 0,
    "studentAccepted": 1,
    "maxRegister": 6,
    "maxAcceptedStudent": 2,
    "timestamp": 1748678431
  },
  {
    "studentRegister": 0,
    "studentAccepted": 1,
    "maxRegister": 6,
    "maxAcceptedStudent": 2,
    "timestamp": 1748679720
  },
  {
    "studentRegister": 0,
    "studentAccepted": 1,
    "maxRegister": 6,
    "maxAcceptedStudent": 2,
    "timestamp": 1748680951
  },
  {
    "studentRegister": 0,
    "studentAccepted": 1,
    "maxRegister": 6,
    "maxAcceptedStudent": 2,
    "timestamp": 1748681648
  },
  {
    "studentRegister": 0,
    "studentAccepted": 1,
    "maxRegister": 6,
    "maxAcceptedStudent": 2,
    "timestamp": 1748682054
  },
  {
    "studentRegister": 0,
    "studentAccepted": 1,
    "maxRegister": 6,
    "maxAcceptedStudent": 2,
    "timestamp": 1748683134
  },
  {
    "studentRegister": 0,
    "studentAccepted": 1,
    "maxRegister": 6,
    "maxAcceptedStudent": 2,
    "timestamp": 1748684041
  },
  {
    "studentRegister": 0,
    "studentAccepted": 1,
    "maxRegister": 6,
    "maxAcceptedStudent": 2,
    "timestamp": 1748684616
  },
  {
    "studentRegister": 0,
    "studentAccepted": 1,
    "maxRegister": 6,
    "maxAcceptedStudent": 2,
    "timestamp": 1748685021
  },
  {
    "studentRegister": 0,
    "studentAccepted": 1,
    "maxRegister": 6,
    "maxAcceptedStudent": 2,
    "timestamp": 1748685422
  },
  {
    "studentRegister": 0,
    "studentAccepted": 1,
    "maxRegister": 6,
    "maxAcceptedStudent": 2,
    "timestamp": 1748685815
  },
  {
    "studentRegister": 0,
    "studentAccepted": 1,
    "maxRegister": 6,
    "maxAcceptedStudent": 2,
    "timestamp": 1748687114
  },
  {
    "studentRegister": 0,
    "studentAccepted": 1,
    "maxRegister": 6,
    "maxAcceptedStudent": 2,
    "timestamp": 1748688121
  },
  {
    "studentRegister": 0,
    "studentAccepted": 1,
    "maxRegister": 6,
    "maxAcceptedStudent": 2,
    "timestamp": 1748688611
  },
  {
    "studentRegister": 0,
    "studentAccepted": 1,
    "maxRegister": 6,
    "maxAcceptedStudent": 2,
    "timestamp": 1748689030
  },
  {
    "studentRegister": 0,
    "studentAccepted": 1,
    "maxRegister": 6,
    "maxAcceptedStudent": 2,
    "timestamp": 1748689417
  },
  {
    "studentRegister": 0,
    "studentAccepted": 1,
    "maxRegister": 6,
    "maxAcceptedStudent": 2,
    "timestamp": 1748690408
  },
  {
    "studentRegister": 0,
    "studentAccepted": 1,
    "maxRegister": 6,
    "maxAcceptedStudent": 2,
    "timestamp": 1748690998
  },
  {
    "studentRegister": 0,
    "studentAccepted": 1,
    "maxRegister": 6,
    "maxAcceptedStudent": 2,
    "timestamp": 1748691523
  },
  {
    "studentRegister": 0,
    "studentAccepted": 1,
    "maxRegister": 6,
    "maxAcceptedStudent": 2,
    "timestamp": 1748691927
  },
  {
    "studentRegister": 0,
    "studentAccepted": 1,
    "maxRegister": 6,
    "maxAcceptedStudent": 2,
    "timestamp": 1748692337
  },
  {
    "studentRegister": 0,
    "studentAccepted": 1,
    "maxRegister": 6,
    "maxAcceptedStudent": 2,
    "timestamp": 1748692746
  },
  {
    "studentRegister": 0,
    "studentAccepted": 1,
    "maxRegister": 6,
    "maxAcceptedStudent": 2,
    "timestamp": 1748694271
  },
  {
    "studentRegister": 0,
    "studentAccepted": 1,
    "maxRegister": 6,
    "maxAcceptedStudent": 2,
    "timestamp": 1748696448
  },
  {
    "studentRegister": 0,
    "studentAccepted": 1,
    "maxRegister": 6,
    "maxAcceptedStudent": 2,
    "timestamp": 1748698099
  },
  {
    "studentRegister": 0,
    "studentAccepted": 1,
    "maxRegister": 6,
    "maxAcceptedStudent": 2,
    "timestamp": 1748699116
  },
  {
    "studentRegister": 0,
    "studentAccepted": 1,
    "maxRegister": 6,
    "maxAcceptedStudent": 2,
    "timestamp": 1748699553
  },
  {
    "studentRegister": 0,
    "studentAccepted": 1,
    "maxRegister": 6,
    "maxAcceptedStudent": 2,
    "timestamp": 1748699948
  },
  {
    "studentRegister": 0,
    "studentAccepted": 1,
    "maxRegister": 6,
    "maxAcceptedStudent": 2,
    "timestamp": 1748700831
  },
  {
    "studentRegister": 0,
    "studentAccepted": 1,
    "maxRegister": 6,
    "maxAcceptedStudent": 2,
    "timestamp": 1748701974
  },
  {
    "studentRegister": 0,
    "studentAccepted": 1,
    "maxRegister": 6,
    "maxAcceptedStudent": 2,
    "timestamp": 1748702690
  },
  {
    "studentRegister": 0,
    "studentAccepted": 1,
    "maxRegister": 6,
    "maxAcceptedStudent": 2,
    "timestamp": 1748703098
  },
  {
    "studentRegister": 0,
    "studentAccepted": 1,
    "maxRegister": 6,
    "maxAcceptedStudent": 2,
    "timestamp": 1748703510
  },
  {
    "studentRegister": 0,
    "studentAccepted": 1,
    "maxRegister": 6,
    "maxAcceptedStudent": 2,
    "timestamp": 1748704380
  },
  {
    "studentRegister": 0,
    "studentAccepted": 1,
    "maxRegister": 6,
    "maxAcceptedStudent": 2,
    "timestamp": 1748705466
  },
  {
    "studentRegister": 0,
    "studentAccepted": 1,
    "maxRegister": 6,
    "maxAcceptedStudent": 2,
    "timestamp": 1748706073
  },
  {
    "studentRegister": 0,
    "studentAccepted": 1,
    "maxRegister": 6,
    "maxAcceptedStudent": 2,
    "timestamp": 1748706485
  },
  {
    "studentRegister": 0,
    "studentAccepted": 1,
    "maxRegister": 6,
    "maxAcceptedStudent": 2,
    "timestamp": 1748706901
  },
  {
    "studentRegister": 0,
    "studentAccepted": 1,
    "maxRegister": 6,
    "maxAcceptedStudent": 2,
    "timestamp": 1748707304
  },
  {
    "studentRegister": 0,
    "studentAccepted": 1,
    "maxRegister": 6,
    "maxAcceptedStudent": 2,
    "timestamp": 1748708613
  },
  {
    "studentRegister": 0,
    "studentAccepted": 1,
    "maxRegister": 6,
    "maxAcceptedStudent": 2,
    "timestamp": 1748709937
  },
  {
    "studentRegister": 0,
    "studentAccepted": 1,
    "maxRegister": 6,
    "maxAcceptedStudent": 2,
    "timestamp": 1748710627
  },
  {
    "studentRegister": 0,
    "studentAccepted": 1,
    "maxRegister": 6,
    "maxAcceptedStudent": 2,
    "timestamp": 1748711021
  },
  {
    "studentRegister": 0,
    "studentAccepted": 1,
    "maxRegister": 6,
    "maxAcceptedStudent": 2,
    "timestamp": 1748712076
  },
  {
    "studentRegister": 0,
    "studentAccepted": 1,
    "maxRegister": 6,
    "maxAcceptedStudent": 2,
    "timestamp": 1748712887
  },
  {
    "studentRegister": 0,
    "studentAccepted": 1,
    "maxRegister": 6,
    "maxAcceptedStudent": 2,
    "timestamp": 1748713458
  },
  {
    "studentRegister": 0,
    "studentAccepted": 1,
    "maxRegister": 6,
    "maxAcceptedStudent": 2,
    "timestamp": 1748713858
  },
  {
    "studentRegister": 0,
    "studentAccepted": 1,
    "maxRegister": 6,
    "maxAcceptedStudent": 2,
    "timestamp": 1748714262
  },
  {
    "studentRegister": 0,
    "studentAccepted": 1,
    "maxRegister": 6,
    "maxAcceptedStudent": 2,
    "timestamp": 1748715267
  },
  {
    "studentRegister": 0,
    "studentAccepted": 1,
    "maxRegister": 6,
    "maxAcceptedStudent": 2,
    "timestamp": 1748716815
  },
  {
    "studentRegister": 0,
    "studentAccepted": 1,
    "maxRegister": 6,
    "maxAcceptedStudent": 2,
    "timestamp": 1748717541
  },
  {
    "studentRegister": 0,
    "studentAccepted": 1,
    "maxRegister": 6,
    "maxAcceptedStudent": 2,
    "timestamp": 1748717940
  },
  {
    "studentRegister": 0,
    "studentAccepted": 1,
    "maxRegister": 6,
    "maxAcceptedStudent": 2,
    "timestamp": 1748718722
  },
  {
    "studentRegister": 0,
    "studentAccepted": 1,
    "maxRegister": 6,
    "maxAcceptedStudent": 2,
    "timestamp": 1748719471
  },
  {
    "studentRegister": 0,
    "studentAccepted": 1,
    "maxRegister": 6,
    "maxAcceptedStudent": 2,
    "timestamp": 1748719880
  },
  {
    "studentRegister": 0,
    "studentAccepted": 1,
    "maxRegister": 6,
    "maxAcceptedStudent": 2,
    "timestamp": 1748720375
  },
  {
    "studentRegister": 0,
    "studentAccepted": 1,
    "maxRegister": 6,
    "maxAcceptedStudent": 2,
    "timestamp": 1748720769
  },
  {
    "studentRegister": 0,
    "studentAccepted": 1,
    "maxRegister": 6,
    "maxAcceptedStudent": 2,
    "timestamp": 1748721186
  },
  {
    "studentRegister": 0,
    "studentAccepted": 1,
    "maxRegister": 6,
    "maxAcceptedStudent": 2,
    "timestamp": 1748721573
  },
  {
    "studentRegister": 0,
    "studentAccepted": 1,
    "maxRegister": 6,
    "maxAcceptedStudent": 2,
    "timestamp": 1748722594
  },
  {
    "studentRegister": 0,
    "studentAccepted": 1,
    "maxRegister": 6,
    "maxAcceptedStudent": 2,
    "timestamp": 1748723612
  },
  {
    "studentRegister": 0,
    "studentAccepted": 1,
    "maxRegister": 6,
    "maxAcceptedStudent": 2,
    "timestamp": 1748724224
  },
  {
    "studentRegister": 0,
    "studentAccepted": 1,
    "maxRegister": 6,
    "maxAcceptedStudent": 2,
    "timestamp": 1748724666
  },
  {
    "studentRegister": 0,
    "studentAccepted": 1,
    "maxRegister": 6,
    "maxAcceptedStudent": 2,
    "timestamp": 1748725056
  },
  {
    "studentRegister": 0,
    "studentAccepted": 1,
    "maxRegister": 6,
    "maxAcceptedStudent": 2,
    "timestamp": 1748725850
  },
  {
    "studentRegister": 0,
    "studentAccepted": 1,
    "maxRegister": 6,
    "maxAcceptedStudent": 2,
    "timestamp": 1748726882
  },
  {
    "studentRegister": 0,
    "studentAccepted": 1,
    "maxRegister": 6,
    "maxAcceptedStudent": 2,
    "timestamp": 1748727451
  },
  {
    "studentRegister": 0,
    "studentAccepted": 1,
    "maxRegister": 6,
    "maxAcceptedStudent": 2,
    "timestamp": 1748727916
  },
  {
    "studentRegister": 0,
    "studentAccepted": 1,
    "maxRegister": 6,
    "maxAcceptedStudent": 2,
    "timestamp": 1748728323
  },
  {
    "studentRegister": 0,
    "studentAccepted": 1,
    "maxRegister": 6,
    "maxAcceptedStudent": 2,
    "timestamp": 1748728720
  },
  {
    "studentRegister": 0,
    "studentAccepted": 1,
    "maxRegister": 6,
    "maxAcceptedStudent": 2,
    "timestamp": 1748729598
  },
  {
    "studentRegister": 0,
    "studentAccepted": 1,
    "maxRegister": 6,
    "maxAcceptedStudent": 2,
    "timestamp": 1748730840
  },
  {
    "studentRegister": 0,
    "studentAccepted": 1,
    "maxRegister": 6,
    "maxAcceptedStudent": 2,
    "timestamp": 1748731577
  },
  {
    "studentRegister": 0,
    "studentAccepted": 1,
    "maxRegister": 6,
    "maxAcceptedStudent": 2,
    "timestamp": 1748731987
  },
  {
    "studentRegister": 0,
    "studentAccepted": 1,
    "maxRegister": 6,
    "maxAcceptedStudent": 2,
    "timestamp": 1748732397
  },
  {
    "studentRegister": 0,
    "studentAccepted": 1,
    "maxRegister": 6,
    "maxAcceptedStudent": 2,
    "timestamp": 1748733406
  },
  {
    "studentRegister": 0,
    "studentAccepted": 1,
    "maxRegister": 6,
    "maxAcceptedStudent": 2,
    "timestamp": 1748734344
  },
  {
    "studentRegister": 0,
    "studentAccepted": 1,
    "maxRegister": 6,
    "maxAcceptedStudent": 2,
    "timestamp": 1748734920
  },
  {
    "studentRegister": 0,
    "studentAccepted": 1,
    "maxRegister": 6,
    "maxAcceptedStudent": 2,
    "timestamp": 1748735349
  },
  {
    "studentRegister": 0,
    "studentAccepted": 1,
    "maxRegister": 6,
    "maxAcceptedStudent": 2,
    "timestamp": 1748735759
  },
  {
    "studentRegister": 0,
    "studentAccepted": 1,
    "maxRegister": 6,
    "maxAcceptedStudent": 2,
    "timestamp": 1748736162
  },
  {
    "studentRegister": 0,
    "studentAccepted": 1,
    "maxRegister": 6,
    "maxAcceptedStudent": 2,
    "timestamp": 1748743415
  },
  {
    "studentRegister": 0,
    "studentAccepted": 1,
    "maxRegister": 6,
    "maxAcceptedStudent": 2,
    "timestamp": 1748749500
  },
  {
    "studentRegister": 0,
    "studentAccepted": 1,
    "maxRegister": 6,
    "maxAcceptedStudent": 2,
    "timestamp": 1748751914
  },
  {
    "studentRegister": 0,
    "studentAccepted": 1,
    "maxRegister": 6,
    "maxAcceptedStudent": 2,
    "timestamp": 1748753615
  },
  {
    "studentRegister": 0,
    "studentAccepted": 1,
    "maxRegister": 6,
    "maxAcceptedStudent": 2,
    "timestamp": 1748754229
  },
  {
    "studentRegister": 0,
    "studentAccepted": 1,
    "maxRegister": 6,
    "maxAcceptedStudent": 2,
    "timestamp": 1748755542
  },
  {
    "studentRegister": 0,
    "studentAccepted": 1,
    "maxRegister": 6,
    "maxAcceptedStudent": 2,
    "timestamp": 1748756514
  },
  {
    "studentRegister": 0,
    "studentAccepted": 1,
    "maxRegister": 6,
    "maxAcceptedStudent": 2,
    "timestamp": 1748757014
  },
  {
    "studentRegister": 0,
    "studentAccepted": 1,
    "maxRegister": 6,
    "maxAcceptedStudent": 2,
    "timestamp": 1748757421
  },
  {
    "studentRegister": 0,
    "studentAccepted": 1,
    "maxRegister": 6,
    "maxAcceptedStudent": 2,
    "timestamp": 1748757822
  },
  {
    "studentRegister": 0,
    "studentAccepted": 1,
    "maxRegister": 6,
    "maxAcceptedStudent": 2,
    "timestamp": 1748759687
  },
  {
    "studentRegister": 0,
    "studentAccepted": 1,
    "maxRegister": 6,
    "maxAcceptedStudent": 2,
    "timestamp": 1748760794
  },
  {
    "studentRegister": 0,
    "studentAccepted": 1,
    "maxRegister": 6,
    "maxAcceptedStudent": 2,
    "timestamp": 1748761211
  },
  {
    "studentRegister": 0,
    "studentAccepted": 1,
    "maxRegister": 6,
    "maxAcceptedStudent": 2,
    "timestamp": 1748762206
  },
  {
    "studentRegister": 0,
    "studentAccepted": 1,
    "maxRegister": 6,
    "maxAcceptedStudent": 2,
    "timestamp": 1748763115
  },
  {
    "studentRegister": 0,
    "studentAccepted": 1,
    "maxRegister": 6,
    "maxAcceptedStudent": 2,
    "timestamp": 1748763706
  },
  {
    "studentRegister": 0,
    "studentAccepted": 1,
    "maxRegister": 6,
    "maxAcceptedStudent": 2,
    "timestamp": 1748764100
  },
  {
    "studentRegister": 0,
    "studentAccepted": 1,
    "maxRegister": 6,
    "maxAcceptedStudent": 2,
    "timestamp": 1748764503
  },
  {
    "studentRegister": 0,
    "studentAccepted": 1,
    "maxRegister": 6,
    "maxAcceptedStudent": 2,
    "timestamp": 1748764905
  },
  {
    "studentRegister": 0,
    "studentAccepted": 1,
    "maxRegister": 6,
    "maxAcceptedStudent": 2,
    "timestamp": 1748766335
  },
  {
    "studentRegister": 0,
    "studentAccepted": 1,
    "maxRegister": 6,
    "maxAcceptedStudent": 2,
    "timestamp": 1748767483
  },
  {
    "studentRegister": 0,
    "studentAccepted": 1,
    "maxRegister": 6,
    "maxAcceptedStudent": 2,
    "timestamp": 1748768313
  },
  {
    "studentRegister": 0,
    "studentAccepted": 1,
    "maxRegister": 6,
    "maxAcceptedStudent": 2,
    "timestamp": 1748769241
  },
  {
    "studentRegister": 0,
    "studentAccepted": 1,
    "maxRegister": 6,
    "maxAcceptedStudent": 2,
    "timestamp": 1748770344
  },
  {
    "studentRegister": 0,
    "studentAccepted": 1,
    "maxRegister": 6,
    "maxAcceptedStudent": 2,
    "timestamp": 1748770978
  },
  {
    "studentRegister": 0,
    "studentAccepted": 1,
    "maxRegister": 6,
    "maxAcceptedStudent": 2,
    "timestamp": 1748771375
  },
  {
    "studentRegister": 0,
    "studentAccepted": 1,
    "maxRegister": 6,
    "maxAcceptedStudent": 2,
    "timestamp": 1748771790
  },
  {
    "studentRegister": 0,
    "studentAccepted": 1,
    "maxRegister": 6,
    "maxAcceptedStudent": 2,
    "timestamp": 1748772190
  },
  {
    "studentRegister": 0,
    "studentAccepted": 1,
    "maxRegister": 6,
    "maxAcceptedStudent": 2,
    "timestamp": 1748773498
  },
  {
    "studentRegister": 0,
    "studentAccepted": 1,
    "maxRegister": 6,
    "maxAcceptedStudent": 2,
    "timestamp": 1748774584
  },
  {
    "studentRegister": 0,
    "studentAccepted": 1,
    "maxRegister": 6,
    "maxAcceptedStudent": 2,
    "timestamp": 1748775101
  },
  {
    "studentRegister": 0,
    "studentAccepted": 1,
    "maxRegister": 6,
    "maxAcceptedStudent": 2,
    "timestamp": 1748775504
  },
  {
    "studentRegister": 0,
    "studentAccepted": 1,
    "maxRegister": 6,
    "maxAcceptedStudent": 2,
    "timestamp": 1748776290
  },
  {
    "studentRegister": 0,
    "studentAccepted": 1,
    "maxRegister": 6,
    "maxAcceptedStudent": 2,
    "timestamp": 1748777200
  },
  {
    "studentRegister": 0,
    "studentAccepted": 1,
    "maxRegister": 6,
    "maxAcceptedStudent": 2,
    "timestamp": 1748777616
  },
  {
    "studentRegister": 0,
    "studentAccepted": 1,
    "maxRegister": 6,
    "maxAcceptedStudent": 2,
    "timestamp": 1748778090
  },
  {
    "studentRegister": 0,
    "studentAccepted": 1,
    "maxRegister": 6,
    "maxAcceptedStudent": 2,
    "timestamp": 1748778481
  },
  {
    "studentRegister": 0,
    "studentAccepted": 1,
    "maxRegister": 6,
    "maxAcceptedStudent": 2,
    "timestamp": 1748778887
  },
  {
    "studentRegister": 0,
    "studentAccepted": 1,
    "maxRegister": 6,
    "maxAcceptedStudent": 2,
    "timestamp": 1748779301
  },
  {
    "studentRegister": 0,
    "studentAccepted": 1,
    "maxRegister": 6,
    "maxAcceptedStudent": 2,
    "timestamp": 1748781447
  },
  {
    "studentRegister": 0,
    "studentAccepted": 1,
    "maxRegister": 6,
    "maxAcceptedStudent": 2,
    "timestamp": 1748783301
  },
  {
    "studentRegister": 0,
    "studentAccepted": 1,
    "maxRegister": 6,
    "maxAcceptedStudent": 2,
    "timestamp": 1748784982
  },
  {
    "studentRegister": 0,
    "studentAccepted": 1,
    "maxRegister": 6,
    "maxAcceptedStudent": 2,
    "timestamp": 1748785655
  },
  {
    "studentRegister": 0,
    "studentAccepted": 1,
    "maxRegister": 6,
    "maxAcceptedStudent": 2,
    "timestamp": 1748786053
  },
  {
    "studentRegister": 0,
    "studentAccepted": 1,
    "maxRegister": 6,
    "maxAcceptedStudent": 2,
    "timestamp": 1748786463
  },
  {
    "studentRegister": 0,
    "studentAccepted": 1,
    "maxRegister": 6,
    "maxAcceptedStudent": 2,
    "timestamp": 1748787417
  },
  {
    "studentRegister": 0,
    "studentAccepted": 1,
    "maxRegister": 6,
    "maxAcceptedStudent": 2,
    "timestamp": 1748788491
  },
  {
    "studentRegister": 0,
    "studentAccepted": 1,
    "maxRegister": 6,
    "maxAcceptedStudent": 2,
    "timestamp": 1748789292
  },
  {
    "studentRegister": 0,
    "studentAccepted": 1,
    "maxRegister": 6,
    "maxAcceptedStudent": 2,
    "timestamp": 1748789687
  },
  {
    "studentRegister": 0,
    "studentAccepted": 1,
    "maxRegister": 6,
    "maxAcceptedStudent": 2,
    "timestamp": 1748790084
  },
  {
    "studentRegister": 0,
    "studentAccepted": 1,
    "maxRegister": 6,
    "maxAcceptedStudent": 2,
    "timestamp": 1748791172
  },
  {
    "studentRegister": 0,
    "studentAccepted": 1,
    "maxRegister": 6,
    "maxAcceptedStudent": 2,
    "timestamp": 1748792065
  },
  {
    "studentRegister": 0,
    "studentAccepted": 1,
    "maxRegister": 6,
    "maxAcceptedStudent": 2,
    "timestamp": 1748792677
  },
  {
    "studentRegister": 0,
    "studentAccepted": 1,
    "maxRegister": 6,
    "maxAcceptedStudent": 2,
    "timestamp": 1748793104
  },
  {
    "studentRegister": 0,
    "studentAccepted": 1,
    "maxRegister": 6,
    "maxAcceptedStudent": 2,
    "timestamp": 1748793502
  },
  {
    "studentRegister": 0,
    "studentAccepted": 1,
    "maxRegister": 6,
    "maxAcceptedStudent": 2,
    "timestamp": 1748794494
  },
  {
    "studentRegister": 0,
    "studentAccepted": 1,
    "maxRegister": 6,
    "maxAcceptedStudent": 2,
    "timestamp": 1748795941
  },
  {
    "studentRegister": 0,
    "studentAccepted": 1,
    "maxRegister": 6,
    "maxAcceptedStudent": 2,
    "timestamp": 1748796795
  },
  {
    "studentRegister": 0,
    "studentAccepted": 1,
    "maxRegister": 6,
    "maxAcceptedStudent": 2,
    "timestamp": 1748797198
  },
  {
    "studentRegister": 0,
    "studentAccepted": 1,
    "maxRegister": 6,
    "maxAcceptedStudent": 2,
    "timestamp": 1748798115
  },
  {
    "studentRegister": 0,
    "studentAccepted": 1,
    "maxRegister": 6,
    "maxAcceptedStudent": 2,
    "timestamp": 1748799161
  },
  {
    "studentRegister": 0,
    "studentAccepted": 1,
    "maxRegister": 6,
    "maxAcceptedStudent": 2,
    "timestamp": 1748799832
  },
  {
    "studentRegister": 0,
    "studentAccepted": 1,
    "maxRegister": 6,
    "maxAcceptedStudent": 2,
    "timestamp": 1748800234
  },
  {
    "studentRegister": 0,
    "studentAccepted": 1,
    "maxRegister": 6,
    "maxAcceptedStudent": 2,
    "timestamp": 1748800633
  },
  {
    "studentRegister": 0,
    "studentAccepted": 1,
    "maxRegister": 6,
    "maxAcceptedStudent": 2,
    "timestamp": 1748801615
  },
  {
    "studentRegister": 0,
    "studentAccepted": 1,
    "maxRegister": 6,
    "maxAcceptedStudent": 2,
    "timestamp": 1748803211
  },
  {
    "studentRegister": 0,
    "studentAccepted": 1,
    "maxRegister": 6,
    "maxAcceptedStudent": 2,
    "timestamp": 1748803972
  },
  {
    "studentRegister": 0,
    "studentAccepted": 1,
    "maxRegister": 6,
    "maxAcceptedStudent": 2,
    "timestamp": 1748804375
  },
  {
    "studentRegister": 0,
    "studentAccepted": 1,
    "maxRegister": 6,
    "maxAcceptedStudent": 2,
    "timestamp": 1748805193
  },
  {
    "studentRegister": 0,
    "studentAccepted": 1,
    "maxRegister": 6,
    "maxAcceptedStudent": 2,
    "timestamp": 1748805973
  },
  {
    "studentRegister": 0,
    "studentAccepted": 1,
    "maxRegister": 6,
    "maxAcceptedStudent": 2,
    "timestamp": 1748806376
  },
  {
    "studentRegister": 0,
    "studentAccepted": 1,
    "maxRegister": 6,
    "maxAcceptedStudent": 2,
    "timestamp": 1748806873
  },
  {
    "studentRegister": 0,
    "studentAccepted": 1,
    "maxRegister": 6,
    "maxAcceptedStudent": 2,
    "timestamp": 1748807275
  },
  {
    "studentRegister": 0,
    "studentAccepted": 1,
    "maxRegister": 6,
    "maxAcceptedStudent": 2,
    "timestamp": 1748807675
  },
  {
    "studentRegister": 0,
    "studentAccepted": 1,
    "maxRegister": 6,
    "maxAcceptedStudent": 2,
    "timestamp": 1748808073
  },
  {
    "studentRegister": 0,
    "studentAccepted": 1,
    "maxRegister": 6,
    "maxAcceptedStudent": 2,
    "timestamp": 1748809264
  },
  {
    "studentRegister": 0,
    "studentAccepted": 1,
    "maxRegister": 6,
    "maxAcceptedStudent": 2,
    "timestamp": 1748810204
  },
  {
    "studentRegister": 0,
    "studentAccepted": 1,
    "maxRegister": 6,
    "maxAcceptedStudent": 2,
    "timestamp": 1748810862
  },
  {
    "studentRegister": 0,
    "studentAccepted": 1,
    "maxRegister": 6,
    "maxAcceptedStudent": 2,
    "timestamp": 1748811242
  },
  {
    "studentRegister": 0,
    "studentAccepted": 1,
    "maxRegister": 6,
    "maxAcceptedStudent": 2,
    "timestamp": 1748811671
  },
  {
    "studentRegister": 0,
    "studentAccepted": 1,
    "maxRegister": 6,
    "maxAcceptedStudent": 2,
    "timestamp": 1748812669
  },
  {
    "studentRegister": 0,
    "studentAccepted": 1,
    "maxRegister": 6,
    "maxAcceptedStudent": 2,
    "timestamp": 1748813513
  },
  {
    "studentRegister": 0,
    "studentAccepted": 1,
    "maxRegister": 6,
    "maxAcceptedStudent": 2,
    "timestamp": 1748814068
  },
  {
    "studentRegister": 0,
    "studentAccepted": 1,
    "maxRegister": 6,
    "maxAcceptedStudent": 2,
    "timestamp": 1748814465
  },
  {
    "studentRegister": 0,
    "studentAccepted": 1,
    "maxRegister": 6,
    "maxAcceptedStudent": 2,
    "timestamp": 1748814868
  },
  {
    "studentRegister": 0,
    "studentAccepted": 1,
    "maxRegister": 6,
    "maxAcceptedStudent": 2,
    "timestamp": 1748815252
  },
  {
    "studentRegister": 0,
    "studentAccepted": 1,
    "maxRegister": 6,
    "maxAcceptedStudent": 2,
    "timestamp": 1748816284
  },
  {
    "studentRegister": 0,
    "studentAccepted": 1,
    "maxRegister": 6,
    "maxAcceptedStudent": 2,
    "timestamp": 1748817404
  },
  {
    "studentRegister": 0,
    "studentAccepted": 1,
    "maxRegister": 6,
    "maxAcceptedStudent": 2,
    "timestamp": 1748818097
  },
  {
    "studentRegister": 0,
    "studentAccepted": 1,
    "maxRegister": 6,
    "maxAcceptedStudent": 2,
    "timestamp": 1748818502
  },
  {
    "studentRegister": 0,
    "studentAccepted": 1,
    "maxRegister": 6,
    "maxAcceptedStudent": 2,
    "timestamp": 1748818904
  },
  {
    "studentRegister": 0,
    "studentAccepted": 1,
    "maxRegister": 6,
    "maxAcceptedStudent": 2,
    "timestamp": 1748820017
  },
  {
    "studentRegister": 0,
    "studentAccepted": 1,
    "maxRegister": 6,
    "maxAcceptedStudent": 2,
    "timestamp": 1748820841
  },
  {
    "studentRegister": 0,
    "studentAccepted": 1,
    "maxRegister": 6,
    "maxAcceptedStudent": 2,
    "timestamp": 1748821448
  },
  {
    "studentRegister": 0,
    "studentAccepted": 1,
    "maxRegister": 6,
    "maxAcceptedStudent": 2,
    "timestamp": 1748821836
  },
  {
    "studentRegister": 0,
    "studentAccepted": 1,
    "maxRegister": 6,
    "maxAcceptedStudent": 2,
    "timestamp": 1748822245
  },
  {
    "studentRegister": 0,
    "studentAccepted": 1,
    "maxRegister": 6,
    "maxAcceptedStudent": 2,
    "timestamp": 1748825316
  },
  {
    "studentRegister": 0,
    "studentAccepted": 1,
    "maxRegister": 6,
    "maxAcceptedStudent": 2,
    "timestamp": 1748831698
  },
  {
    "studentRegister": 0,
    "studentAccepted": 1,
    "maxRegister": 6,
    "maxAcceptedStudent": 2,
    "timestamp": 1748835769
  },
  {
    "studentRegister": 0,
    "studentAccepted": 1,
    "maxRegister": 6,
    "maxAcceptedStudent": 2,
    "timestamp": 1748837380
  },
  {
    "studentRegister": 0,
    "studentAccepted": 1,
    "maxRegister": 6,
    "maxAcceptedStudent": 2,
    "timestamp": 1748839317
  },
  {
    "studentRegister": 0,
    "studentAccepted": 1,
    "maxRegister": 6,
    "maxAcceptedStudent": 2,
    "timestamp": 1748840347
  },
  {
    "studentRegister": 0,
    "studentAccepted": 1,
    "maxRegister": 6,
    "maxAcceptedStudent": 2,
    "timestamp": 1748841421
  },
  {
    "studentRegister": 0,
    "studentAccepted": 1,
    "maxRegister": 6,
    "maxAcceptedStudent": 2,
    "timestamp": 1748842684
  },
  {
    "studentRegister": 0,
    "studentAccepted": 1,
    "maxRegister": 6,
    "maxAcceptedStudent": 2,
    "timestamp": 1748843441
  },
  {
    "studentRegister": 0,
    "studentAccepted": 1,
    "maxRegister": 6,
    "maxAcceptedStudent": 2,
    "timestamp": 1748843838
  },
  {
    "studentRegister": 0,
    "studentAccepted": 1,
    "maxRegister": 6,
    "maxAcceptedStudent": 2,
    "timestamp": 1748845005
  },
  {
    "studentRegister": 0,
    "studentAccepted": 1,
    "maxRegister": 6,
    "maxAcceptedStudent": 2,
    "timestamp": 1748846914
  },
  {
    "studentRegister": 0,
    "studentAccepted": 1,
    "maxRegister": 6,
    "maxAcceptedStudent": 2,
    "timestamp": 1748847702
  },
  {
    "studentRegister": 0,
    "studentAccepted": 1,
    "maxRegister": 6,
    "maxAcceptedStudent": 2,
    "timestamp": 1748848920
  },
  {
    "studentRegister": 0,
    "studentAccepted": 1,
    "maxRegister": 6,
    "maxAcceptedStudent": 2,
    "timestamp": 1748849842
  },
  {
    "studentRegister": 0,
    "studentAccepted": 1,
    "maxRegister": 6,
    "maxAcceptedStudent": 2,
    "timestamp": 1748850435
  },
  {
    "studentRegister": 0,
    "studentAccepted": 1,
    "maxRegister": 6,
    "maxAcceptedStudent": 2,
    "timestamp": 1748850837
  },
  {
    "studentRegister": 0,
    "studentAccepted": 1,
    "maxRegister": 6,
    "maxAcceptedStudent": 2,
    "timestamp": 1748851249
  },
  {
    "studentRegister": 0,
    "studentAccepted": 1,
    "maxRegister": 6,
    "maxAcceptedStudent": 2,
    "timestamp": 1748852769
  },
  {
    "studentRegister": 0,
    "studentAccepted": 1,
    "maxRegister": 6,
    "maxAcceptedStudent": 2,
    "timestamp": 1748854121
  },
  {
    "studentRegister": 0,
    "studentAccepted": 1,
    "maxRegister": 6,
    "maxAcceptedStudent": 2,
    "timestamp": 1748854845
  },
  {
    "studentRegister": 1,
    "studentAccepted": 1,
    "maxRegister": 6,
    "maxAcceptedStudent": 2,
    "timestamp": 1748856098
  },
  {
    "studentRegister": 1,
    "studentAccepted": 1,
    "maxRegister": 6,
    "maxAcceptedStudent": 2,
    "timestamp": 1748857200
  },
  {
    "studentRegister": 1,
    "studentAccepted": 1,
    "maxRegister": 6,
    "maxAcceptedStudent": 2,
    "timestamp": 1748857843
  },
  {
    "studentRegister": 1,
    "studentAccepted": 1,
    "maxRegister": 6,
    "maxAcceptedStudent": 2,
    "timestamp": 1748858234
  },
  {
    "studentRegister": 1,
    "studentAccepted": 1,
    "maxRegister": 6,
    "maxAcceptedStudent": 2,
    "timestamp": 1748859180
  },
  {
    "studentRegister": 1,
    "studentAccepted": 1,
    "maxRegister": 6,
    "maxAcceptedStudent": 2,
    "timestamp": 1748860780
  },
  {
    "studentRegister": 1,
    "studentAccepted": 1,
    "maxRegister": 6,
    "maxAcceptedStudent": 2,
    "timestamp": 1748861570
  },
  {
    "studentRegister": 1,
    "studentAccepted": 1,
    "maxRegister": 6,
    "maxAcceptedStudent": 2,
    "timestamp": 1748861974
  },
  {
    "studentRegister": 1,
    "studentAccepted": 1,
    "maxRegister": 6,
    "maxAcceptedStudent": 2,
    "timestamp": 1748862924
  },
  {
    "studentRegister": 1,
    "studentAccepted": 1,
    "maxRegister": 6,
    "maxAcceptedStudent": 2,
    "timestamp": 1748863843
  },
  {
    "studentRegister": 1,
    "studentAccepted": 1,
    "maxRegister": 6,
    "maxAcceptedStudent": 2,
    "timestamp": 1748864434
  },
  {
    "studentRegister": 1,
    "studentAccepted": 1,
    "maxRegister": 6,
    "maxAcceptedStudent": 2,
    "timestamp": 1748864828
  },
  {
    "studentRegister": 1,
    "studentAccepted": 1,
    "maxRegister": 6,
    "maxAcceptedStudent": 2,
    "timestamp": 1748865237
  },
  {
    "studentRegister": 1,
    "studentAccepted": 1,
    "maxRegister": 6,
    "maxAcceptedStudent": 2,
    "timestamp": 1748865643
  },
  {
    "studentRegister": 1,
    "studentAccepted": 1,
    "maxRegister": 6,
    "maxAcceptedStudent": 2,
    "timestamp": 1748867771
  },
  {
    "studentRegister": 1,
    "studentAccepted": 1,
    "maxRegister": 6,
    "maxAcceptedStudent": 2,
    "timestamp": 1748869965
  },
  {
    "studentRegister": 2,
    "studentAccepted": 1,
    "maxRegister": 6,
    "maxAcceptedStudent": 2,
    "timestamp": 1748871865
  },
  {
    "studentRegister": 2,
    "studentAccepted": 1,
    "maxRegister": 6,
    "maxAcceptedStudent": 2,
    "timestamp": 1748872542
  },
  {
    "studentRegister": 2,
    "studentAccepted": 1,
    "maxRegister": 6,
    "maxAcceptedStudent": 2,
    "timestamp": 1748872935
  },
  {
    "studentRegister": 2,
    "studentAccepted": 1,
    "maxRegister": 6,
    "maxAcceptedStudent": 2,
    "timestamp": 1748874195
  },
  {
    "studentRegister": 2,
    "studentAccepted": 1,
    "maxRegister": 6,
    "maxAcceptedStudent": 2,
    "timestamp": 1748875503
  },
  {
    "studentRegister": 2,
    "studentAccepted": 1,
    "maxRegister": 6,
    "maxAcceptedStudent": 2,
    "timestamp": 1748876145
  },
  {
    "studentRegister": 2,
    "studentAccepted": 1,
    "maxRegister": 6,
    "maxAcceptedStudent": 2,
    "timestamp": 1748876540
  },
  {
    "studentRegister": 2,
    "studentAccepted": 1,
    "maxRegister": 6,
    "maxAcceptedStudent": 2,
    "timestamp": 1748877884
  },
  {
    "studentRegister": 2,
    "studentAccepted": 1,
    "maxRegister": 6,
    "maxAcceptedStudent": 2,
    "timestamp": 1748878960
  },
  {
    "studentRegister": 2,
    "studentAccepted": 1,
    "maxRegister": 6,
    "maxAcceptedStudent": 2,
    "timestamp": 1748879565
  },
  {
    "studentRegister": 2,
    "studentAccepted": 1,
    "maxRegister": 6,
    "maxAcceptedStudent": 2,
    "timestamp": 1748879973
  },
  {
    "studentRegister": 2,
    "studentAccepted": 1,
    "maxRegister": 6,
    "maxAcceptedStudent": 2,
    "timestamp": 1748881207
  },
  {
    "studentRegister": 2,
    "studentAccepted": 1,
    "maxRegister": 6,
    "maxAcceptedStudent": 2,
    "timestamp": 1748882922
  },
  {
    "studentRegister": 2,
    "studentAccepted": 1,
    "maxRegister": 6,
    "maxAcceptedStudent": 2,
    "timestamp": 1748883713
  },
  {
    "studentRegister": 2,
    "studentAccepted": 1,
    "maxRegister": 6,
    "maxAcceptedStudent": 2,
    "timestamp": 1748884834
  },
  {
    "studentRegister": 2,
    "studentAccepted": 1,
    "maxRegister": 6,
    "maxAcceptedStudent": 2,
    "timestamp": 1748885882
  },
  {
    "studentRegister": 2,
    "studentAccepted": 1,
    "maxRegister": 6,
    "maxAcceptedStudent": 2,
    "timestamp": 1748886544
  },
  {
    "studentRegister": 2,
    "studentAccepted": 1,
    "maxRegister": 6,
    "maxAcceptedStudent": 2,
    "timestamp": 1748886952
  },
  {
    "studentRegister": 2,
    "studentAccepted": 1,
    "maxRegister": 6,
    "maxAcceptedStudent": 2,
    "timestamp": 1748887346
  },
  {
    "studentRegister": 2,
    "studentAccepted": 1,
    "maxRegister": 6,
    "maxAcceptedStudent": 2,
    "timestamp": 1748889095
  },
  {
    "studentRegister": 2,
    "studentAccepted": 1,
    "maxRegister": 6,
    "maxAcceptedStudent": 2,
    "timestamp": 1748890389
  },
  {
    "studentRegister": 2,
    "studentAccepted": 1,
    "maxRegister": 6,
    "maxAcceptedStudent": 2,
    "timestamp": 1748890875
  },
  {
    "studentRegister": 2,
    "studentAccepted": 1,
    "maxRegister": 6,
    "maxAcceptedStudent": 2,
    "timestamp": 1748891785
  },
  {
    "studentRegister": 2,
    "studentAccepted": 1,
    "maxRegister": 6,
    "maxAcceptedStudent": 2,
    "timestamp": 1748892546
  },
  {
    "studentRegister": 2,
    "studentAccepted": 1,
    "maxRegister": 6,
    "maxAcceptedStudent": 2,
    "timestamp": 1748893028
  },
  {
    "studentRegister": 2,
    "studentAccepted": 1,
    "maxRegister": 6,
    "maxAcceptedStudent": 2,
    "timestamp": 1748893444
  },
  {
    "studentRegister": 2,
    "studentAccepted": 1,
    "maxRegister": 6,
    "maxAcceptedStudent": 2,
    "timestamp": 1748893863
  },
  {
    "studentRegister": 2,
    "studentAccepted": 1,
    "maxRegister": 6,
    "maxAcceptedStudent": 2,
    "timestamp": 1748894246
  },
  {
    "studentRegister": 2,
    "studentAccepted": 1,
    "maxRegister": 6,
    "maxAcceptedStudent": 2,
    "timestamp": 1748895189
  },
  {
    "studentRegister": 2,
    "studentAccepted": 1,
    "maxRegister": 6,
    "maxAcceptedStudent": 2,
    "timestamp": 1748896499
  },
  {
    "studentRegister": 2,
    "studentAccepted": 1,
    "maxRegister": 6,
    "maxAcceptedStudent": 2,
    "timestamp": 1748897258
  },
  {
    "studentRegister": 2,
    "studentAccepted": 1,
    "maxRegister": 6,
    "maxAcceptedStudent": 2,
    "timestamp": 1748897725
  },
  {
    "studentRegister": 2,
    "studentAccepted": 1,
    "maxRegister": 6,
    "maxAcceptedStudent": 2,
    "timestamp": 1748898116
  },
  {
    "studentRegister": 2,
    "studentAccepted": 1,
    "maxRegister": 6,
    "maxAcceptedStudent": 2,
    "timestamp": 1748899305
  },
  {
    "studentRegister": 2,
    "studentAccepted": 1,
    "maxRegister": 6,
    "maxAcceptedStudent": 2,
    "timestamp": 1748900262
  },
  {
    "studentRegister": 2,
    "studentAccepted": 1,
    "maxRegister": 6,
    "maxAcceptedStudent": 2,
    "timestamp": 1748900896
  },
  {
    "studentRegister": 2,
    "studentAccepted": 1,
    "maxRegister": 6,
    "maxAcceptedStudent": 2,
    "timestamp": 1748901297
  },
  {
    "studentRegister": 2,
    "studentAccepted": 1,
    "maxRegister": 6,
    "maxAcceptedStudent": 2,
    "timestamp": 1748901690
  },
  {
    "studentRegister": 2,
    "studentAccepted": 1,
    "maxRegister": 6,
    "maxAcceptedStudent": 2,
    "timestamp": 1748902809
  },
  {
    "studentRegister": 2,
    "studentAccepted": 1,
    "maxRegister": 6,
    "maxAcceptedStudent": 2,
    "timestamp": 1748903950
  },
  {
    "studentRegister": 2,
    "studentAccepted": 1,
    "maxRegister": 6,
    "maxAcceptedStudent": 2,
    "timestamp": 1748904585
  },
  {
    "studentRegister": 2,
    "studentAccepted": 1,
    "maxRegister": 6,
    "maxAcceptedStudent": 2,
    "timestamp": 1748905001
  },
  {
    "studentRegister": 2,
    "studentAccepted": 1,
    "maxRegister": 6,
    "maxAcceptedStudent": 2,
    "timestamp": 1748905396
  },
  {
    "studentRegister": 2,
    "studentAccepted": 1,
    "maxRegister": 6,
    "maxAcceptedStudent": 2,
    "timestamp": 1748906639
  },
  {
    "studentRegister": 2,
    "studentAccepted": 1,
    "maxRegister": 6,
    "maxAcceptedStudent": 2,
    "timestamp": 1748907496
  },
  {
    "studentRegister": 2,
    "studentAccepted": 1,
    "maxRegister": 6,
    "maxAcceptedStudent": 2,
    "timestamp": 1748908116
  },
  {
    "studentRegister": 2,
    "studentAccepted": 1,
    "maxRegister": 6,
    "maxAcceptedStudent": 2,
    "timestamp": 1748908506
  },
  {
    "studentRegister": 2,
    "studentAccepted": 1,
    "maxRegister": 6,
    "maxAcceptedStudent": 2,
    "timestamp": 1748908916
  },
  {
    "studentRegister": 1,
    "studentAccepted": 1,
    "maxRegister": 6,
    "maxAcceptedStudent": 2,
    "timestamp": 1748914276
  },
  {
    "studentRegister": 1,
    "studentAccepted": 1,
    "maxRegister": 6,
    "maxAcceptedStudent": 2,
    "timestamp": 1748919957
  },
  {
    "studentRegister": 1,
    "studentAccepted": 1,
    "maxRegister": 6,
    "maxAcceptedStudent": 2,
    "timestamp": 1748922824
  },
  {
    "studentRegister": 1,
    "studentAccepted": 1,
    "maxRegister": 6,
    "maxAcceptedStudent": 2,
    "timestamp": 1748924293
  },
  {
    "studentRegister": 1,
    "studentAccepted": 1,
    "maxRegister": 6,
    "maxAcceptedStudent": 2,
    "timestamp": 1748925939
  },
  {
    "studentRegister": 1,
    "studentAccepted": 1,
    "maxRegister": 6,
    "maxAcceptedStudent": 2,
    "timestamp": 1748926642
  },
  {
    "studentRegister": 1,
    "studentAccepted": 1,
    "maxRegister": 6,
    "maxAcceptedStudent": 2,
    "timestamp": 1748927591
  },
  {
    "studentRegister": 1,
    "studentAccepted": 1,
    "maxRegister": 6,
    "maxAcceptedStudent": 2,
    "timestamp": 1748928982
  },
  {
    "studentRegister": 1,
    "studentAccepted": 1,
    "maxRegister": 6,
    "maxAcceptedStudent": 2,
    "timestamp": 1748929761
  },
  {
    "studentRegister": 1,
    "studentAccepted": 1,
    "maxRegister": 6,
    "maxAcceptedStudent": 2,
    "timestamp": 1748930166
  },
  {
    "studentRegister": 1,
    "studentAccepted": 1,
    "maxRegister": 6,
    "maxAcceptedStudent": 2,
    "timestamp": 1748930561
  },
  {
    "studentRegister": 1,
    "studentAccepted": 1,
    "maxRegister": 6,
    "maxAcceptedStudent": 2,
    "timestamp": 1748932498
  },
  {
    "studentRegister": 1,
    "studentAccepted": 1,
    "maxRegister": 6,
    "maxAcceptedStudent": 2,
    "timestamp": 1748933823
  },
  {
    "studentRegister": 1,
    "studentAccepted": 1,
    "maxRegister": 6,
    "maxAcceptedStudent": 2,
    "timestamp": 1748934240
  },
  {
    "studentRegister": 1,
    "studentAccepted": 1,
    "maxRegister": 6,
    "maxAcceptedStudent": 2,
    "timestamp": 1748935668
  },
  {
    "studentRegister": 1,
    "studentAccepted": 1,
    "maxRegister": 6,
    "maxAcceptedStudent": 2,
    "timestamp": 1748936483
  },
  {
    "studentRegister": 1,
    "studentAccepted": 1,
    "maxRegister": 6,
    "maxAcceptedStudent": 2,
    "timestamp": 1748936959
  },
  {
    "studentRegister": 1,
    "studentAccepted": 1,
    "maxRegister": 6,
    "maxAcceptedStudent": 2,
    "timestamp": 1748937370
  },
  {
    "studentRegister": 1,
    "studentAccepted": 1,
    "maxRegister": 6,
    "maxAcceptedStudent": 2,
    "timestamp": 1748937749
  },
  {
    "studentRegister": 1,
    "studentAccepted": 1,
    "maxRegister": 6,
    "maxAcceptedStudent": 2,
    "timestamp": 1748939511
  },
  {
    "studentRegister": 1,
    "studentAccepted": 1,
    "maxRegister": 6,
    "maxAcceptedStudent": 2,
    "timestamp": 1748940784
  },
  {
    "studentRegister": 1,
    "studentAccepted": 1,
    "maxRegister": 6,
    "maxAcceptedStudent": 2,
    "timestamp": 1748941392
  },
  {
    "studentRegister": 2,
    "studentAccepted": 1,
    "maxRegister": 6,
    "maxAcceptedStudent": 2,
    "timestamp": 1748942835
  },
  {
    "studentRegister": 1,
    "studentAccepted": 1,
    "maxRegister": 6,
    "maxAcceptedStudent": 2,
    "timestamp": 1748943763
  },
  {
    "studentRegister": 1,
    "studentAccepted": 1,
    "maxRegister": 6,
    "maxAcceptedStudent": 2,
    "timestamp": 1748944370
  },
  {
    "studentRegister": 1,
    "studentAccepted": 1,
    "maxRegister": 6,
    "maxAcceptedStudent": 2,
    "timestamp": 1748944766
  },
  {
    "studentRegister": 1,
    "studentAccepted": 1,
    "maxRegister": 6,
    "maxAcceptedStudent": 2,
    "timestamp": 1748945855
  },
  {
    "studentRegister": 1,
    "studentAccepted": 1,
    "maxRegister": 6,
    "maxAcceptedStudent": 2,
    "timestamp": 1748947367
  },
  {
    "studentRegister": 1,
    "studentAccepted": 1,
    "maxRegister": 6,
    "maxAcceptedStudent": 2,
    "timestamp": 1748948100
  },
  {
    "studentRegister": 1,
    "studentAccepted": 1,
    "maxRegister": 6,
    "maxAcceptedStudent": 2,
    "timestamp": 1748948498
  },
  {
    "studentRegister": 1,
    "studentAccepted": 1,
    "maxRegister": 6,
    "maxAcceptedStudent": 2,
    "timestamp": 1748949548
  },
  {
    "studentRegister": 1,
    "studentAccepted": 1,
    "maxRegister": 6,
    "maxAcceptedStudent": 2,
    "timestamp": 1748950354
  },
  {
    "studentRegister": 1,
    "studentAccepted": 1,
    "maxRegister": 6,
    "maxAcceptedStudent": 2,
    "timestamp": 1748950928
  },
  {
    "studentRegister": 1,
    "studentAccepted": 1,
    "maxRegister": 6,
    "maxAcceptedStudent": 2,
    "timestamp": 1748951342
  },
  {
    "studentRegister": 1,
    "studentAccepted": 1,
    "maxRegister": 6,
    "maxAcceptedStudent": 2,
    "timestamp": 1748951736
  },
  {
    "studentRegister": 1,
    "studentAccepted": 1,
    "maxRegister": 6,
    "maxAcceptedStudent": 2,
    "timestamp": 1748952140
  },
  {
    "studentRegister": 1,
    "studentAccepted": 1,
    "maxRegister": 6,
    "maxAcceptedStudent": 2,
    "timestamp": 1748954633
  },
  {
    "studentRegister": 1,
    "studentAccepted": 1,
    "maxRegister": 6,
    "maxAcceptedStudent": 2,
    "timestamp": 1748957013
  },
  {
    "studentRegister": 1,
    "studentAccepted": 1,
    "maxRegister": 6,
    "maxAcceptedStudent": 2,
    "timestamp": 1748958606
  },
  {
    "studentRegister": 1,
    "studentAccepted": 1,
    "maxRegister": 6,
    "maxAcceptedStudent": 2,
    "timestamp": 1748959213
  },
  {
    "studentRegister": 1,
    "studentAccepted": 1,
    "maxRegister": 6,
    "maxAcceptedStudent": 2,
    "timestamp": 1748960306
  },
  {
    "studentRegister": 1,
    "studentAccepted": 1,
    "maxRegister": 6,
    "maxAcceptedStudent": 2,
    "timestamp": 1748961767
  },
  {
    "studentRegister": 1,
    "studentAccepted": 1,
    "maxRegister": 6,
    "maxAcceptedStudent": 2,
    "timestamp": 1748962588
  },
  {
    "studentRegister": 1,
    "studentAccepted": 1,
    "maxRegister": 6,
    "maxAcceptedStudent": 2,
    "timestamp": 1748962980
  },
  {
    "studentRegister": 1,
    "studentAccepted": 1,
    "maxRegister": 6,
    "maxAcceptedStudent": 2,
    "timestamp": 1748964452
  },
  {
    "studentRegister": 1,
    "studentAccepted": 1,
    "maxRegister": 6,
    "maxAcceptedStudent": 2,
    "timestamp": 1748965490
  },
  {
    "studentRegister": 1,
    "studentAccepted": 1,
    "maxRegister": 6,
    "maxAcceptedStudent": 2,
    "timestamp": 1748966114
  },
  {
    "studentRegister": 1,
    "studentAccepted": 1,
    "maxRegister": 6,
    "maxAcceptedStudent": 2,
    "timestamp": 1748966502
  },
  {
    "studentRegister": 1,
    "studentAccepted": 1,
    "maxRegister": 6,
    "maxAcceptedStudent": 2,
    "timestamp": 1748968086
  },
  {
    "studentRegister": 1,
    "studentAccepted": 1,
    "maxRegister": 6,
    "maxAcceptedStudent": 2,
    "timestamp": 1748969491
  },
  {
    "studentRegister": 1,
    "studentAccepted": 1,
    "maxRegister": 6,
    "maxAcceptedStudent": 2,
    "timestamp": 1748970178
  },
  {
    "studentRegister": 1,
    "studentAccepted": 1,
    "maxRegister": 6,
    "maxAcceptedStudent": 2,
    "timestamp": 1748971387
  },
  {
    "studentRegister": 1,
    "studentAccepted": 1,
    "maxRegister": 6,
    "maxAcceptedStudent": 2,
    "timestamp": 1748972480
  },
  {
    "studentRegister": 1,
    "studentAccepted": 1,
    "maxRegister": 6,
    "maxAcceptedStudent": 2,
    "timestamp": 1748973012
  },
  {
    "studentRegister": 1,
    "studentAccepted": 1,
    "maxRegister": 6,
    "maxAcceptedStudent": 2,
    "timestamp": 1748973421
  },
  {
    "studentRegister": 1,
    "studentAccepted": 1,
    "maxRegister": 6,
    "maxAcceptedStudent": 2,
    "timestamp": 1748973817
  },
  {
    "studentRegister": 1,
    "studentAccepted": 1,
    "maxRegister": 6,
    "maxAcceptedStudent": 2,
    "timestamp": 1748975744
  },
  {
    "studentRegister": 1,
    "studentAccepted": 1,
    "maxRegister": 6,
    "maxAcceptedStudent": 2,
    "timestamp": 1748976923
  },
  {
    "studentRegister": 1,
    "studentAccepted": 1,
    "maxRegister": 6,
    "maxAcceptedStudent": 2,
    "timestamp": 1748977378
  },
  {
    "studentRegister": 1,
    "studentAccepted": 1,
    "maxRegister": 6,
    "maxAcceptedStudent": 2,
    "timestamp": 1748978389
  },
  {
    "studentRegister": 1,
    "studentAccepted": 1,
    "maxRegister": 6,
    "maxAcceptedStudent": 2,
    "timestamp": 1748979061
  },
  {
    "studentRegister": 1,
    "studentAccepted": 1,
    "maxRegister": 6,
    "maxAcceptedStudent": 2,
    "timestamp": 1748979589
  },
  {
    "studentRegister": 1,
    "studentAccepted": 1,
    "maxRegister": 6,
    "maxAcceptedStudent": 2,
    "timestamp": 1748979962
  },
  {
    "studentRegister": 1,
    "studentAccepted": 1,
    "maxRegister": 6,
    "maxAcceptedStudent": 2,
    "timestamp": 1748980385
  },
  {
    "studentRegister": 1,
    "studentAccepted": 1,
    "maxRegister": 6,
    "maxAcceptedStudent": 2,
    "timestamp": 1748980786
  },
  {
    "studentRegister": 1,
    "studentAccepted": 1,
    "maxRegister": 6,
    "maxAcceptedStudent": 2,
    "timestamp": 1748981924
  },
  {
    "studentRegister": 1,
    "studentAccepted": 1,
    "maxRegister": 6,
    "maxAcceptedStudent": 2,
    "timestamp": 1748983084
  },
  {
    "studentRegister": 1,
    "studentAccepted": 1,
    "maxRegister": 6,
    "maxAcceptedStudent": 2,
    "timestamp": 1748983718
  },
  {
    "studentRegister": 1,
    "studentAccepted": 1,
    "maxRegister": 6,
    "maxAcceptedStudent": 2,
    "timestamp": 1748984107
  },
  {
    "studentRegister": 1,
    "studentAccepted": 1,
    "maxRegister": 6,
    "maxAcceptedStudent": 2,
    "timestamp": 1748984511
  },
  {
    "studentRegister": 1,
    "studentAccepted": 1,
    "maxRegister": 6,
    "maxAcceptedStudent": 2,
    "timestamp": 1748985537
  },
  {
    "studentRegister": 1,
    "studentAccepted": 1,
    "maxRegister": 6,
    "maxAcceptedStudent": 2,
    "timestamp": 1748986406
  },
  {
    "studentRegister": 1,
    "studentAccepted": 1,
    "maxRegister": 6,
    "maxAcceptedStudent": 2,
    "timestamp": 1748986986
  },
  {
    "studentRegister": 1,
    "studentAccepted": 1,
    "maxRegister": 6,
    "maxAcceptedStudent": 2,
    "timestamp": 1748987387
  },
  {
    "studentRegister": 1,
    "studentAccepted": 1,
    "maxRegister": 6,
    "maxAcceptedStudent": 2,
    "timestamp": 1748987798
  },
  {
    "studentRegister": 1,
    "studentAccepted": 1,
    "maxRegister": 6,
    "maxAcceptedStudent": 2,
    "timestamp": 1748988182
  },
  {
    "studentRegister": 1,
    "studentAccepted": 1,
    "maxRegister": 6,
    "maxAcceptedStudent": 2,
    "timestamp": 1748989427
  },
  {
    "studentRegister": 1,
    "studentAccepted": 1,
    "maxRegister": 6,
    "maxAcceptedStudent": 2,
    "timestamp": 1748990553
  },
  {
    "studentRegister": 1,
    "studentAccepted": 1,
    "maxRegister": 6,
    "maxAcceptedStudent": 2,
    "timestamp": 1748991101
  },
  {
    "studentRegister": 1,
    "studentAccepted": 1,
    "maxRegister": 6,
    "maxAcceptedStudent": 2,
    "timestamp": 1748991495
  },
  {
    "studentRegister": 1,
    "studentAccepted": 1,
    "maxRegister": 6,
    "maxAcceptedStudent": 2,
    "timestamp": 1748992371
  },
  {
    "studentRegister": 1,
    "studentAccepted": 1,
    "maxRegister": 6,
    "maxAcceptedStudent": 2,
    "timestamp": 1748993483
  },
  {
    "studentRegister": 1,
    "studentAccepted": 1,
    "maxRegister": 6,
    "maxAcceptedStudent": 2,
    "timestamp": 1748994118
  },
  {
    "studentRegister": 1,
    "studentAccepted": 1,
    "maxRegister": 6,
    "maxAcceptedStudent": 2,
    "timestamp": 1748994540
  },
  {
    "studentRegister": 1,
    "studentAccepted": 1,
    "maxRegister": 6,
    "maxAcceptedStudent": 2,
    "timestamp": 1748994962
  },
  {
    "studentRegister": 1,
    "studentAccepted": 1,
    "maxRegister": 6,
    "maxAcceptedStudent": 2,
    "timestamp": 1748995367
  },
  {
    "studentRegister": 1,
    "studentAccepted": 1,
    "maxRegister": 6,
    "maxAcceptedStudent": 2,
    "timestamp": 1749001657
  },
  {
    "studentRegister": 1,
    "studentAccepted": 1,
    "maxRegister": 6,
    "maxAcceptedStudent": 2,
    "timestamp": 1749006734
  },
  {
    "studentRegister": 1,
    "studentAccepted": 1,
    "maxRegister": 6,
    "maxAcceptedStudent": 2,
    "timestamp": 1749009377
  },
  {
    "studentRegister": 1,
    "studentAccepted": 1,
    "maxRegister": 6,
    "maxAcceptedStudent": 2,
    "timestamp": 1749010723
  },
  {
    "studentRegister": 1,
    "studentAccepted": 1,
    "maxRegister": 6,
    "maxAcceptedStudent": 2,
    "timestamp": 1749012360
  },
  {
    "studentRegister": 1,
    "studentAccepted": 1,
    "maxRegister": 6,
    "maxAcceptedStudent": 2,
    "timestamp": 1749013076
  },
  {
    "studentRegister": 1,
    "studentAccepted": 1,
    "maxRegister": 6,
    "maxAcceptedStudent": 2,
    "timestamp": 1749014041
  },
  {
    "studentRegister": 1,
    "studentAccepted": 1,
    "maxRegister": 6,
    "maxAcceptedStudent": 2,
    "timestamp": 1749015398
  },
  {
    "studentRegister": 1,
    "studentAccepted": 1,
    "maxRegister": 6,
    "maxAcceptedStudent": 2,
    "timestamp": 1749016186
  },
  {
    "studentRegister": 1,
    "studentAccepted": 1,
    "maxRegister": 6,
    "maxAcceptedStudent": 2,
    "timestamp": 1749016591
  },
  {
    "studentRegister": 1,
    "studentAccepted": 1,
    "maxRegister": 6,
    "maxAcceptedStudent": 2,
    "timestamp": 1749017014
  },
  {
    "studentRegister": 1,
    "studentAccepted": 1,
    "maxRegister": 6,
    "maxAcceptedStudent": 2,
    "timestamp": 1749018932
  },
  {
    "studentRegister": 1,
    "studentAccepted": 1,
    "maxRegister": 6,
    "maxAcceptedStudent": 2,
    "timestamp": 1749020146
  },
  {
    "studentRegister": 1,
    "studentAccepted": 1,
    "maxRegister": 6,
    "maxAcceptedStudent": 2,
    "timestamp": 1749020555
  },
  {
    "studentRegister": 1,
    "studentAccepted": 1,
    "maxRegister": 6,
    "maxAcceptedStudent": 2,
    "timestamp": 1749021795
  },
  {
    "studentRegister": 1,
    "studentAccepted": 1,
    "maxRegister": 6,
    "maxAcceptedStudent": 2,
    "timestamp": 1749022619
  },
  {
    "studentRegister": 1,
    "studentAccepted": 1,
    "maxRegister": 6,
    "maxAcceptedStudent": 2,
    "timestamp": 1749023253
  },
  {
    "studentRegister": 1,
    "studentAccepted": 1,
    "maxRegister": 6,
    "maxAcceptedStudent": 2,
    "timestamp": 1749023669
  },
  {
    "studentRegister": 1,
    "studentAccepted": 1,
    "maxRegister": 6,
    "maxAcceptedStudent": 2,
    "timestamp": 1749024078
  },
  {
    "studentRegister": 1,
    "studentAccepted": 1,
    "maxRegister": 6,
    "maxAcceptedStudent": 2,
    "timestamp": 1749025618
  },
  {
    "studentRegister": 1,
    "studentAccepted": 1,
    "maxRegister": 6,
    "maxAcceptedStudent": 2,
    "timestamp": 1749026927
  },
  {
    "studentRegister": 1,
    "studentAccepted": 1,
    "maxRegister": 6,
    "maxAcceptedStudent": 2,
    "timestamp": 1749027676
  },
  {
    "studentRegister": 1,
    "studentAccepted": 1,
    "maxRegister": 6,
    "maxAcceptedStudent": 2,
    "timestamp": 1749028898
  },
  {
    "studentRegister": 1,
    "studentAccepted": 1,
    "maxRegister": 6,
    "maxAcceptedStudent": 2,
    "timestamp": 1749030012
  },
  {
    "studentRegister": 1,
    "studentAccepted": 1,
    "maxRegister": 6,
    "maxAcceptedStudent": 2,
    "timestamp": 1749030640
  },
  {
    "studentRegister": 1,
    "studentAccepted": 1,
    "maxRegister": 6,
    "maxAcceptedStudent": 2,
    "timestamp": 1749031045
  },
  {
    "studentRegister": 1,
    "studentAccepted": 1,
    "maxRegister": 6,
    "maxAcceptedStudent": 2,
    "timestamp": 1749031974
  },
  {
    "studentRegister": 1,
    "studentAccepted": 1,
    "maxRegister": 6,
    "maxAcceptedStudent": 2,
    "timestamp": 1749033577
  },
  {
    "studentRegister": 1,
    "studentAccepted": 1,
    "maxRegister": 6,
    "maxAcceptedStudent": 2,
    "timestamp": 1749034409
  },
  {
    "studentRegister": 1,
    "studentAccepted": 1,
    "maxRegister": 6,
    "maxAcceptedStudent": 2,
    "timestamp": 1749034813
  },
  {
    "studentRegister": 1,
    "studentAccepted": 1,
    "maxRegister": 6,
    "maxAcceptedStudent": 2,
    "timestamp": 1749035772
  },
  {
    "studentRegister": 1,
    "studentAccepted": 1,
    "maxRegister": 6,
    "maxAcceptedStudent": 2,
    "timestamp": 1749036704
  },
  {
    "studentRegister": 1,
    "studentAccepted": 1,
    "maxRegister": 6,
    "maxAcceptedStudent": 2,
    "timestamp": 1749037324
  },
  {
    "studentRegister": 1,
    "studentAccepted": 1,
    "maxRegister": 6,
    "maxAcceptedStudent": 2,
    "timestamp": 1749037731
  },
  {
    "studentRegister": 1,
    "studentAccepted": 1,
    "maxRegister": 6,
    "maxAcceptedStudent": 2,
    "timestamp": 1749038142
  },
  {
    "studentRegister": 1,
    "studentAccepted": 1,
    "maxRegister": 6,
    "maxAcceptedStudent": 2,
    "timestamp": 1749038541
  },
  {
    "studentRegister": 1,
    "studentAccepted": 1,
    "maxRegister": 6,
    "maxAcceptedStudent": 2,
    "timestamp": 1749041044
  },
  {
    "studentRegister": 1,
    "studentAccepted": 1,
    "maxRegister": 6,
    "maxAcceptedStudent": 2,
    "timestamp": 1749043474
  },
  {
    "studentRegister": 1,
    "studentAccepted": 1,
    "maxRegister": 6,
    "maxAcceptedStudent": 2,
    "timestamp": 1749045080
  },
  {
    "studentRegister": 1,
    "studentAccepted": 1,
    "maxRegister": 6,
    "maxAcceptedStudent": 2,
    "timestamp": 1749045593
  },
  {
    "studentRegister": 1,
    "studentAccepted": 1,
    "maxRegister": 6,
    "maxAcceptedStudent": 2,
    "timestamp": 1749046527
  },
  {
    "studentRegister": 1,
    "studentAccepted": 1,
    "maxRegister": 6,
    "maxAcceptedStudent": 2,
    "timestamp": 1749048709
  },
  {
    "studentRegister": 1,
    "studentAccepted": 1,
    "maxRegister": 6,
    "maxAcceptedStudent": 2,
    "timestamp": 1749051339
  },
  {
    "studentRegister": 1,
    "studentAccepted": 1,
    "maxRegister": 6,
    "maxAcceptedStudent": 2,
    "timestamp": 1749052848
  },
  {
    "studentRegister": 1,
    "studentAccepted": 1,
    "maxRegister": 6,
    "maxAcceptedStudent": 2,
    "timestamp": 1749054071
  },
  {
    "studentRegister": 1,
    "studentAccepted": 1,
    "maxRegister": 6,
    "maxAcceptedStudent": 2,
    "timestamp": 1749055455
  },
  {
    "studentRegister": 1,
    "studentAccepted": 1,
    "maxRegister": 6,
    "maxAcceptedStudent": 2,
    "timestamp": 1749056202
  },
  {
    "studentRegister": 1,
    "studentAccepted": 1,
    "maxRegister": 6,
    "maxAcceptedStudent": 2,
    "timestamp": 1749056608
  },
  {
    "studentRegister": 1,
    "studentAccepted": 1,
    "maxRegister": 6,
    "maxAcceptedStudent": 2,
    "timestamp": 1749057820
  },
  {
    "studentRegister": 1,
    "studentAccepted": 1,
    "maxRegister": 6,
    "maxAcceptedStudent": 2,
    "timestamp": 1749058874
  },
  {
    "studentRegister": 1,
    "studentAccepted": 1,
    "maxRegister": 6,
    "maxAcceptedStudent": 2,
    "timestamp": 1749059408
  },
  {
    "studentRegister": 1,
    "studentAccepted": 1,
    "maxRegister": 6,
    "maxAcceptedStudent": 2,
    "timestamp": 1749059781
  },
  {
    "studentRegister": 1,
    "studentAccepted": 1,
    "maxRegister": 6,
    "maxAcceptedStudent": 2,
    "timestamp": 1749060186
  },
  {
    "studentRegister": 1,
    "studentAccepted": 1,
    "maxRegister": 6,
    "maxAcceptedStudent": 2,
    "timestamp": 1749061980
  },
  {
    "studentRegister": 1,
    "studentAccepted": 1,
    "maxRegister": 6,
    "maxAcceptedStudent": 2,
    "timestamp": 1749063218
  },
  {
    "studentRegister": 1,
    "studentAccepted": 1,
    "maxRegister": 6,
    "maxAcceptedStudent": 2,
    "timestamp": 1749063706
  },
  {
    "studentRegister": 1,
    "studentAccepted": 1,
    "maxRegister": 6,
    "maxAcceptedStudent": 2,
    "timestamp": 1749064683
  },
  {
    "studentRegister": 1,
    "studentAccepted": 1,
    "maxRegister": 6,
    "maxAcceptedStudent": 2,
    "timestamp": 1749065349
  },
  {
    "studentRegister": 1,
    "studentAccepted": 1,
    "maxRegister": 6,
    "maxAcceptedStudent": 2,
    "timestamp": 1749065798
  },
  {
    "studentRegister": 1,
    "studentAccepted": 1,
    "maxRegister": 6,
    "maxAcceptedStudent": 2,
    "timestamp": 1749066191
  },
  {
    "studentRegister": 1,
    "studentAccepted": 1,
    "maxRegister": 6,
    "maxAcceptedStudent": 2,
    "timestamp": 1749066586
  },
  {
    "studentRegister": 1,
    "studentAccepted": 1,
    "maxRegister": 6,
    "maxAcceptedStudent": 2,
    "timestamp": 1749066995
  },
  {
    "studentRegister": 1,
    "studentAccepted": 1,
    "maxRegister": 6,
    "maxAcceptedStudent": 2,
    "timestamp": 1749067386
  },
  {
    "studentRegister": 1,
    "studentAccepted": 1,
    "maxRegister": 6,
    "maxAcceptedStudent": 2,
    "timestamp": 1749068522
  },
  {
    "studentRegister": 1,
    "studentAccepted": 1,
    "maxRegister": 6,
    "maxAcceptedStudent": 2,
    "timestamp": 1749069200
  },
  {
    "studentRegister": 1,
    "studentAccepted": 1,
    "maxRegister": 6,
    "maxAcceptedStudent": 2,
    "timestamp": 1749069755
  },
  {
    "studentRegister": 1,
    "studentAccepted": 1,
    "maxRegister": 6,
    "maxAcceptedStudent": 2,
    "timestamp": 1749070136
  },
  {
    "studentRegister": 1,
    "studentAccepted": 1,
    "maxRegister": 6,
    "maxAcceptedStudent": 2,
    "timestamp": 1749070544
  },
  {
    "studentRegister": 1,
    "studentAccepted": 1,
    "maxRegister": 6,
    "maxAcceptedStudent": 2,
    "timestamp": 1749070931
  },
  {
    "studentRegister": 1,
    "studentAccepted": 1,
    "maxRegister": 6,
    "maxAcceptedStudent": 2,
    "timestamp": 1749071896
  },
  {
    "studentRegister": 1,
    "studentAccepted": 1,
    "maxRegister": 6,
    "maxAcceptedStudent": 2,
    "timestamp": 1749072556
  },
  {
    "studentRegister": 1,
    "studentAccepted": 1,
    "maxRegister": 6,
    "maxAcceptedStudent": 2,
    "timestamp": 1749072996
  },
  {
    "studentRegister": 1,
    "studentAccepted": 1,
    "maxRegister": 6,
    "maxAcceptedStudent": 2,
    "timestamp": 1749073403
  },
  {
    "studentRegister": 1,
    "studentAccepted": 1,
    "maxRegister": 6,
    "maxAcceptedStudent": 2,
    "timestamp": 1749073809
  }
]