[
  {
    "studentRegister": 0,
    "studentAccepted": 0,
    "maxRegister": 1,
    "maxAcceptedStudent": 1,
    "timestamp": 1748864843
  },
  {
    "studentRegister": 0,
    "studentAccepted": 0,
    "maxRegister": 1,
    "maxAcceptedStudent": 1,
    "timestamp": 1748865257
  },
  {
    "studentRegister": 0,
    "studentAccepted": 0,
    "maxRegister": 1,
    "maxAcceptedStudent": 1,
    "timestamp": 1748865665
  },
  {
    "studentRegister": 0,
    "studentAccepted": 0,
    "maxRegister": 1,
    "maxAcceptedStudent": 1,
    "timestamp": 1748867797
  },
  {
    "studentRegister": 0,
    "studentAccepted": 0,
    "maxRegister": 1,
    "maxAcceptedStudent": 1,
    "timestamp": 1748869990
  },
  {
    "studentRegister": 0,
    "studentAccepted": 0,
    "maxRegister": 1,
    "maxAcceptedStudent": 1,
    "timestamp": 1748871892
  },
  {
    "studentRegister": 0,
    "studentAccepted": 0,
    "maxRegister": 1,
    "maxAcceptedStudent": 1,
    "timestamp": 1748872568
  },
  {
    "studentRegister": 0,
    "studentAccepted": 0,
    "maxRegister": 1,
    "maxAcceptedStudent": 1,
    "timestamp": 1748872961
  },
  {
    "studentRegister": 1,
    "studentAccepted": 0,
    "maxRegister": 1,
    "maxAcceptedStudent": 1,
    "timestamp": 1748874220
  },
  {
    "studentRegister": 1,
    "studentAccepted": 0,
    "maxRegister": 1,
    "maxAcceptedStudent": 1,
    "timestamp": 1748875529
  },
  {
    "studentRegister": 1,
    "studentAccepted": 0,
    "maxRegister": 1,
    "maxAcceptedStudent": 1,
    "timestamp": 1748876170
  },
  {
    "studentRegister": 1,
    "studentAccepted": 0,
    "maxRegister": 1,
    "maxAcceptedStudent": 1,
    "timestamp": 1748876566
  },
  {
    "studentRegister": 1,
    "studentAccepted": 0,
    "maxRegister": 1,
    "maxAcceptedStudent": 1,
    "timestamp": 1748877910
  },
  {
    "studentRegister": 1,
    "studentAccepted": 0,
    "maxRegister": 1,
    "maxAcceptedStudent": 1,
    "timestamp": 1748878986
  },
  {
    "studentRegister": 1,
    "studentAccepted": 0,
    "maxRegister": 1,
    "maxAcceptedStudent": 1,
    "timestamp": 1748879591
  },
  {
    "studentRegister": 1,
    "studentAccepted": 0,
    "maxRegister": 1,
    "maxAcceptedStudent": 1,
    "timestamp": 1748879999
  },
  {
    "studentRegister": 1,
    "studentAccepted": 0,
    "maxRegister": 1,
    "maxAcceptedStudent": 1,
    "timestamp": 1748881232
  },
  {
    "studentRegister": 1,
    "studentAccepted": 0,
    "maxRegister": 1,
    "maxAcceptedStudent": 1,
    "timestamp": 1748882947
  },
  {
    "studentRegister": 1,
    "studentAccepted": 0,
    "maxRegister": 1,
    "maxAcceptedStudent": 1,
    "timestamp": 1748883739
  },
  {
    "studentRegister": 1,
    "studentAccepted": 0,
    "maxRegister": 1,
    "maxAcceptedStudent": 1,
    "timestamp": 1748884861
  },
  {
    "studentRegister": 1,
    "studentAccepted": 0,
    "maxRegister": 1,
    "maxAcceptedStudent": 1,
    "timestamp": 1748885907
  },
  {
    "studentRegister": 1,
    "studentAccepted": 0,
    "maxRegister": 1,
    "maxAcceptedStudent": 1,
    "timestamp": 1748886572
  },
  {
    "studentRegister": 1,
    "studentAccepted": 0,
    "maxRegister": 1,
    "maxAcceptedStudent": 1,
    "timestamp": 1748886978
  },
  {
    "studentRegister": 1,
    "studentAccepted": 0,
    "maxRegister": 1,
    "maxAcceptedStudent": 1,
    "timestamp": 1748887372
  },
  {
    "studentRegister": 1,
    "studentAccepted": 0,
    "maxRegister": 1,
    "maxAcceptedStudent": 1,
    "timestamp": 1748889121
  },
  {
    "studentRegister": 1,
    "studentAccepted": 0,
    "maxRegister": 1,
    "maxAcceptedStudent": 1,
    "timestamp": 1748890414
  },
  {
    "studentRegister": 1,
    "studentAccepted": 0,
    "maxRegister": 1,
    "maxAcceptedStudent": 1,
    "timestamp": 1748890900
  },
  {
    "studentRegister": 1,
    "studentAccepted": 0,
    "maxRegister": 1,
    "maxAcceptedStudent": 1,
    "timestamp": 1748891810
  },
  {
    "studentRegister": 1,
    "studentAccepted": 0,
    "maxRegister": 1,
    "maxAcceptedStudent": 1,
    "timestamp": 1748892572
  },
  {
    "studentRegister": 1,
    "studentAccepted": 0,
    "maxRegister": 1,
    "maxAcceptedStudent": 1,
    "timestamp": 1748893054
  },
  {
    "studentRegister": 1,
    "studentAccepted": 0,
    "maxRegister": 1,
    "maxAcceptedStudent": 1,
    "timestamp": 1748893469
  },
  {
    "studentRegister": 1,
    "studentAccepted": 0,
    "maxRegister": 1,
    "maxAcceptedStudent": 1,
    "timestamp": 1748893888
  },
  {
    "studentRegister": 1,
    "studentAccepted": 0,
    "maxRegister": 1,
    "maxAcceptedStudent": 1,
    "timestamp": 1748894271
  },
  {
    "studentRegister": 1,
    "studentAccepted": 0,
    "maxRegister": 1,
    "maxAcceptedStudent": 1,
    "timestamp": 1748895213
  },
  {
    "studentRegister": 1,
    "studentAccepted": 0,
    "maxRegister": 1,
    "maxAcceptedStudent": 1,
    "timestamp": 1748896524
  },
  {
    "studentRegister": 1,
    "studentAccepted": 0,
    "maxRegister": 1,
    "maxAcceptedStudent": 1,
    "timestamp": 1748897284
  },
  {
    "studentRegister": 1,
    "studentAccepted": 0,
    "maxRegister": 1,
    "maxAcceptedStudent": 1,
    "timestamp": 1748897750
  },
  {
    "studentRegister": 1,
    "studentAccepted": 0,
    "maxRegister": 1,
    "maxAcceptedStudent": 1,
    "timestamp": 1748898141
  },
  {
    "studentRegister": 1,
    "studentAccepted": 0,
    "maxRegister": 1,
    "maxAcceptedStudent": 1,
    "timestamp": 1748899331
  },
  {
    "studentRegister": 1,
    "studentAccepted": 0,
    "maxRegister": 1,
    "maxAcceptedStudent": 1,
    "timestamp": 1748900287
  },
  {
    "studentRegister": 1,
    "studentAccepted": 0,
    "maxRegister": 1,
    "maxAcceptedStudent": 1,
    "timestamp": 1748900921
  },
  {
    "studentRegister": 1,
    "studentAccepted": 0,
    "maxRegister": 1,
    "maxAcceptedStudent": 1,
    "timestamp": 1748901323
  },
  {
    "studentRegister": 1,
    "studentAccepted": 0,
    "maxRegister": 1,
    "maxAcceptedStudent": 1,
    "timestamp": 1748901716
  },
  {
    "studentRegister": 1,
    "studentAccepted": 0,
    "maxRegister": 1,
    "maxAcceptedStudent": 1,
    "timestamp": 1748902835
  },
  {
    "studentRegister": 1,
    "studentAccepted": 0,
    "maxRegister": 1,
    "maxAcceptedStudent": 1,
    "timestamp": 1748903976
  },
  {
    "studentRegister": 1,
    "studentAccepted": 0,
    "maxRegister": 1,
    "maxAcceptedStudent": 1,
    "timestamp": 1748904611
  },
  {
    "studentRegister": 1,
    "studentAccepted": 0,
    "maxRegister": 1,
    "maxAcceptedStudent": 1,
    "timestamp": 1748905027
  },
  {
    "studentRegister": 1,
    "studentAccepted": 0,
    "maxRegister": 1,
    "maxAcceptedStudent": 1,
    "timestamp": 1748905422
  },
  {
    "studentRegister": 1,
    "studentAccepted": 0,
    "maxRegister": 1,
    "maxAcceptedStudent": 1,
    "timestamp": 1748906664
  },
  {
    "studentRegister": 1,
    "studentAccepted": 0,
    "maxRegister": 1,
    "maxAcceptedStudent": 1,
    "timestamp": 1748907523
  },
  {
    "studentRegister": 1,
    "studentAccepted": 0,
    "maxRegister": 1,
    "maxAcceptedStudent": 1,
    "timestamp": 1748908141
  }
]