[
  {
    "studentRegister": 0,
    "studentAccepted": 1,
    "maxRegister": 1,
    "maxAcceptedStudent": 1,
    "timestamp": 1783583414
  },
  {
    "studentRegister": 0,
    "studentAccepted": 1,
    "maxRegister": 1,
    "maxAcceptedStudent": 1,
    "timestamp": 1783586786
  },
  {
    "studentRegister": 0,
    "studentAccepted": 1,
    "maxRegister": 1,
    "maxAcceptedStudent": 1,
    "timestamp": 1783597061
  },
  {
    "studentRegister": 0,
    "studentAccepted": 1,
    "maxRegister": 1,
    "maxAcceptedStudent": 1,
    "timestamp": 1783606321
  },
  {
    "studentRegister": 0,
    "studentAccepted": 1,
    "maxRegister": 1,
    "maxAcceptedStudent": 1,
    "timestamp": 1783615191
  },
  {
    "studentRegister": 0,
    "studentAccepted": 1,
    "maxRegister": 1,
    "maxAcceptedStudent": 1,
    "timestamp": 1783621529
  }
]